Workbook

Sheet 产品数据源
A1: 店铺 | B1: SKU | C1: 商品名称 | D1: 型号 | E1: 价格 | F1: 一级类目 | G1: 二级类目 | H1: 客服分组 | I1: 是否新增
A2: 官旗 | B2: 72495663391 | C2: 德玛仕（DEMASHI）开水器商用 奶茶店步进式开水机饮水机 不锈钢电热烧水器机 热水箱 KW-30SA（出水量40L/H） | E2: 799 | F2: =_xlfn.XLOOKUP($G2,[1]类目转化数据!$B:$B,[1]类目转化数据!$A:$A) -> 社会餐饮设备 | G2: 商用开水器 | H2: =_xlfn.XLOOKUP(G2,[1]类目转化数据!B:B,[1]类目转化数据!C:C) -> 小客单
A3: 官旗 | B3: 10102749069015 | C3: 德玛仕（DEMASHI）步进式开水器 商用开水机奶茶店餐厅吧台全自动电热开水器商用饮水机 开水机商用 热水机烧水器 35L/h|定时开关|内置二级过滤 | E3: 1099 | F3: =_xlfn.XLOOKUP($G3,[1]类目转化数据!$B:$B,[1]类目转化数据!$A:$A) -> 社会餐饮设备 | G3: 商用开水器 | H3: =_xlfn.XLOOKUP(G3,[1]类目转化数据!B:B,[1]类目转化数据!C:C) -> 小客单
A4: 官旗 | B4: 10030089579450 | C4: 德玛仕（DEMASHI）步进式开水器 商用开水机奶茶店餐厅吧台全自动电热开水器商用饮水机 开水机商用 热水机烧水器 45L/h|可调温|冷热两用|五级过滤 | E4: 1549 | F4: =_xlfn.XLOOKUP($G4,[1]类目转化数据!$B:$B,[1]类目转化数据!$A:$A) -> 社会餐饮设备 | G4: 商用开水器 | H4: =_xlfn.XLOOKUP(G4,[1]类目转化数据!B:B,[1]类目转化数据!C:C) -> 小客单
A5: 官旗 | B5: 41485142294 | C5: 德玛仕（DEMASHI）步进式开水器 商用开水机奶茶店餐厅吧台全自动电热开水器商用饮水机 开水机商用 热水机烧水器 白钢40L/h|可调温|2分钟速热|三级过滤 | E5: 749 | F5: =_xlfn.XLOOKUP($G5,[1]类目转化数据!$B:$B,[1]类目转化数据!$A:$A) -> 社会餐饮设备 | G5: 商用开水器 | H5: =_xlfn.XLOOKUP(G5,[1]类目转化数据!B:B,[1]类目转化数据!C:C) -> 小客单
A6: 官旗 | B6: 10161576873895 | C6: 德玛仕（DEMASHI）步进式开水器 商用开水机奶茶店餐厅吧台全自动电热开水器商用饮水机 开水机商用 热水机烧水器 30L/h|机械指针|实时温度 | E6: 438 | F6: =_xlfn.XLOOKUP($G6,[1]类目转化数据!$B:$B,[1]类目转化数据!$A:$A) -> 社会餐饮设备 | G6: 商用开水器 | H6: =_xlfn.XLOOKUP(G6,[1]类目转化数据!B:B,[1]类目转化数据!C:C) -> 小客单
A7: 官旗 | B7: 10162382352383 | C7: 德玛仕（DEMASHI）步进式开水器 商用开水机奶茶店餐厅吧台全自动电热开水器商用饮水机 开水机商用 热水机烧水器 30L/h|数显款智能定时|可调温 | E7: 638 | F7: =_xlfn.XLOOKUP($G7,[1]类目转化数据!$B:$B,[1]类目转化数据!$A:$A) -> 社会餐饮设备 | G7: 商用开水器 | H7: =_xlfn.XLOOKUP(G7,[1]类目转化数据!B:B,[1]类目转化数据!C:C) -> 小客单
A8: 官旗 | B8: 10118415127029 | C8: 德玛仕（DEMASHI）步进式开水器 商用开水机奶茶店餐厅吧台全自动电热开水器商用饮水机 开水机商用 热水机烧水器 40L/h|智能定时|智能调温|加大内胆 | E8: 1399 | F8: =_xlfn.XLOOKUP($G8,[1]类目转化数据!$B:$B,[1]类目转化数据!$A:$A) -> 社会餐饮设备 | G8: 商用开水器 | H8: =_xlfn.XLOOKUP(G8,[1]类目转化数据!B:B,[1]类目转化数据!C:C) -> 小客单
A9: 官旗 | B9: 10161576873896 | C9: 德玛仕（DEMASHI）步进式开水器 商用开水机奶茶店餐厅吧台全自动电热开水器商用饮水机 开水机商用 热水机烧水器 40L/h|机械指针|实时温度 | E9: 558 | F9: =_xlfn.XLOOKUP($G9,[1]类目转化数据!$B:$B,[1]类目转化数据!$A:$A) -> 社会餐饮设备 | G9: 商用开水器 | H9: =_xlfn.XLOOKUP(G9,[1]类目转化数据!B:B,[1]类目转化数据!C:C) -> 小客单
A10: 官旗 | B10: 10162382352384 | C10: 德玛仕（DEMASHI）步进式开水器 商用开水机奶茶店餐厅吧台全自动电热开水器商用饮水机 开水机商用 热水机烧水器 40L/h|数显款智能定时|可调温 | E10: 668 | F10: =_xlfn.XLOOKUP($G10,[1]类目转化数据!$B:$B,[1]类目转化数据!$A:$A) -> 社会餐饮设备 | G10: 商用开水器 | H10: =_xlfn.XLOOKUP(G10,[1]类目转化数据!B:B,[1]类目转化数据!C:C) -> 小客单
A11: 官旗 | B11: 41485142295 | C11: 德玛仕（DEMASHI）步进式开水器 商用开水机奶茶店餐厅吧台全自动电热开水器商用饮水机 开水机商用 热水机烧水器 黑钢35L/h|可调温|1分钟速热 | E11: 629 | F11: =_xlfn.XLOOKUP($G11,[1]类目转化数据!$B:$B,[1]类目转化数据!$A:$A) -> 社会餐饮设备 | G11: 商用开水器 | H11: =_xlfn.XLOOKUP(G11,[1]类目转化数据!B:B,[1]类目转化数据!C:C) -> 小客单
A12: 官旗 | B12: 10102749069016 | C12: 德玛仕（DEMASHI）步进式开水器 商用开水机奶茶店餐厅吧台全自动电热开水器商用饮水机 开水机商用 热水机烧水器 40L/h|定时开关|内置二级过滤 | E12: 1199 | F12: =_xlfn.XLOOKUP($G12,[1]类目转化数据!$B:$B,[1]类目转化数据!$A:$A) -> 社会餐饮设备 | G12: 商用开水器 | H12: =_xlfn.XLOOKUP(G12,[1]类目转化数据!B:B,[1]类目转化数据!C:C) -> 小客单
A13: 官旗 | B13: 26240183156 | C13: 德玛仕（DEMASHI）步进式开水器 商用开水机奶茶店餐厅吧台全自动电热开水器商用饮水机 开水机商用 热水机烧水器 黑钢40L/h|可调温|智能定时|三级过滤 | E13: 799 | F13: =_xlfn.XLOOKUP($G13,[1]类目转化数据!$B:$B,[1]类目转化数据!$A:$A) -> 社会餐饮设备 | G13: 商用开水器 | H13: =_xlfn.XLOOKUP(G13,[1]类目转化数据!B:B,[1]类目转化数据!C:C) -> 小客单
... A148: 官旗 | B148: 71257965867 | C148: 德玛仕（DEMASHI）大功率电磁炉商用电磁灶台大锅灶单头双头电灶台凹面学校酒店食堂厨房炒菜汤锅炉 8KW丨双头高背汤炉丨MC-STL08C-02 | E148: 10499 | F148: =_xlfn.XLOOKUP($G148,[1]类目转化数据!$B:$B,[1]类目转化数据!$A:$A) -> 制热设备 | G148: 电磁大锅灶 | H148: =_xlfn.XLOOKUP(G148,[1]类目转化数据!B:B,[1]类目转化数据!C:C) -> 大锅灶组
A149: 官旗 | B149: 10208654363828 | C149: 德玛仕（DEMASHI）商用电磁炉5000W 大功率商业电磁炉电磁灶 酒店食堂高功率大火力电炒炉【全铜线圈】 双头电磁炉一平—凹丨—机双用丨3500W | E149: 1580 | F149: =_xlfn.XLOOKUP($G149,[1]类目转化数据!$B:$B,[1]类目转化数据!$A:$A) -> 社会餐饮设备 | G149: 电磁炉 | H149: =_xlfn.XLOOKUP(G149,[1]类目转化数据!B:B,[1]类目转化数据!C:C) -> 小客单 | I149: 是
A150: 官旗 | B150: 11265206463 | C150: 德玛仕（DEMASHI）商用电磁炉5000W 大功率商业电磁炉电磁灶 酒店食堂高功率大火力电炒炉【全铜线圈】 强劲爆炒丨5000W丨可炒约40人菜量丨九档火力 | E150: 1149 | F150: =_xlfn.XLOOKUP($G150,[1]类目转化数据!$B:$B,[1]类目转化数据!$A:$A) -> 社会餐饮设备 | G150: 电磁炉 | H150: =_xlfn.XLOOKUP(G150,[1]类目转化数据!B:B,[1]类目转化数据!C:C) -> 小客单
A151: 官旗 | B151: 11265206464 | C151: 德玛仕（DEMASHI）商用电磁炉5000W 大功率商业电磁炉电磁灶 酒店食堂高功率大火力电炒炉【全铜线圈】 品酒会同款丨3500W凹面丨配45cm炒锅 | E151: 799 | F151: =_xlfn.XLOOKUP($G151,[1]类目转化数据!$B:$B,[1]类目转化数据!$A:$A) -> 社会餐饮设备 | G151: 电磁炉 | H151: =_xlfn.XLOOKUP(G151,[1]类目转化数据!B:B,[1]类目转化数据!C:C) -> 小客单
A152: 官旗 | B152: 10047256185267 | C152: 德玛仕（DEMASHI）商用电磁炉5000W 大功率商业电磁炉电磁灶 酒店食堂高功率大火力电炒炉【全铜线圈】 双头电磁炉一平—凹丨—机双用丨5000W | E152: 1980 | F152: =_xlfn.XLOOKUP($G152,[1]类目转化数据!$B:$B,[1]类目转化数据!$A:$A) -> 社会餐饮设备 | G152: 电磁炉 | H152: =_xlfn.XLOOKUP(G152,[1]类目转化数据!B:B,[1]类目转化数据!C:C) -> 小客单
A153: 官旗 | B153: 10033949372826 | C153: 德玛仕（DEMASHI）商用电磁炉5000W 大功率商业电磁炉电磁灶 酒店食堂高功率大火力电炒炉【全铜线圈】 高脚架款丨6000W丨220V丨配50cm炒锅 | E153: 1699 | F153: =_xlfn.XLOOKUP($G153,[1]类目转化数据!$B:$B,[1]类目转化数据!$A:$A) -> 社会餐饮设备 | G153: 电磁炉 | H153: =_xlfn.XLOOKUP(G153,[1]类目转化数据!B:B,[1]类目转化数据!C:C) -> 小客单
A154: 官旗 | B154: 10026536908906 | C154: 德玛仕（DEMASHI）商用电磁炉5000W 大功率商业电磁炉电磁灶 酒店食堂高功率大火力电炒炉【全铜线圈】 公司爆炒丨6000W丨220V丨凹面带插头 | E154: 1449 | F154: =_xlfn.XLOOKUP($G154,[1]类目转化数据!$B:$B,[1]类目转化数据!$A:$A) -> 社会餐饮设备 | G154: 电磁炉 | H154: =_xlfn.XLOOKUP(G154,[1]类目转化数据!B:B,[1]类目转化数据!C:C) -> 小客单
A155: 官旗 | B155: 10031644704801 | C155: 德玛仕（DEMASHI）商用电磁炉5000W 大功率商业电磁炉电磁灶 酒店食堂高功率大火力电炒炉【全铜线圈】 卤煮款5000W丨可调底脚MC-TPL05A | E155: 1898 | F155: =_xlfn.XLOOKUP($G155,[1]类目转化数据!$B:$B,[1]类目转化数据!$A:$A) -> 社会餐饮设备 | G155: 电磁炉 | H155: =_xlfn.XLOOKUP(G155,[1]类目转化数据!B:B,[1]类目转化数据!C:C) -> 小客单
A156: 官旗 | B156: 10105991135799 | C156: 德玛仕（DEMASHI）商用电磁炉5000W 大功率商业电磁炉电磁灶 酒店食堂高功率大火力电炒炉【全铜线圈】 5000W立式丨可调底脚MC-TPL05A | E156: 1598 | F156: =_xlfn.XLOOKUP($G156,[1]类目转化数据!$B:$B,[1]类目转化数据!$A:$A) -> 社会餐饮设备 | G156: 电磁炉 | H156: =_xlfn.XLOOKUP(G156,[1]类目转化数据!B:B,[1]类目转化数据!C:C) -> 小客单
A157: 官旗 | B157: 10105991135798 | C157: 德玛仕（DEMASHI）商用电磁炉5000W 大功率商业电磁炉电磁灶 酒店食堂高功率大火力电炒炉【全铜线圈】 一平一凹丨5000W双头灶TC-100A2 | E157: 1980 | F157: =_xlfn.XLOOKUP($G157,[1]类目转化数据!$B:$B,[1]类目转化数据!$A:$A) -> 社会餐饮设备 | G157: 电磁炉 | H157: =_xlfn.XLOOKUP(G157,[1]类目转化数据!B:B,[1]类目转化数据!C:C) -> 小客单
A158: 官旗 | B158: 10105991135797 | C158: 德玛仕（DEMASHI）商用电磁炉5000W 大功率商业电磁炉电磁灶 酒店食堂高功率大火力电炒炉【全铜线圈】 6000W凹面丨380V款IH-TC-6000W | E158: 1699 | F158: =_xlfn.XLOOKUP($G158,[1]类目转化数据!$B:$B,[1]类目转化数据!$A:$A) -> 社会餐饮设备 | G158: 电磁炉 | H158: =_xlfn.XLOOKUP(G158,[1]类目转化数据!B:B,[1]类目转化数据!C:C) -> 小客单
A159: 官旗 | B159: 10105991135796 | C159: 德玛仕（DEMASHI）商用电磁炉5000W 大功率商业电磁炉电磁灶 酒店食堂高功率大火力电炒炉【全铜线圈】 6000W平面丨380V款IH-TT-6000W | E159: 1499 | F159: =_xlfn.XLOOKUP($G159,[1]类目转化数据!$B:$B,[1]类目转化数据!$A:$A) -> 社会餐饮设备 | G159: 电磁炉 | H159: =_xlfn.XLOOKUP(G159,[1]类目转化数据!B:B,[1]类目转化数据!C:C) -> 小客单
A160: 官旗 | B160: 10097788639036 | C160: 德玛仕（DEMASHI）商用电磁炉5000W 大功率商业电磁炉电磁灶 酒店食堂高功率大火力电炒炉【全铜线圈】 5000W凹面丨多档调控IH-TC-5000N | E160: 1199 | F160: =_xlfn.XLOOKUP($G160,[1]类目转化数据!$B:$B,[1]类目转化数据!$A:$A) -> 社会餐饮设备 | G160: 电磁炉 | H160: =_xlfn.XLOOKUP(G160,[1]类目转化数据!B:B,[1]类目转化数据!C:C) -> 小客单
A161: 官旗 | B161: 10105991135802 | C161: 德玛仕（DEMASHI）商用电磁炉5000W 大功率商业电磁炉电磁灶 酒店食堂高功率大火力电炒炉【全铜线圈】 8000W台立丨凹面猛爆炒TC-8000NA | E161: 2998 | F161: =_xlfn.XLOOKUP($G161,[1]类目转化数据!$B:$B,[1]类目转化数据!$A:$A) -> 社会餐饮设备 | G161: 电磁炉 | H161: =_xlfn.XLOOKUP(G161,[1]类目转化数据!B:B,[1]类目转化数据!C:C) -> 小客单
... A182: 官旗 | B182: 29399558595 | C182: 德玛仕（DEMASHI）商用电磁炉大功率3500w大电磁炉炒菜电池炉电磁灶大锅灶炒菜电炒炉火锅【全铜线圈】 不锈钢款【3500W旋钮】TT-3500AX | E182: 398 | F182: =_xlfn.XLOOKUP($G182,[1]类目转化数据!$B:$B,[1]类目转化数据!$A:$A) -> 社会餐饮设备 | G182: 电磁炉 | H182: =_xlfn.XLOOKUP(G182,[1]类目转化数据!B:B,[1]类目转化数据!C:C) -> 小客单
A183: 官旗 | B183: 10208868719396 | C183: 德玛仕（DEMASHI）商用电磁炉大功率3500w大电磁炉炒菜电池炉电磁灶大锅灶炒菜电炒炉火锅【全铜线圈】 凹面大锅【自带45CM锅】TC-3500N | E183: 799 | F183: =_xlfn.XLOOKUP($G183,[1]类目转化数据!$B:$B,[1]类目转化数据!$A:$A) -> 社会餐饮设备 | G183: 电磁炉 | H183: =_xlfn.XLOOKUP(G183,[1]类目转化数据!B:B,[1]类目转化数据!C:C) -> 小客单 | I183: 是
A184: 官旗 | B184: 10207996061871 | C184: 德玛仕（DEMASHI）商用电磁炉大功率3500w大电磁炉炒菜电池炉电磁灶大锅灶炒菜电炒炉火锅【全铜线圈】 凹面按键【3500W单机】BC-3500A | E184: 398 | F184: =_xlfn.XLOOKUP($G184,[1]类目转化数据!$B:$B,[1]类目转化数据!$A:$A) -> 社会餐饮设备 | G184: 电磁炉 | H184: =_xlfn.XLOOKUP(G184,[1]类目转化数据!B:B,[1]类目转化数据!C:C) -> 小客单
A185: 官旗 | B185: 10118712097536 | C185: 德玛仕（DEMASHI）商用电磁炉大功率3500w大电磁炉炒菜电池炉电磁灶大锅灶炒菜电炒炉火锅【全铜线圈】 四头平面丨3500W*4丨BZL-35X4-T1 | E185: 2380 | F185: =_xlfn.XLOOKUP($G185,[1]类目转化数据!$B:$B,[1]类目转化数据!$A:$A) -> 社会餐饮设备 | G185: 电磁炉 | H185: =_xlfn.XLOOKUP(G185,[1]类目转化数据!B:B,[1]类目转化数据!C:C) -> 小客单
A186: 官旗 | B186: 10111302108541 | C186: 德玛仕（DEMASHI）商用电磁炉大功率3500w大电磁炉炒菜电池炉电磁灶大锅灶炒菜电炒炉火锅【全铜线圈】 不锈钢款【3500W按键】BT-3500A | E186: 369 | F186: =_xlfn.XLOOKUP($G186,[1]类目转化数据!$B:$B,[1]类目转化数据!$A:$A) -> 社会餐饮设备 | G186: 电磁炉 | H186: =_xlfn.XLOOKUP(G186,[1]类目转化数据!B:B,[1]类目转化数据!C:C) -> 小客单
A187: 官旗 | B187: 10043181351361 | C187: 德玛仕（DEMASHI）商用电磁炉大功率3500w大电磁炉炒菜电池炉电磁灶大锅灶炒菜电炒炉火锅【全铜线圈】 不挑锅具【3500W电陶炉】DTL3500 | E187: 699 | F187: =_xlfn.XLOOKUP($G187,[1]类目转化数据!$B:$B,[1]类目转化数据!$A:$A) -> 社会餐饮设备 | G187: 电磁炉 | H187: =_xlfn.XLOOKUP(G187,[1]类目转化数据!B:B,[1]类目转化数据!C:C) -> 小客单
A188: 官旗 | B188: 11284521025 | C188: 德玛仕（DEMASHI）商用电磁炉大功率3500w大电磁炉炒菜电池炉电磁灶大锅灶炒菜电炒炉火锅【全铜线圈】 炒锅套餐【炒锅+插头】35P6-CM1 | E188: 379 | F188: =_xlfn.XLOOKUP($G188,[1]类目转化数据!$B:$B,[1]类目转化数据!$A:$A) -> 社会餐饮设备 | G188: 电磁炉 | H188: =_xlfn.XLOOKUP(G188,[1]类目转化数据!B:B,[1]类目转化数据!C:C) -> 小客单
A189: 官旗 | B189: 10036069503895 | C189: 德玛仕（DEMASHI）商用电磁炉大功率3500w大电磁炉炒菜电池炉电磁灶大锅灶炒菜电炒炉火锅【全铜线圈】 不锈钢款【3500W凹面】BC-3500A | E189: 448 | F189: =_xlfn.XLOOKUP($G189,[1]类目转化数据!$B:$B,[1]类目转化数据!$A:$A) -> 社会餐饮设备 | G189: 电磁炉 | H189: =_xlfn.XLOOKUP(G189,[1]类目转化数据!B:B,[1]类目转化数据!C:C) -> 小客单
A190: 官旗 | B190: 11360403795 | C190: 德玛仕（DEMASHI）商用电磁炉大功率3500w大电磁炉炒菜电池炉电磁灶大锅灶炒菜电炒炉火锅【全铜线圈】 汤桶套餐【插头+汤桶】35P6-CM1 | E190: 399 | F190: =_xlfn.XLOOKUP($G190,[1]类目转化数据!$B:$B,[1]类目转化数据!$A:$A) -> 社会餐饮设备 | G190: 电磁炉 | H190: =_xlfn.XLOOKUP(G190,[1]类目转化数据!B:B,[1]类目转化数据!C:C) -> 小客单
A191: 官旗 | B191: 10036069503894 | C191: 德玛仕（DEMASHI）商用电磁炉大功率3500w大电磁炉炒菜电池炉电磁灶大锅灶炒菜电炒炉火锅【全铜线圈】 炒煮套餐【炒锅+汤桶】35P6-CM1 | E191: 449 | F191: =_xlfn.XLOOKUP($G191,[1]类目转化数据!$B:$B,[1]类目转化数据!$A:$A) -> 社会餐饮设备 | G191: 电磁炉 | H191: =_xlfn.XLOOKUP(G191,[1]类目转化数据!B:B,[1]类目转化数据!C:C) -> 小客单
A192: 官旗 | B192: 10052607756364 | C192: 德玛仕（DEMASHI）商用电磁炉大功率3500w大电磁炉炒菜电池炉电磁灶大锅灶炒菜电炒炉火锅【全铜线圈】 平面卤煮【5000W功率】TT-5000W | E192: 1019 | F192: =_xlfn.XLOOKUP($G192,[1]类目转化数据!$B:$B,[1]类目转化数据!$A:$A) -> 社会餐饮设备 | G192: 电磁炉 | H192: =_xlfn.XLOOKUP(G192,[1]类目转化数据!B:B,[1]类目转化数据!C:C) -> 小客单
A193: 官旗 | B193: 10118305685839 | C193: 德玛仕（DEMASHI）商用电磁炉大功率3500w大电磁炉炒菜电池炉电磁灶大锅灶炒菜电炒炉火锅【全铜线圈】 双头平面丨不挑锅具DTL-3500S1 | E193: 1480 | F193: =_xlfn.XLOOKUP($G193,[1]类目转化数据!$B:$B,[1]类目转化数据!$A:$A) -> 社会餐饮设备 | G193: 电磁炉 | H193: =_xlfn.XLOOKUP(G193,[1]类目转化数据!B:B,[1]类目转化数据!C:C) -> 小客单
A194: 官旗 | B194: 10174927379547 | C194: 德玛仕（DEMASHI）商用电磁炉大功率3500w大电磁炉炒菜电池炉电磁灶大锅灶炒菜电炒炉火锅【全铜线圈】 双系统款【3500W双显】TT-35C1 | E194: 499 | F194: =_xlfn.XLOOKUP($G194,[1]类目转化数据!$B:$B,[1]类目转化数据!$A:$A) -> 社会餐饮设备 | G194: 电磁炉 | H194: =_xlfn.XLOOKUP(G194,[1]类目转化数据!B:B,[1]类目转化数据!C:C) -> 小客单
A195: 官旗 | B195: 10118305685838 | C195: 德玛仕（DEMASHI）商用电磁炉大功率3500w大电磁炉炒菜电池炉电磁灶大锅灶炒菜电炒炉火锅【全铜线圈】 不挑锅具【凹面电陶炉】TC3500-F1 | E195: 799 | F195: =_xlfn.XLOOKUP($G195,[1]类目转化数据!$B:$B,[1]类目转化数据!$A:$A) -> 社会餐饮设备 | G195: 电磁炉 | H195: =_xlfn.XLOOKUP(G195,[1]类目转化数据!B:B,[1]类目转化数据!C:C) -> 小客单
... A271: 官旗 | B271: 12154924170 | C271: 德玛仕（DEMASHI）茶杯消毒柜 家用商立式高温 办公室茶杯茶具消毒碗柜 大容量双开门 商用消毒柜 立式消毒柜 三层70L丨可放40个茶杯 | E271: 599 | F271: =_xlfn.XLOOKUP($G271,[1]类目转化数据!$B:$B,[1]类目转化数据!$A:$A) -> 烟消洗设备 | G271: 茶杯消毒柜 | H271: =_xlfn.XLOOKUP(G271,[1]类目转化数据!B:B,[1]类目转化数据!C:C) -> 小客单
A272: 官旗 | B272: 10033863816020 | C272: 德玛仕（DEMASHI）茶杯消毒柜 家用商用台式高温 办公室茶杯茶具消毒碗柜 小型台式二星级消毒柜RTD55PD-1 双层45L丨可放24个茶杯 | E272: 419 | F272: =_xlfn.XLOOKUP($G272,[1]类目转化数据!$B:$B,[1]类目转化数据!$A:$A) -> 烟消洗设备 | G272: 茶杯消毒柜 | H272: =_xlfn.XLOOKUP(G272,[1]类目转化数据!B:B,[1]类目转化数据!C:C) -> 小客单 | I272: 是
A273: 官旗 | B273: 23493271162 | C273: 德玛仕（DEMASHI）商用冷藏工作台 操作台冰柜 水吧台厨房奶茶店保鲜操作台 工作台冰柜 平台雪柜 双温工作台【工程款】 1.8*0.6*0.8 | E273: 4298 | F273: =_xlfn.XLOOKUP($G273,[1]类目转化数据!$B:$B,[1]类目转化数据!$A:$A) -> 制冷设备 | G273: 冷藏工作台 | H273: =_xlfn.XLOOKUP(G273,[1]类目转化数据!B:B,[1]类目转化数据!C:C) -> 后厨组
A274: 官旗 | B274: 23493271163 | C274: 德玛仕（DEMASHI）商用冷藏工作台 操作台冰柜 水吧台厨房奶茶店保鲜操作台 工作台冰柜 平台雪柜 双温工作台【工程款】 1.8*0.8*0.8 | E274: 4298 | F274: =_xlfn.XLOOKUP($G274,[1]类目转化数据!$B:$B,[1]类目转化数据!$A:$A) -> 制冷设备 | G274: 冷藏工作台 | H274: =_xlfn.XLOOKUP(G274,[1]类目转化数据!B:B,[1]类目转化数据!C:C) -> 后厨组
A275: 官旗 | B275: 23493271167 | C275: 德玛仕（DEMASHI）商用冷藏工作台 操作台冰柜 水吧台厨房奶茶店保鲜操作台 工作台冰柜 平台雪柜 保鲜工作台【工程款】 1.8*0.6*0.8 | E275: 4298 | F275: =_xlfn.XLOOKUP($G275,[1]类目转化数据!$B:$B,[1]类目转化数据!$A:$A) -> 制冷设备 | G275: 冷藏工作台 | H275: =_xlfn.XLOOKUP(G275,[1]类目转化数据!B:B,[1]类目转化数据!C:C) -> 后厨组
A276: 官旗 | B276: 23493271161 | C276: 德玛仕（DEMASHI）商用冷藏工作台 操作台冰柜 水吧台厨房奶茶店保鲜操作台 工作台冰柜 平台雪柜 双温工作台【工程款】 1.5*0.8*0.8 | E276: 4180 | F276: =_xlfn.XLOOKUP($G276,[1]类目转化数据!$B:$B,[1]类目转化数据!$A:$A) -> 制冷设备 | G276: 冷藏工作台 | H276: =_xlfn.XLOOKUP(G276,[1]类目转化数据!B:B,[1]类目转化数据!C:C) -> 后厨组
A277: 官旗 | B277: 23493271166 | C277: 德玛仕（DEMASHI）商用冷藏工作台 操作台冰柜 水吧台厨房奶茶店保鲜操作台 工作台冰柜 平台雪柜 保鲜工作台【工程款】 1.5*0.8*0.8 | E277: 4180 | F277: =_xlfn.XLOOKUP($G277,[1]类目转化数据!$B:$B,[1]类目转化数据!$A:$A) -> 制冷设备 | G277: 冷藏工作台 | H277: =_xlfn.XLOOKUP(G277,[1]类目转化数据!B:B,[1]类目转化数据!C:C) -> 后厨组
A278: 官旗 | B278: 23493271165 | C278: 德玛仕（DEMASHI）商用冷藏工作台 操作台冰柜 水吧台厨房奶茶店保鲜操作台 工作台冰柜 平台雪柜 保鲜工作台【工程款】 1.5*0.6*0.8 | E278: 4180 | F278: =_xlfn.XLOOKUP($G278,[1]类目转化数据!$B:$B,[1]类目转化数据!$A:$A) -> 制冷设备 | G278: 冷藏工作台 | H278: =_xlfn.XLOOKUP(G278,[1]类目转化数据!B:B,[1]类目转化数据!C:C) -> 后厨组
A279: 官旗 | B279: 23493271171 | C279: 德玛仕（DEMASHI）商用冷藏工作台 操作台冰柜 水吧台厨房奶茶店保鲜操作台 工作台冰柜 平台雪柜 冷冻工作台【工程款】 1.5*0.8*0.8 | E279: 4180 | F279: =_xlfn.XLOOKUP($G279,[1]类目转化数据!$B:$B,[1]类目转化数据!$A:$A) -> 制冷设备 | G279: 冷藏工作台 | H279: =_xlfn.XLOOKUP(G279,[1]类目转化数据!B:B,[1]类目转化数据!C:C) -> 后厨组
A280: 官旗 | B280: 23493271170 | C280: 德玛仕（DEMASHI）商用冷藏工作台 操作台冰柜 水吧台厨房奶茶店保鲜操作台 工作台冰柜 平台雪柜 冷冻工作台【工程款】 1.5*0.6*0.8 | E280: 4180 | F280: =_xlfn.XLOOKUP($G280,[1]类目转化数据!$B:$B,[1]类目转化数据!$A:$A) -> 制冷设备 | G280: 冷藏工作台 | H280: =_xlfn.XLOOKUP(G280,[1]类目转化数据!B:B,[1]类目转化数据!C:C) -> 后厨组
A281: 官旗 | B281: 23493271168 | C281: 德玛仕（DEMASHI）商用冷藏工作台 操作台冰柜 水吧台厨房奶茶店保鲜操作台 工作台冰柜 平台雪柜 保鲜工作台【工程款】 1.8*0.8*0.8 | E281: 4298 | F281: =_xlfn.XLOOKUP($G281,[1]类目转化数据!$B:$B,[1]类目转化数据!$A:$A) -> 制冷设备 | G281: 冷藏工作台 | H281: =_xlfn.XLOOKUP(G281,[1]类目转化数据!B:B,[1]类目转化数据!C:C) -> 后厨组
A282: 官旗 | B282: 23493271172 | C282: 德玛仕（DEMASHI）商用冷藏工作台 操作台冰柜 水吧台厨房奶茶店保鲜操作台 工作台冰柜 平台雪柜 冷冻工作台【工程款】 1.8*0.6*0.8 | E282: 4298 | F282: =_xlfn.XLOOKUP($G282,[1]类目转化数据!$B:$B,[1]类目转化数据!$A:$A) -> 制冷设备 | G282: 冷藏工作台 | H282: =_xlfn.XLOOKUP(G282,[1]类目转化数据!B:B,[1]类目转化数据!C:C) -> 后厨组
A283: 官旗 | B283: 23493271173 | C283: 德玛仕（DEMASHI）商用冷藏工作台 操作台冰柜 水吧台厨房奶茶店保鲜操作台 工作台冰柜 平台雪柜 冷冻工作台【工程款】 1.8*0.8*0.8 | E283: 4298 | F283: =_xlfn.XLOOKUP($G283,[1]类目转化数据!$B:$B,[1]类目转化数据!$A:$A) -> 制冷设备 | G283: 冷藏工作台 | H283: =_xlfn.XLOOKUP(G283,[1]类目转化数据!B:B,[1]类目转化数据!C:C) -> 后厨组
A284: 官旗 | B284: 10175734298951 | C284: 德玛仕（DEMASHI）包子馒头压面机商用电动压面条机擀面机食堂用大型全自动压饺子皮揉面机不锈钢 【面皮宽19cm】2厘方刀+3厘圆刀 | E284: 3318 | F284: =_xlfn.XLOOKUP($G284,[1]类目转化数据!$B:$B,[1]类目转化数据!$A:$A) -> 机械设备 | G284: 商用压面机 | H284: =_xlfn.XLOOKUP(G284,[1]类目转化数据!B:B,[1]类目转化数据!C:C) -> 机械设备
... A406: 官旗 | B406: 10122017899168 | C406: 德玛仕（DEMASHI）商用消毒柜 立式消毒碗柜消毒柜家用酒杯茶杯餐具碗筷家用厨房紫外线消毒柜大容量立式消毒柜 6层大空间丨中温丨紫外线一星丨260升 | E406: 799 | F406: =_xlfn.XLOOKUP($G406,[1]类目转化数据!$B:$B,[1]类目转化数据!$A:$A) -> 烟消洗设备 | G406: 2000以下消毒柜 | H406: =_xlfn.XLOOKUP(G406,[1]类目转化数据!B:B,[1]类目转化数据!C:C) -> 小客单
A407: 官旗 | B407: 10028874006996 | C407: 德玛仕（DEMASHI）商用消毒柜 立式消毒碗柜消毒柜家用酒杯茶杯餐具碗筷立式厨房紫外线消毒柜大容量高温消毒碗柜 8层330L丨1.63米高丨紫外线+高温 | E407: 1798 | F407: =_xlfn.XLOOKUP($G407,[1]类目转化数据!$B:$B,[1]类目转化数据!$A:$A) -> 烟消洗设备 | G407: 2000以下消毒柜 | H407: =_xlfn.XLOOKUP(G407,[1]类目转化数据!B:B,[1]类目转化数据!C:C) -> 小客单 | I407: 是
A408: 官旗 | B408: 11868119984 | C408: 德玛仕（DEMASHI）扁刀和面机商用全自动多功能搅拌食堂用揉面机电动厨师机15-50KG大容量 单次和面30斤YF-HJ15【220V】 | E408: 2698 | F408: =_xlfn.XLOOKUP($G408,[1]类目转化数据!$B:$B,[1]类目转化数据!$A:$A) -> 机械设备 | G408: 商用搅拌机/商用和面机 | H408: =_xlfn.XLOOKUP(G408,[1]类目转化数据!B:B,[1]类目转化数据!C:C) -> 机械设备
A409: 官旗 | B409: 10067900410634 | C409: 德玛仕（DEMASHI）扁刀和面机商用全自动多功能搅拌食堂用揉面机电动厨师机15-50KG大容量 单次和面30斤YF-HJ15【380V】 | E409: 2698 | F409: =_xlfn.XLOOKUP($G409,[1]类目转化数据!$B:$B,[1]类目转化数据!$A:$A) -> 机械设备 | G409: 商用搅拌机/商用和面机 | H409: =_xlfn.XLOOKUP(G409,[1]类目转化数据!B:B,[1]类目转化数据!C:C) -> 机械设备
A410: 官旗 | B410: 10088834403090 | C410: 德玛仕（DEMASHI）扁刀和面机商用全自动多功能搅拌食堂用揉面机电动厨师机15-50KG大容量 单次和面50斤YF-HJ25【220V】 | E410: 3198 | F410: =_xlfn.XLOOKUP($G410,[1]类目转化数据!$B:$B,[1]类目转化数据!$A:$A) -> 机械设备 | G410: 商用搅拌机/商用和面机 | H410: =_xlfn.XLOOKUP(G410,[1]类目转化数据!B:B,[1]类目转化数据!C:C) -> 机械设备
A411: 官旗 | B411: 65803883162 | C411: 德玛仕（DEMASHI）扁刀和面机商用全自动多功能搅拌食堂用揉面机电动厨师机15-50KG大容量 单次和面100斤YF-HJ50【380V】 | E411: 5498 | F411: =_xlfn.XLOOKUP($G411,[1]类目转化数据!$B:$B,[1]类目转化数据!$A:$A) -> 机械设备 | G411: 商用搅拌机/商用和面机 | H411: =_xlfn.XLOOKUP(G411,[1]类目转化数据!B:B,[1]类目转化数据!C:C) -> 机械设备
A412: 官旗 | B412: 41806936214 | C412: 德玛仕（DEMASHI）扁刀和面机商用全自动多功能搅拌食堂用揉面机电动厨师机15-50KG大容量 单次和面100斤YF-HJ50【220V】 | E412: 5498 | F412: =_xlfn.XLOOKUP($G412,[1]类目转化数据!$B:$B,[1]类目转化数据!$A:$A) -> 机械设备 | G412: 商用搅拌机/商用和面机 | H412: =_xlfn.XLOOKUP(G412,[1]类目转化数据!B:B,[1]类目转化数据!C:C) -> 机械设备
A413: 官旗 | B413: 55314895044 | C413: 德玛仕（DEMASHI）扁刀和面机商用全自动多功能搅拌食堂用揉面机电动厨师机15-50KG大容量 单次和面50斤YF-HJ25【380V】 | E413: 3198 | F413: =_xlfn.XLOOKUP($G413,[1]类目转化数据!$B:$B,[1]类目转化数据!$A:$A) -> 机械设备 | G413: 商用搅拌机/商用和面机 | H413: =_xlfn.XLOOKUP(G413,[1]类目转化数据!B:B,[1]类目转化数据!C:C) -> 机械设备
A414: 官旗 | B414: 10033187124588 | C414: 德玛仕（DEMASHI）扁刀和面机商用全自动多功能搅拌食堂用揉面机电动厨师机15-50KG大容量 【304款】30斤YF-HJ15A【220V】 | E414: 4498 | F414: =_xlfn.XLOOKUP($G414,[1]类目转化数据!$B:$B,[1]类目转化数据!$A:$A) -> 机械设备 | G414: 商用搅拌机/商用和面机 | H414: =_xlfn.XLOOKUP(G414,[1]类目转化数据!B:B,[1]类目转化数据!C:C) -> 机械设备
A415: 官旗 | B415: 10109486761870 | C415: 德玛仕（DEMASHI）扁刀和面机商用全自动多功能搅拌食堂用揉面机电动厨师机15-50KG大容量 200kg/h自动翻斗卸面HMJ200 | E415: 55880 | F415: =_xlfn.XLOOKUP($G415,[1]类目转化数据!$B:$B,[1]类目转化数据!$A:$A) -> 机械设备 | G415: 商用搅拌机/商用和面机 | H415: =_xlfn.XLOOKUP(G415,[1]类目转化数据!B:B,[1]类目转化数据!C:C) -> 机械设备
A416: 官旗 | B416: 10033238034898 | C416: 德玛仕（DEMASHI）扁刀和面机商用全自动多功能搅拌食堂用揉面机电动厨师机15-50KG大容量 【304款】50斤YF-HJ25A【220V】 | E416: 5248 | F416: =_xlfn.XLOOKUP($G416,[1]类目转化数据!$B:$B,[1]类目转化数据!$A:$A) -> 机械设备 | G416: 商用搅拌机/商用和面机 | H416: =_xlfn.XLOOKUP(G416,[1]类目转化数据!B:B,[1]类目转化数据!C:C) -> 机械设备
A417: 官旗 | B417: 10109486761867 | C417: 德玛仕（DEMASHI）扁刀和面机商用全自动多功能搅拌食堂用揉面机电动厨师机15-50KG大容量 75kg/h自动翻斗卸面HMJ75 | E417: 24980 | F417: =_xlfn.XLOOKUP($G417,[1]类目转化数据!$B:$B,[1]类目转化数据!$A:$A) -> 机械设备 | G417: 商用搅拌机/商用和面机 | H417: =_xlfn.XLOOKUP(G417,[1]类目转化数据!B:B,[1]类目转化数据!C:C) -> 机械设备
A418: 官旗 | B418: 10109863873980 | C418: 德玛仕（DEMASHI）扁刀和面机商用全自动多功能搅拌食堂用揉面机电动厨师机15-50KG大容量 翻缸和面机DMS-HM260 | E418: 99980 | F418: =_xlfn.XLOOKUP($G418,[1]类目转化数据!$B:$B,[1]类目转化数据!$A:$A) -> 机械设备 | G418: 商用搅拌机/商用和面机 | H418: =_xlfn.XLOOKUP(G418,[1]类目转化数据!B:B,[1]类目转化数据!C:C) -> 机械设备
A419: 官旗 | B419: 10033187124589 | C419: 德玛仕（DEMASHI）扁刀和面机商用全自动多功能搅拌食堂用揉面机电动厨师机15-50KG大容量 【304款】100斤YF-HJ50A【220V】 | E419: 8598 | F419: =_xlfn.XLOOKUP($G419,[1]类目转化数据!$B:$B,[1]类目转化数据!$A:$A) -> 机械设备 | G419: 商用搅拌机/商用和面机 | H419: =_xlfn.XLOOKUP(G419,[1]类目转化数据!B:B,[1]类目转化数据!C:C) -> 机械设备
... A577: 官旗 | B577: 10070799244917 | C577: 德玛仕（DEMASHI）消毒柜茶杯茶具消毒柜 功夫茶具桌面高温二星消毒 家用小型消毒柜办公室茶水间用 XDR28B-1 22L丨高颜值款丨约放16个杯子 | E577: 419 | F577: =_xlfn.XLOOKUP($G577,[1]类目转化数据!$B:$B,[1]类目转化数据!$A:$A) -> 烟消洗设备 | G577: 茶杯消毒柜 | H577: =_xlfn.XLOOKUP(G577,[1]类目转化数据!B:B,[1]类目转化数据!C:C) -> 小客单
A578: 官旗 | B578: 50562902386 | C578: 德玛仕（DEMASHI）消毒柜茶杯茶具消毒柜 功夫茶具桌面高温二星消毒 家用小型消毒柜办公室茶水间用 RTD60PD-1 55L丨茶水间用丨约放30个杯子 | E578: 499 | F578: =_xlfn.XLOOKUP($G578,[1]类目转化数据!$B:$B,[1]类目转化数据!$A:$A) -> 烟消洗设备 | G578: 茶杯消毒柜 | H578: =_xlfn.XLOOKUP(G578,[1]类目转化数据!B:B,[1]类目转化数据!C:C) -> 小客单 | I578: 是
A579: 官旗 | B579: 30398942235 | C579: 德玛仕（DEMASHI）消毒柜茶杯茶具消毒柜 功夫茶具桌面高温二星消毒 家用小型消毒柜办公室茶水间用ZTD28A-1 22L丨办公室款丨约放16个杯子 | E579: 399 | F579: =_xlfn.XLOOKUP($G579,[1]类目转化数据!$B:$B,[1]类目转化数据!$A:$A) -> 烟消洗设备 | G579: 茶杯消毒柜 | H579: =_xlfn.XLOOKUP(G579,[1]类目转化数据!B:B,[1]类目转化数据!C:C) -> 小客单
A580: 官旗 | B580: 30267894158 | C580: 德玛仕（DEMASHI）杀菌率99.99%消毒柜 家用 立式 家用消毒碗柜 大容量高温碗筷消毒柜 立式消毒柜 高温消毒柜 5层120升丨可供4-8人丨125℃高温 | E580: 998 | F580: =_xlfn.XLOOKUP($G580,[1]类目转化数据!$B:$B,[1]类目转化数据!$A:$A) -> 烟消洗设备 | G580: 2000以下消毒柜 | H580: =_xlfn.XLOOKUP(G580,[1]类目转化数据!B:B,[1]类目转化数据!C:C) -> 小客单
A581: 官旗 | B581: 10024473932205 | C581: 德玛仕（DEMASHI）开水器 商用 开水机全自动饮水机 煮水桶 步进式电热烧水器炉 热水机烧水箱 步进式100L/h（四级过滤）KW-90G-2BH | E581: 2949 | F581: =_xlfn.XLOOKUP($G581,[1]类目转化数据!$B:$B,[1]类目转化数据!$A:$A) -> 社会餐饮设备 | G581: 商用开水器 | H581: =_xlfn.XLOOKUP(G581,[1]类目转化数据!B:B,[1]类目转化数据!C:C) -> 小客单
A582: 官旗 | B582: 10024473932204 | C582: 德玛仕（DEMASHI）开水器 商用 开水机全自动饮水机 煮水桶 步进式电热烧水器炉 热水机烧水箱 步进式70L/h（四级过滤）KW-60G-1BH | E582: 2849 | F582: =_xlfn.XLOOKUP($G582,[1]类目转化数据!$B:$B,[1]类目转化数据!$A:$A) -> 社会餐饮设备 | G582: 商用开水器 | H582: =_xlfn.XLOOKUP(G582,[1]类目转化数据!B:B,[1]类目转化数据!C:C) -> 小客单
A583: 官旗 | B583: 10094639773473 | C583: 德玛仕（DEMASHI）开水器 商用 开水机全自动饮水机 煮水桶 步进式电热烧水器炉 热水机烧水箱 步进式烧水40L/h（五级过滤）KW-30B5-1 | E583: 999 | F583: =_xlfn.XLOOKUP($G583,[1]类目转化数据!$B:$B,[1]类目转化数据!$A:$A) -> 社会餐饮设备 | G583: 商用开水器 | H583: =_xlfn.XLOOKUP(G583,[1]类目转化数据!B:B,[1]类目转化数据!C:C) -> 小客单
A584: 官旗 | B584: 10024473932207 | C584: 德玛仕（DEMASHI）开水器 商用 开水机全自动饮水机 煮水桶 步进式电热烧水器炉 热水机烧水箱 支承座KS-9-12kW（带四级过滤） | E584: 1548 | F584: =_xlfn.XLOOKUP($G584,[1]类目转化数据!$B:$B,[1]类目转化数据!$A:$A) -> 社会餐饮设备 | G584: 商用开水器 | H584: =_xlfn.XLOOKUP(G584,[1]类目转化数据!B:B,[1]类目转化数据!C:C) -> 小客单
A585: 官旗 | B585: 10024473932206 | C585: 德玛仕（DEMASHI）开水器 商用 开水机全自动饮水机 煮水桶 步进式电热烧水器炉 热水机烧水箱 支承座KS-3-6kW（带四级过滤） | E585: 1398 | F585: =_xlfn.XLOOKUP($G585,[1]类目转化数据!$B:$B,[1]类目转化数据!$A:$A) -> 社会餐饮设备 | G585: 商用开水器 | H585: =_xlfn.XLOOKUP(G585,[1]类目转化数据!B:B,[1]类目转化数据!C:C) -> 小客单
A586: 官旗 | B586: 10024473932203 | C586: 德玛仕（DEMASHI）开水器 商用 开水机全自动饮水机 煮水桶 步进式电热烧水器炉 热水机烧水箱 步进式45L/h（四级过滤）KW-45G-1BH | E586: 2349 | F586: =_xlfn.XLOOKUP($G586,[1]类目转化数据!$B:$B,[1]类目转化数据!$A:$A) -> 社会餐饮设备 | G586: 商用开水器 | H586: =_xlfn.XLOOKUP(G586,[1]类目转化数据!B:B,[1]类目转化数据!C:C) -> 小客单
A587: 官旗 | B587: 10128413262662 | C587: 德玛仕（DEMASHI）开水器 商用 开水机全自动饮水机 煮水桶 步进式电热烧水器炉 热水机烧水箱 四级超滤专用滤芯(需购买底座后适用） | E587: 249 | F587: =_xlfn.XLOOKUP($G587,[1]类目转化数据!$B:$B,[1]类目转化数据!$A:$A) -> 配件/赠品 | G587: 滤芯 | H587: =_xlfn.XLOOKUP(G587,[1]类目转化数据!B:B,[1]类目转化数据!C:C) -> 直饮机组
A588: 官旗 | B588: 45284831337 | C588: 德玛仕（DEMASHI）开水器 商用 开水机全自动饮水机 煮水桶 步进式电热烧水器炉 热水机烧水箱 步进式120L/h（四级过滤）KW-100G-2 | E588: 3199 | F588: =_xlfn.XLOOKUP($G588,[1]类目转化数据!$B:$B,[1]类目转化数据!$A:$A) -> 社会餐饮设备 | G588: 商用开水器 | H588: =_xlfn.XLOOKUP(G588,[1]类目转化数据!B:B,[1]类目转化数据!C:C) -> 小客单
A589: 官旗 | B589: 10064280311376 | C589: 德玛仕（DEMASHI）开水器 商用 开水机全自动饮水机 煮水桶 步进式电热烧水器炉 热水机烧水箱 步进式100L/h（底座套餐）KW-90G-2BH | E589: 4498 | F589: =_xlfn.XLOOKUP($G589,[1]类目转化数据!$B:$B,[1]类目转化数据!$A:$A) -> 社会餐饮设备 | G589: 商用开水器 | H589: =_xlfn.XLOOKUP(G589,[1]类目转化数据!B:B,[1]类目转化数据!C:C) -> 小客单
A590: 官旗 | B590: 10110082563807 | C590: 德玛仕（DEMASHI）开水器 商用 开水机全自动饮水机 煮水桶 步进式电热烧水器炉 热水机烧水箱 步进式70L（双龙头）KW-60B5-2~380V | E590: 1299 | F590: =_xlfn.XLOOKUP($G590,[1]类目转化数据!$B:$B,[1]类目转化数据!$A:$A) -> 社会餐饮设备 | G590: 商用开水器 | H590: =_xlfn.XLOOKUP(G590,[1]类目转化数据!B:B,[1]类目转化数据!C:C) -> 小客单
... A689: 官旗 | B689: 10105799277825 | C689: 德玛仕（DEMASHI）凹面电磁炉家用大功率3500w电磁灶电炒炉电炉灶商业火锅灶炒菜猛火爆炒【全铜线圈】 3500W双旋钮丨持续低功率加热丨炒煮款3500N | E689: 499 | F689: =_xlfn.XLOOKUP($G689,[1]类目转化数据!$B:$B,[1]类目转化数据!$A:$A) -> 社会餐饮设备 | G689: 电磁炉 | H689: =_xlfn.XLOOKUP(G689,[1]类目转化数据!B:B,[1]类目转化数据!C:C) -> 小客单
A690: 官旗 | B690: 10208655255620 | C690: 德玛仕（DEMASHI）凹面电磁炉家用大功率3500w电磁灶电炒炉电炉灶商业火锅灶炒菜猛火爆炒【全铜线圈】 3500W线圈加大丨多功能彩屏款丨TC-3500D | E690: 899 | F690: =_xlfn.XLOOKUP($G690,[1]类目转化数据!$B:$B,[1]类目转化数据!$A:$A) -> 社会餐饮设备 | G690: 电磁炉 | H690: =_xlfn.XLOOKUP(G690,[1]类目转化数据!B:B,[1]类目转化数据!C:C) -> 小客单 | I690: 是
A691: 官旗 | B691: 10110531237990 | C691: 德玛仕（DEMASHI）凹面电磁炉家用大功率3500w电磁灶电炒炉电炉灶商业火锅灶炒菜猛火爆炒【全铜线圈】 3500W双旋钮丨单机款丨QC-3500E1 | E691: 399 | F691: =_xlfn.XLOOKUP($G691,[1]类目转化数据!$B:$B,[1]类目转化数据!$A:$A) -> 社会餐饮设备 | G691: 电磁炉 | H691: =_xlfn.XLOOKUP(G691,[1]类目转化数据!B:B,[1]类目转化数据!C:C) -> 小客单
A692: 官旗 | B692: 10116960498122 | C692: 德玛仕（DEMASHI）凹面电磁炉家用大功率3500w电磁灶电炒炉电炉灶商业火锅灶炒菜猛火爆炒【全铜线圈】 3500W双旋钮丨带炒锅丨QC-3500E1 | E692: 399 | F692: =_xlfn.XLOOKUP($G692,[1]类目转化数据!$B:$B,[1]类目转化数据!$A:$A) -> 社会餐饮设备 | G692: 电磁炉 | H692: =_xlfn.XLOOKUP(G692,[1]类目转化数据!B:B,[1]类目转化数据!C:C) -> 小客单
A693: 官旗 | B693: 10134993539926 | C693: 德玛仕（DEMASHI）凹面电磁炉家用大功率3500w电磁灶电炒炉电炉灶商业火锅灶炒菜猛火爆炒【全铜线圈】 3500W双旋钮丨持续低功率加热丨单机款3500N | E693: 389 | F693: =_xlfn.XLOOKUP($G693,[1]类目转化数据!$B:$B,[1]类目转化数据!$A:$A) -> 社会餐饮设备 | G693: 电磁炉 | H693: =_xlfn.XLOOKUP(G693,[1]类目转化数据!B:B,[1]类目转化数据!C:C) -> 小客单
A694: 官旗 | B694: 10111630736246 | C694: 德玛仕（DEMASHI）凹面电磁炉家用大功率3500w电磁灶电炒炉电炉灶商业火锅灶炒菜猛火爆炒【全铜线圈】 3500W按键款丨单机款丨BC-3500A | E694: 377.9 | F694: =_xlfn.XLOOKUP($G694,[1]类目转化数据!$B:$B,[1]类目转化数据!$A:$A) -> 社会餐饮设备 | G694: 电磁炉 | H694: =_xlfn.XLOOKUP(G694,[1]类目转化数据!B:B,[1]类目转化数据!C:C) -> 小客单
A695: 官旗 | B695: 10106891948215 | C695: 德玛仕（DEMASHI）凹面电磁炉家用大功率3500w电磁灶电炒炉电炉灶商业火锅灶炒菜猛火爆炒【全铜线圈】 3500W触控款丨带炒锅丨BC-35G1 | E695: 498 | F695: =_xlfn.XLOOKUP($G695,[1]类目转化数据!$B:$B,[1]类目转化数据!$A:$A) -> 社会餐饮设备 | G695: 电磁炉 | H695: =_xlfn.XLOOKUP(G695,[1]类目转化数据!B:B,[1]类目转化数据!C:C) -> 小客单
A696: 官旗 | B696: 10208658009618 | C696: 德玛仕（DEMASHI）凹面电磁炉家用大功率3500w电磁灶电炒炉电炉灶商业火锅灶炒菜猛火爆炒【全铜线圈】 凹面电陶炉丨3500W不挑锅具丨全钢机身 | E696: 698.9 | F696: =_xlfn.XLOOKUP($G696,[1]类目转化数据!$B:$B,[1]类目转化数据!$A:$A) -> 社会餐饮设备 | G696: 电磁炉 | H696: =_xlfn.XLOOKUP(G696,[1]类目转化数据!B:B,[1]类目转化数据!C:C) -> 小客单 | I696: 是
A697: 官旗 | B697: 10039048119408 | C697: 德玛仕（DEMASHI）凹面电磁炉家用大功率3500w电磁灶电炒炉电炉灶商业火锅灶炒菜猛火爆炒【全铜线圈】 3500W按键款丨炒煮款丨BC-3500A | E697: 508 | F697: =_xlfn.XLOOKUP($G697,[1]类目转化数据!$B:$B,[1]类目转化数据!$A:$A) -> 社会餐饮设备 | G697: 电磁炉 | H697: =_xlfn.XLOOKUP(G697,[1]类目转化数据!B:B,[1]类目转化数据!C:C) -> 小客单
A698: 官旗 | B698: 10111894832364 | C698: 德玛仕（DEMASHI）凹面电磁炉家用大功率3500w电磁灶电炒炉电炉灶商业火锅灶炒菜猛火爆炒【全铜线圈】 3500W双旋钮丨单机款丨QC-3500E2 | E698: 357.8 | F698: =_xlfn.XLOOKUP($G698,[1]类目转化数据!$B:$B,[1]类目转化数据!$A:$A) -> 社会餐饮设备 | G698: 电磁炉 | H698: =_xlfn.XLOOKUP(G698,[1]类目转化数据!B:B,[1]类目转化数据!C:C) -> 小客单
A699: 官旗 | B699: 10163350673374 | C699: 德玛仕（DEMASHI）凹面电磁炉家用大功率3500w电磁灶电炒炉电炉灶商业火锅灶炒菜猛火爆炒【全铜线圈】 3500W双旋钮丨炒煮款丨QC-3500E2 | E699: 369 | F699: =_xlfn.XLOOKUP($G699,[1]类目转化数据!$B:$B,[1]类目转化数据!$A:$A) -> 社会餐饮设备 | G699: 电磁炉 | H699: =_xlfn.XLOOKUP(G699,[1]类目转化数据!B:B,[1]类目转化数据!C:C) -> 小客单
A700: 官旗 | B700: 10111894832365 | C700: 德玛仕（DEMASHI）凹面电磁炉家用大功率3500w电磁灶电炒炉电炉灶商业火锅灶炒菜猛火爆炒【全铜线圈】 3500W双旋钮丨带炒锅丨QC-3500E2 | E700: 388 | F700: =_xlfn.XLOOKUP($G700,[1]类目转化数据!$B:$B,[1]类目转化数据!$A:$A) -> 社会餐饮设备 | G700: 电磁炉 | H700: =_xlfn.XLOOKUP(G700,[1]类目转化数据!B:B,[1]类目转化数据!C:C) -> 小客单
A701: 官旗 | B701: 10106891948217 | C701: 德玛仕（DEMASHI）凹面电磁炉家用大功率3500w电磁灶电炒炉电炉灶商业火锅灶炒菜猛火爆炒【全铜线圈】 3500W不锈钢丨带炒锅丨TC-3500K | E701: 579 | F701: =_xlfn.XLOOKUP($G701,[1]类目转化数据!$B:$B,[1]类目转化数据!$A:$A) -> 社会餐饮设备 | G701: 电磁炉 | H701: =_xlfn.XLOOKUP(G701,[1]类目转化数据!B:B,[1]类目转化数据!C:C) -> 小客单
A702: 官旗 | B702: 10106891948216 | C702: 德玛仕（DEMASHI）凹面电磁炉家用大功率3500w电磁灶电炒炉电炉灶商业火锅灶炒菜猛火爆炒【全铜线圈】 3500W触控款丨炒煮款丨BC-35G1 | E702: 598.9 | F702: =_xlfn.XLOOKUP($G702,[1]类目转化数据!$B:$B,[1]类目转化数据!$A:$A) -> 社会餐饮设备 | G702: 电磁炉 | H702: =_xlfn.XLOOKUP(G702,[1]类目转化数据!B:B,[1]类目转化数据!C:C) -> 小客单
A703: 官旗 | B703: 10163088950990 | C703: 德玛仕（DEMASHI）凹面电磁炉家用大功率3500w电磁灶电炒炉电炉灶商业火锅灶炒菜猛火爆炒【全铜线圈】 3500W单旋钮丨带炒锅丨BC-35AX | E703: 498 | F703: =_xlfn.XLOOKUP($G703,[1]类目转化数据!$B:$B,[1]类目转化数据!$A:$A) -> 社会餐饮设备 | G703: 电磁炉 | H703: =_xlfn.XLOOKUP(G703,[1]类目转化数据!B:B,[1]类目转化数据!C:C) -> 小客单
A704: 官旗 | B704: 10106891948218 | C704: 德玛仕（DEMASHI）凹面电磁炉家用大功率3500w电磁灶电炒炉电炉灶商业火锅灶炒菜猛火爆炒【全铜线圈】 3500W不锈钢丨炒煮款丨TC-3500K | E704: 669 | F704: =_xlfn.XLOOKUP($G704,[1]类目转化数据!$B:$B,[1]类目转化数据!$A:$A) -> 社会餐饮设备 | G704: 电磁炉 | H704: =_xlfn.XLOOKUP(G704,[1]类目转化数据!B:B,[1]类目转化数据!C:C) -> 小客单
A705: 官旗 | B705: 10028574381902 | C705: 德玛仕（DEMASHI）商用凹面电磁炉家用大功率3500w电磁灶电炒炉电炉灶商业火锅灶炒菜猛火爆炒【全铜线圈】 商用款套丨3500W抛锅丨炒锅+汤锅 | E705: 669 | F705: =_xlfn.XLOOKUP($G705,[1]类目转化数据!$B:$B,[1]类目转化数据!$A:$A) -> 社会餐饮设备 | G705: 电磁炉 | H705: =_xlfn.XLOOKUP(G705,[1]类目转化数据!B:B,[1]类目转化数据!C:C) -> 小客单
...

Sheet 咨询明细-数据源
A1: 年 | B1: 月份 | C1: 店铺 | D1: 类目 | E1: 成交金额 | F1: 日期 | G1: 顾客昵称 | H1: 商品编号 | I1: 商品名称 | J1: 客服昵称 | K1: 状态 | L1: 咨询结果
A2: =IFERROR(YEAR(F2)&"年","-") -> 2025年 | B2: =IFERROR(YEAR(F2)&"年"&MONTH(F2)&"月","-") -> 2025年6月 | C2: 官旗 | D2: 智慧厨房 | E2: 0 | F2: 2025-06-19 | G2: j***b | H2: 10162200870892 | I2: 德玛仕（DEMASHI）智慧智能厨房食堂 食安智能留样仪留样机留样秤 自动称重 食品菜品 保存日期标签打印一体机 智能留样仪丨留样自动记录丨可报表导出 | J2: 陈满红 | K2: 询单 | L2: 未成交 | M2: 61c00d3058b07f49f8e619fcbde977ae | N2: =COUNTIF(M:M,M2) -> 1
A3: =IFERROR(YEAR(F3)&"年","-") -> 2025年 | B3: =IFERROR(YEAR(F3)&"年"&MONTH(F3)&"月","-") -> 2025年6月 | C3: 官旗 | D3: 智慧厨房 | E3: 0 | F3: 2025-06-19 | G3: j***a | H3: 10162200870892 | I3: 德玛仕（DEMASHI）智慧智能厨房食堂 食安智能留样仪留样机留样秤 自动称重 食品菜品 保存日期标签打印一体机 智能留样仪丨留样自动记录丨可报表导出 | J3: 梁毅聪 | K3: 询单 | L3: 未成交 | M3: d301b6feed9deaec399919f644740bd6 | N3: =COUNTIF(M:M,M3) -> 1
A4: =IFERROR(YEAR(F4)&"年","-") -> 2025年 | B4: =IFERROR(YEAR(F4)&"年"&MONTH(F4)&"月","-") -> 2025年6月 | C4: 官旗 | D4: 智慧厨房 | E4: 279 | F4: 2025-06-26 | G4: j***w | H4: 10162200870892 | I4: 德玛仕（DEMASHI）智慧智能厨房食堂 食安智能留样仪留样机留样秤 自动称重 食品菜品 保存日期标签打印一体机 智能留样仪丨留样自动记录丨可报表导出 | J4: 梁毅聪 | K4: 询单 | L4: 未成交 | M4: f433845bda198b71e6ac9a7a5caf3933 | N4: =COUNTIF(M:M,M4) -> 2
A5: =IFERROR(YEAR(F5)&"年","-") -> 2025年 | B5: =IFERROR(YEAR(F5)&"年"&MONTH(F5)&"月","-") -> 2025年8月 | C5: 官旗 | D5: 智慧厨房 | E5: 8079 | F5: 2025-08-30 | G5: w***c | H5: 10175269720969 | I5: 德玛仕（DEMASHI）食品留样冰箱柜 冷藏柜保鲜柜商用展示柜 生物实验室设备学校幼儿园食堂公司用 食物冷藏保鲜商用 智能留样仪丨留样自动记录丨可报表导出 | J5: 许炎宏 | K5: 询单 | L5: 成交 | M5: 2f6331ecde140791ae7b8cf48574da2f | N5: =COUNTIF(M:M,M5) -> 1
A6: =IFERROR(YEAR(F6)&"年","-") -> 2025年 | B6: =IFERROR(YEAR(F6)&"年"&MONTH(F6)&"月","-") -> 2025年9月 | C6: 官旗 | D6: 智慧厨房 | E6: 0 | F6: 2025-09-02 | G6: j***f | H6: 10172530525873 | I6: 德玛仕（DEMASHI）智能智慧厨房食堂 食安智能留样仪留样机留样秤 自动称重 食品菜品 保存日期标签打印留样仪RX1011 自动称重丨自动拍照丨可导数据 | J6: 蔡梦飞 | K6: 非询单 | L6: 未成交 | M6: 1ff545488743c214882b4998326d1592 | N6: =COUNTIF(M:M,M6) -> 1
A7: =IFERROR(YEAR(F7)&"年","-") -> 2025年 | B7: =IFERROR(YEAR(F7)&"年"&MONTH(F7)&"月","-") -> 2025年9月 | C7: 官旗 | D7: 智慧厨房 | E7: 0 | F7: 2025-09-03 | G7: j***j | H7: 10162205073104 | I7: 德玛仕（DEMASHI）智能食堂厨房自助视觉识别智能双屏 刷卡扫码人脸识别三合一支付点餐结算机双屏人脸识别结算机 | J7: 许炎宏 | K7: 询单 | L7: 未成交 | M7: 055b17bc5805d0713b0b4234090d4cda | N7: =COUNTIF(M:M,M7) -> 1
A8: =IFERROR(YEAR(F8)&"年","-") -> 2025年 | B8: =IFERROR(YEAR(F8)&"年"&MONTH(F8)&"月","-") -> 2025年9月 | C8: 官旗 | D8: 智慧厨房 | E8: 0 | F8: 2025-09-04 | G8: j***2 | H8: 10175269720969 | I8: 德玛仕（DEMASHI）食品留样冰箱柜 冷藏柜保鲜柜商用展示柜 生物实验室设备学校幼儿园食堂公司用 食物冷藏保鲜商用 智能留样仪丨留样自动记录丨可报表导出 | J8: 许炎宏 | K8: 询单 | L8: 未成交 | M8: 2380f8bc2c34c62ecd5410a2b811f317 | N8: =COUNTIF(M:M,M8) -> 1
A9: =IFERROR(YEAR(F9)&"年","-") -> 2025年 | B9: =IFERROR(YEAR(F9)&"年"&MONTH(F9)&"月","-") -> 2025年9月 | C9: 官旗 | D9: 智慧厨房 | E9: 0 | F9: 2025-09-06 | G9: j***9 | H9: 10162203268678 | I9: 德玛仕（DEMASHI）智能智慧食堂厨房 智能出入库磅秤 进销存报表导出 商用高精度精准 不锈钢防水充电可移动 物联网 单机版丨无需联网丨可称150KG | J9: 刘惠雯 | K9: 询单 | L9: 未成交 | M9: eab720abb82466666e330945119ec057 | N9: =COUNTIF(M:M,M9) -> 1
A10: =IFERROR(YEAR(F10)&"年","-") -> 2025年 | B10: =IFERROR(YEAR(F10)&"年"&MONTH(F10)&"月","-") -> 2025年9月 | C10: 官旗 | D10: 智慧厨房 | E10: 279 | F10: 2025-09-17 | G10: j***w | H10: 10175269720969 | I10: 德玛仕（DEMASHI）食品留样冰箱柜 冷藏柜保鲜柜商用展示柜 生物实验室设备学校幼儿园食堂公司用 食物冷藏保鲜商用 智能留样仪丨留样自动记录丨可报表导出 | J10: 陈满红 | K10: 非询单 | L10: 未成交 | M10: f433845bda198b71e6ac9a7a5caf3933 | N10: =COUNTIF(M:M,M10) -> 2
A11: =IFERROR(YEAR(F11)&"年","-") -> 2025年 | B11: =IFERROR(YEAR(F11)&"年"&MONTH(F11)&"月","-") -> 2025年10月 | C11: 官旗 | D11: 智慧厨房 | E11: 0 | F11: 2025-10-05 | G11: x***3 | H11: 10175269720969 | I11: 德玛仕（DEMASHI）食品留样冰箱柜 冷藏柜保鲜柜商用展示柜 生物实验室设备学校幼儿园食堂公司用 食物冷藏保鲜商用 智能留样仪丨留样自动记录丨可报表导出 | J11: 林静宜 | K11: 询单 | L11: 未成交 | M11: bd6fe52b5cf596fa78801286f728618c | N11: =COUNTIF(M:M,M11) -> 1
A12: =IFERROR(YEAR(F12)&"年","-") -> 2025年 | B12: =IFERROR(YEAR(F12)&"年"&MONTH(F12)&"月","-") -> 2025年10月 | C12: 官旗 | D12: 智慧厨房 | E12: 0 | F12: 2025-10-07 | G12: w***6 | H12: 10186484654926 | I12: 德玛仕（DEMASHI）商用豆浆机大容量浆渣分离早餐店单位食堂用全自动磨煮一体大型免煮全自动打玉米汁米糊五谷豆浆机 【学校优选】智能食品留样仪丨符合食品安全 | J12: 刘惠雯 | K12: 询单 | L12: 未成交 | M12: 630a6114829f575bf94c4e2f937d6cd0 | N12: =COUNTIF(M:M,M12) -> 2
A13: =IFERROR(YEAR(F13)&"年","-") -> 2025年 | B13: =IFERROR(YEAR(F13)&"年"&MONTH(F13)&"月","-") -> 2025年10月 | C13: 官旗 | D13: 智慧厨房 | E13: 0 | F13: 2025-10-07 | G13: w***6 | H13: 10162200870892 | I13: 德玛仕（DEMASHI）智慧智能厨房食堂 食安智能留样仪留样机留样秤 自动称重 食品菜品 保存日期标签打印一体机 智能留样仪丨留样自动记录丨可报表导出 | J13: 刘惠雯 | K13: 询单 | L13: 未成交 | M13: 630a6114829f575bf94c4e2f937d6cd0 | N13: =COUNTIF(M:M,M13) -> 2
... A18: =IFERROR(YEAR(F18)&"年","-") -> 2025年 | B18: =IFERROR(YEAR(F18)&"年"&MONTH(F18)&"月","-") -> 2025年10月 | C18: 官旗 | D18: 智慧厨房 | E18: 0 | F18: 2025-10-21 | G18: j***b | H18: 10175269720969 | I18: 德玛仕（DEMASHI）食品留样冰箱柜 冷藏柜保鲜柜商用展示柜 生物实验室设备学校幼儿园食堂公司用 食物冷藏保鲜商用 智能留样仪丨留样自动记录丨可报表导出 | J18: 许炎宏 | K18: 询单 | L18: 未成交 | M18: e905c1150bd78eebb472d56be0fce5de | N18: =COUNTIF(M:M,M18) -> 1
A19: =IFERROR(YEAR(F19)&"年","-") -> 2025年 | B19: =IFERROR(YEAR(F19)&"年"&MONTH(F19)&"月","-") -> 2025年10月 | C19: 官旗 | D19: 智慧厨房 | E19: #VALUE! | F19: 2025-10-22 | G19: j***o | H19: 10186484654926 | I19: 德玛仕（DEMASHI）商用豆浆机大容量浆渣分离早餐店单位食堂用全自动磨煮一体大型免煮全自动打玉米汁米糊五谷豆浆机 【学校优选】智能食品留样仪丨符合食品安全 | J19: 陈冠中 | K19: 询单 | L19: 未成交 | M19: e28acbcf7b905151aef4317303966937 | N19: =COUNTIF(M:M,M19) -> 1
A20: =IFERROR(YEAR(F20)&"年","-") -> 2025年 | B20: =IFERROR(YEAR(F20)&"年"&MONTH(F20)&"月","-") -> 2025年10月 | C20: 官旗 | D20: 智慧厨房 | E20: 0 | F20: 2025-10-24 | G20: 小***悠 | H20: 10174209434926 | I20: 德玛仕（DEMASHI）智能智慧厨房食堂 双屏视觉结算机 台式挂式人脸识别 刷卡刷脸刷码高精度灵敏 食堂学校企业酒店 挂式智慧双屏结算机丨多种支付方式丨记录随时看 | J20: 冯俊燊 | K20: 询单 | L20: 未成交 | M20: c5e72fc7aec8e58e37623e0f5ae5544d | N20: =COUNTIF(M:M,M20) -> 1
A21: =IFERROR(YEAR(F21)&"年","-") -> 2025年 | B21: =IFERROR(YEAR(F21)&"年"&MONTH(F21)&"月","-") -> 2025年10月 | C21: 官旗 | D21: 智慧厨房 | E21: 0 | F21: 2025-10-24 | G21: j***8 | H21: 10175269720969 | I21: 德玛仕（DEMASHI）食品留样冰箱柜 冷藏柜保鲜柜商用展示柜 生物实验室设备学校幼儿园食堂公司用 食物冷藏保鲜商用 智能留样仪丨留样自动记录丨可报表导出 | J21: 许炎宏 | K21: 询单 | L21: 未成交 | M21: 6e4f054e617b7186f9df4d531b3fc2f2 | N21: =COUNTIF(M:M,M21) -> 1
A22: =IFERROR(YEAR(F22)&"年","-") -> 2025年 | B22: =IFERROR(YEAR(F22)&"年"&MONTH(F22)&"月","-") -> 2025年10月 | C22: 官旗 | D22: 智慧厨房 | E22: 0 | F22: 2025-10-29 | G22: j***1 | H22: 10175269720969 | I22: 德玛仕（DEMASHI）食品留样冰箱柜 冷藏柜保鲜柜商用展示柜 生物实验室设备学校幼儿园食堂公司用 食物冷藏保鲜商用 智能留样仪丨留样自动记录丨可报表导出 | J22: 陈满红 | K22: 询单 | L22: 未成交 | M22: fb524deb4106b46bc3aad00b48cddbc7 | N22: =COUNTIF(M:M,M22) -> 1
A23: =IFERROR(YEAR(F23)&"年","-") -> 2025年 | B23: =IFERROR(YEAR(F23)&"年"&MONTH(F23)&"月","-") -> 2025年10月 | C23: 官旗 | D23: 智慧厨房 | E23: 0 | F23: 2025-10-29 | G23: j***a | H23: 10175269720969 | I23: 德玛仕（DEMASHI）食品留样冰箱柜 冷藏柜保鲜柜商用展示柜 生物实验室设备学校幼儿园食堂公司用 食物冷藏保鲜商用 智能留样仪丨留样自动记录丨可报表导出 | J23: 周远锋 | K23: 非询单 | L23: 未成交 | M23: 04e29b433396557af23acf4a1dbc5ae0 | N23: =COUNTIF(M:M,M23) -> 1
A24: =IFERROR(YEAR(F24)&"年","-") -> 2025年 | B24: =IFERROR(YEAR(F24)&"年"&MONTH(F24)&"月","-") -> 2025年10月 | C24: 官旗 | D24: 智慧厨房 | E24: 4043.02 | F24: 2025-10-31 | G24: 5***m | H24: 10172530525873 | I24: 德玛仕（DEMASHI）智能智慧厨房食堂 食安智能留样仪留样机留样秤 自动称重 食品菜品 保存日期标签打印留样仪RX1011 自动称重丨自动拍照丨可导数据 | J24: 杨雯雯 | K24: 非询单 | L24: 未成交 | M24: 5ff36c9ae65312f367a75d44f6515d73 | N24: =COUNTIF(M:M,M24) -> 2
A25: =IFERROR(YEAR(F25)&"年","-") -> 2025年 | B25: =IFERROR(YEAR(F25)&"年"&MONTH(F25)&"月","-") -> 2025年10月 | C25: 官旗 | D25: 智慧厨房 | E25: 4043.02 | F25: 2025-10-31 | G25: 5***m | H25: 10172530525873 | I25: 德玛仕（DEMASHI）智能智慧厨房食堂 食安智能留样仪留样机留样秤 自动称重 食品菜品 保存日期标签打印留样仪RX1011 自动称重丨自动拍照丨可导数据 | J25: 蔡梦飞 | K25: 询单 | L25: 成交 | M25: 5ff36c9ae65312f367a75d44f6515d73 | N25: =COUNTIF(M:M,M25) -> 2
A26: =IFERROR(YEAR(F26)&"年","-") -> 2025年 | B26: =IFERROR(YEAR(F26)&"年"&MONTH(F26)&"月","-") -> 2025年10月 | C26: 官旗 | D26: 智慧厨房 | E26: 0 | F26: 2025-10-31 | G26: j***c | H26: 10187041017441 | I26: 德玛仕（DEMASHI）商用四门六门冰箱保鲜柜冷藏冷冻双温立式厨房冰柜四开门冰箱商用 150KG磅秤【单机版】无需联网T600-150A | J26: 许炎宏 | K26: 非询单 | L26: 未成交 | M26: 09e97b21c81abab0df081ad08e8b6f2a | N26: =COUNTIF(M:M,M26) -> 1
A27: =IFERROR(YEAR(F27)&"年","-") -> 2025年 | B27: =IFERROR(YEAR(F27)&"年"&MONTH(F27)&"月","-") -> 2025年10月 | C27: 官旗 | D27: 智慧厨房 | E27: 0 | F27: 2025-10-31 | G27: z***3 | H27: 10175269720969 | I27: 德玛仕（DEMASHI）食品留样冰箱柜 冷藏柜保鲜柜商用展示柜 生物实验室设备学校幼儿园食堂公司用 食物冷藏保鲜商用 智能留样仪丨留样自动记录丨可报表导出 | J27: 许炎宏 | K27: 非询单 | L27: 未成交 | M27: 3e0fbd4891b33b5b96c669ce7037b683 | N27: =COUNTIF(M:M,M27) -> 1
A28: =IFERROR(YEAR(F28)&"年","-") -> 2025年 | B28: =IFERROR(YEAR(F28)&"年"&MONTH(F28)&"月","-") -> 2025年11月 | C28: 官旗 | D28: 智慧厨房 | E28: 0 | F28: 2025-11-04 | G28: 远***芬 | H28: 10187041017440 | I28: 德玛仕（DEMASHI）商用四门六门冰箱保鲜柜冷藏冷冻双温立式厨房冰柜四开门冰箱商用 150KG磅秤【网络版】联网存储T600-150A | J28: 陈绮雯 | K28: 询单 | L28: 未成交 | M28: d0d5169d087681cadd43776fb5b17bce | N28: =COUNTIF(M:M,M28) -> 1
A29: =IFERROR(YEAR(F29)&"年","-") -> 2025年 | B29: =IFERROR(YEAR(F29)&"年"&MONTH(F29)&"月","-") -> 2025年11月 | C29: 官旗 | D29: 智慧厨房 | E29: 0 | F29: 2025-11-05 | G29: 李***7 | H29: 10162200870892 | I29: 德玛仕（DEMASHI）智慧智能厨房食堂 食安智能留样仪留样机留样秤 自动称重 食品菜品 保存日期标签打印一体机 智能留样仪丨留样自动记录丨可报表导出 | J29: 陈满红 | K29: 询单 | L29: 未成交 | M29: 4a8f6718c4fdbbcf5bb0b4390e4ed4b7 | N29: =COUNTIF(M:M,M29) -> 1
A30: =IFERROR(YEAR(F30)&"年","-") -> 2025年 | B30: =IFERROR(YEAR(F30)&"年"&MONTH(F30)&"月","-") -> 2025年11月 | C30: 官旗 | D30: 智慧厨房 | E30: 0 | F30: 2025-11-06 | G30: j***g | H30: 10175269720969 | I30: 德玛仕（DEMASHI）食品留样冰箱柜 冷藏柜保鲜柜商用展示柜 生物实验室设备学校幼儿园食堂公司用 食物冷藏保鲜商用 智能留样仪丨留样自动记录丨可报表导出 | J30: 罗广强 | K30: 询单 | L30: 未成交 | M30: d7405c361e8a72def21417c13b485646 | N30: =COUNTIF(M:M,M30) -> 1
A31: =IFERROR(YEAR(F31)&"年","-") -> 2025年 | B31: =IFERROR(YEAR(F31)&"年"&MONTH(F31)&"月","-") -> 2025年11月 | C31: 官旗 | D31: 智慧厨房 | E31: 0 | F31: 2025-11-10 | G31: j***d | H31: 10175269720969 | I31: 德玛仕（DEMASHI）食品留样冰箱柜 冷藏柜保鲜柜商用展示柜 生物实验室设备学校幼儿园食堂公司用 食物冷藏保鲜商用 智能留样仪丨留样自动记录丨可报表导出 | J31: 刘惠雯 | K31: 询单 | L31: 未成交 | M31: 419aafbf9dbe78d9938001184feae163 | N31: =COUNTIF(M:M,M31) -> 1
... A34: =IFERROR(YEAR(F34)&"年","-") -> 2025年 | B34: =IFERROR(YEAR(F34)&"年"&MONTH(F34)&"月","-") -> 2025年11月 | C34: 官旗 | D34: 智慧厨房 | E34: 0 | F34: 2025-11-25 | G34: j***i | H34: 10175269720969 | I34: 德玛仕（DEMASHI）食品留样冰箱柜 冷藏柜保鲜柜商用展示柜 生物实验室设备学校幼儿园食堂公司用 食物冷藏保鲜商用 智能留样仪丨留样自动记录丨可报表导出 | J34: 梁慧怡 | K34: 非询单 | L34: 未成交 | M34: cd06bd780025a4770ee9f55bf8e95570 | N34: =COUNTIF(M:M,M34) -> 1
A35: =IFERROR(YEAR(F35)&"年","-") -> 2025年 | B35: =IFERROR(YEAR(F35)&"年"&MONTH(F35)&"月","-") -> 2025年11月 | C35: 官旗 | D35: 智慧厨房 | E35: #VALUE! | F35: 2025-11-25 | G35: j***c | H35: 10200543466910 | I35: 德玛仕（DEMASHI）大功率电磁炉商用电磁灶台大锅灶单头双头电灶台凹面学校酒店食堂厨房炒菜汤锅炉 【学校食堂】出入库磅秤丨T600-150A单机版 | J35: 刘惠雯 | K35: 询单 | L35: 未成交 | M35: d54766c8de7bc2fa790a730cc51e3e9e | N35: =COUNTIF(M:M,M35) -> 3
A36: =IFERROR(YEAR(F36)&"年","-") -> 2025年 | B36: =IFERROR(YEAR(F36)&"年"&MONTH(F36)&"月","-") -> 2025年11月 | C36: 官旗 | D36: 智慧厨房 | E36: 0 | F36: 2025-11-25 | G36: j***2 | H36: 10172530525873 | I36: 德玛仕（DEMASHI）智能智慧厨房食堂 食安智能留样仪留样机留样秤 自动称重 食品菜品 保存日期标签打印留样仪RX1011 自动称重丨自动拍照丨可导数据 | J36: 蔡梦飞 | K36: 询单 | L36: 未成交 | M36: 40547029a75399436211dc276af3367f | N36: =COUNTIF(M:M,M36) -> 1
A37: =IFERROR(YEAR(F37)&"年","-") -> 2025年 | B37: =IFERROR(YEAR(F37)&"年"&MONTH(F37)&"月","-") -> 2025年11月 | C37: 官旗 | D37: 智慧厨房 | E37: 0 | F37: 2025-11-27 | G37: j***a | H37: 10162200870892 | I37: 德玛仕（DEMASHI）智慧智能厨房食堂 食安智能留样仪留样机留样秤 自动称重 食品菜品 保存日期标签打印一体机 智能留样仪丨留样自动记录丨可报表导出 | J37: 吴仁迪 | K37: 询单 | L37: 未成交 | M37: 09197076a758024edd81e9ff3f4d9b1d | N37: =COUNTIF(M:M,M37) -> 2
A38: =IFERROR(YEAR(F38)&"年","-") -> 2025年 | B38: =IFERROR(YEAR(F38)&"年"&MONTH(F38)&"月","-") -> 2025年11月 | C38: 官旗 | D38: 智慧厨房 | E38: 0 | F38: 2025-11-30 | G38: j***5 | H38: 10162203268679 | I38: 德玛仕（DEMASHI）智能智慧食堂厨房 智能出入库磅秤 进销存报表导出 商用高精度精准 不锈钢防水充电可移动 物联网 网络版丨物联组网丨可称300KG | J38: 蔡梦飞 | K38: 询单 | L38: 未成交 | M38: ab5dc70b160903482370686f6c742fb1 | N38: =COUNTIF(M:M,M38) -> 1
A39: =IFERROR(YEAR(F39)&"年","-") -> 2025年 | B39: =IFERROR(YEAR(F39)&"年"&MONTH(F39)&"月","-") -> 2025年12月 | C39: 官旗 | D39: 智慧厨房 | E39: 0 | F39: 2025-12-02 | G39: 五***云 | H39: 10198766314146 | I39: 德玛仕（DEMASHI）智能智慧食堂厨房 智能出入库磅秤 进销存报表导出 商用高精度精准 不锈钢防水充电可移动 物联网 赠送10年云服务器丨库存管理丨库存监控 | J39: 吴仁迪 | K39: 询单 | L39: 未成交 | M39: 181fd2fce416e51dc8c945876fde7899 | N39: =COUNTIF(M:M,M39) -> 1
A40: =IFERROR(YEAR(F40)&"年","-") -> 2025年 | B40: =IFERROR(YEAR(F40)&"年"&MONTH(F40)&"月","-") -> 2025年12月 | C40: 官旗 | D40: 智慧厨房 | E40: 0 | F40: 2025-12-05 | G40: j***2 | H40: 10175269720969 | I40: 德玛仕（DEMASHI）食品留样冰箱柜 冷藏柜保鲜柜商用展示柜 生物实验室设备学校幼儿园食堂公司用 食物冷藏保鲜商用 智能留样仪丨留样自动记录丨可报表导出 | J40: 罗广强 | K40: 非询单 | L40: 未成交 | M40: 3aa29aac0ab565d025a0977a39dc9e4f | N40: =COUNTIF(M:M,M40) -> 3
A41: =IFERROR(YEAR(F41)&"年","-") -> 2025年 | B41: =IFERROR(YEAR(F41)&"年"&MONTH(F41)&"月","-") -> 2025年12月 | C41: 官旗 | D41: 智慧厨房 | E41: 0 | F41: 2025-12-05 | G41: j***m | H41: 10175269720969 | I41: 德玛仕（DEMASHI）食品留样冰箱柜 冷藏柜保鲜柜商用展示柜 生物实验室设备学校幼儿园食堂公司用 食物冷藏保鲜商用 智能留样仪丨留样自动记录丨可报表导出 | J41: 罗广强 | K41: 非询单 | L41: 成交 | M41: 38662c607c16521b903ec5a3026d8bb0 | N41: =COUNTIF(M:M,M41) -> 1
A42: =IFERROR(YEAR(F42)&"年","-") -> 2025年 | B42: =IFERROR(YEAR(F42)&"年"&MONTH(F42)&"月","-") -> 2025年12月 | C42: 官旗 | D42: 智慧厨房 | E42: 0 | F42: 2025-12-06 | G42: j***i | H42: 10162200870892 | I42: 德玛仕（DEMASHI）智慧智能厨房食堂 食安智能留样仪留样机留样秤 自动称重 食品菜品 保存日期标签打印一体机 智能留样仪丨留样自动记录丨可报表导出 | J42: 马玉 | K42: 询单 | L42: 未成交 | M42: 8ac4a9b56d3e3988c082beb6f23f741c | N42: =COUNTIF(M:M,M42) -> 1
A43: =IFERROR(YEAR(F43)&"年","-") -> 2025年 | B43: =IFERROR(YEAR(F43)&"年"&MONTH(F43)&"月","-") -> 2025年12月 | C43: 官旗 | D43: 智慧厨房 | E43: 0 | F43: 2025-12-07 | G43: j***4 | H43: 10197091535141 | I43: 德玛仕智慧智能厨房食堂 视觉自助计量打餐终端 结算计费一体机 人脸识别自助多种支付 自助餐称重 视觉自助计量打餐终端 | J43: 蔡梦飞 | K43: 询单 | L43: 未成交 | M43: 2530d86828d480df45400d51386301c8 | N43: =COUNTIF(M:M,M43) -> 1
A44: =IFERROR(YEAR(F44)&"年","-") -> 2025年 | B44: =IFERROR(YEAR(F44)&"年"&MONTH(F44)&"月","-") -> 2025年12月 | C44: 官旗 | D44: 智慧厨房 | E44: 0 | F44: 2025-12-08 | G44: 1***p | H44: 10202847203709 | I44: 德玛仕（DEMASHI）【免费包安装】商用蒸饭柜蒸饭车单位学校蒸箱商用蒸饭箱蒸饭机食堂饭堂 安全蒸柜蒸包炉 【学校食堂】智能晨检仪丨C200 | J44: 许炎宏 | K44: 非询单 | L44: 未成交 | M44: 2116e5b373857f2c228d6eccf4266980 | N44: =COUNTIF(M:M,M44) -> 1
A45: =IFERROR(YEAR(F45)&"年","-") -> 2025年 | B45: =IFERROR(YEAR(F45)&"年"&MONTH(F45)&"月","-") -> 2025年12月 | C45: 官旗 | D45: 智慧厨房 | E45: 0 | F45: 2025-12-09 | G45: j***d | H45: 10172530525873 | I45: 德玛仕（DEMASHI）智能智慧厨房食堂 食安智能留样仪留样机留样秤 自动称重 食品菜品 保存日期标签打印留样仪RX1011 自动称重丨自动拍照丨可导数据 | J45: 李想 | K45: 非询单 | L45: 未成交 | M45: 897b41253ebd7e0049251f1eff08641d | N45: =COUNTIF(M:M,M45) -> 1
A46: =IFERROR(YEAR(F46)&"年","-") -> 2025年 | B46: =IFERROR(YEAR(F46)&"年"&MONTH(F46)&"月","-") -> 2025年12月 | C46: 官旗 | D46: 智慧厨房 | E46: 0 | F46: 2025-12-09 | G46: j***2 | H46: 10175269720969 | I46: 德玛仕（DEMASHI）食品留样冰箱柜 冷藏柜保鲜柜商用展示柜 生物实验室设备学校幼儿园食堂公司用 食物冷藏保鲜商用 智能留样仪丨留样自动记录丨可报表导出 | J46: 黄植胜 | K46: 非询单 | L46: 未成交 | M46: 3aa29aac0ab565d025a0977a39dc9e4f | N46: =COUNTIF(M:M,M46) -> 3
A47: =IFERROR(YEAR(F47)&"年","-") -> 2025年 | B47: =IFERROR(YEAR(F47)&"年"&MONTH(F47)&"月","-") -> 2025年12月 | C47: 官旗 | D47: 智慧厨房 | E47: 0 | F47: 2025-12-09 | G47: j***c | H47: 10175269720969 | I47: 德玛仕（DEMASHI）食品留样冰箱柜 冷藏柜保鲜柜商用展示柜 生物实验室设备学校幼儿园食堂公司用 食物冷藏保鲜商用 智能留样仪丨留样自动记录丨可报表导出 | J47: 蔡梦飞 | K47: 询单 | L47: 未成交 | M47: 6fc56c115feed2794b1628757a2c013b | N47: =COUNTIF(M:M,M47) -> 3
... A56: =IFERROR(YEAR(F56)&"年","-") -> 2025年 | B56: =IFERROR(YEAR(F56)&"年"&MONTH(F56)&"月","-") -> 2025年12月 | C56: FCS | D56: 智慧厨房 | E56: 0 | F56: 2025-12-18 | G56: j***o | H56: 10198265272970 | I56: 德玛仕（DEMASHI）消毒柜商用双开门消毒碗柜烘干消毒一体机酒店餐饮饭店厨房食堂学校用餐具杯子分餐盘碗筷柜大容量 【智慧餐厅】200人套餐丨无人售卖秤+智能绑盘机 | J56: 陈满红 | K56: 询单 | L56: 未成交 | M56: 65be3dd76120b253bd962e95cd5eab87 | N56: =COUNTIF(M:M,M56) -> 1
A57: =IFERROR(YEAR(F57)&"年","-") -> 2025年 | B57: =IFERROR(YEAR(F57)&"年"&MONTH(F57)&"月","-") -> 2025年12月 | C57: FCS | D57: 智慧厨房 | E57: #VALUE! | F57: 2025-12-23 | G57: j***7 | H57: 10205559971672 | I57: 德玛仕（DEMASHI）智慧智能厨房食堂 食安智能留样仪留样机留样秤 自动称重 食品菜品 保存日期标签打印一体机 智能晨检仪丨C2000 | J57: 蔡梦飞 | K57: 询单 | L57: 未成交 | M57: 9d45c9ec48dc1f34bc8e95a14f82f84d | N57: =COUNTIF(M:M,M57) -> 1
A58: =IFERROR(YEAR(F58)&"年","-") -> 2025年 | B58: =IFERROR(YEAR(F58)&"年"&MONTH(F58)&"月","-") -> 2025年4月 | C58: 西厨 | D58: 智慧厨房 | E58: 0 | F58: 2025-04-02 | G58: j***b | H58: 10107955108310 | I58: 德玛仕智能称重称电子秤商用高精度计数秤精密称重台秤克称工业精准计重电子称 智能称重称 | J58: 吴浩彦 | K58: 询单 | L58: 未成交 | M58: b15fb4be5203b322c0ae316909bd9618 | N58: =COUNTIF(M:M,M58) -> 1
A59: =IFERROR(YEAR(F59)&"年","-") -> 2025年 | B59: =IFERROR(YEAR(F59)&"年"&MONTH(F59)&"月","-") -> 2025年8月 | C59: 西厨 | D59: 智慧厨房 | E59: 0 | F59: 2025-08-07 | G59: m***0 | H59: 10107955108310 | I59: 德玛仕智能称重称电子秤商用高精度计数秤精密称重台秤克称工业精准计重电子称 智能称重称 | J59: 许炎宏 | K59: 非询单 | L59: 未成交 | M59: e4f2f0665ea553c33c03d42736c9ef0e | N59: =COUNTIF(M:M,M59) -> 1
A60: =IFERROR(YEAR(F60)&"年","-") -> 2025年 | B60: =IFERROR(YEAR(F60)&"年"&MONTH(F60)&"月","-") -> 2025年10月 | C60: 西厨 | D60: 智慧厨房 | E60: 0 | F60: 2025-10-11 | G60: j***5 | H60: 10176475918498 | I60: 德玛仕智慧智能厨房食堂进销存报表导出 智能出入库磅秤 【网络版】联网存储丨可称300kg | J60: 许炎宏 | K60: 询单 | L60: 未成交 | M60: f60ac272e09e99b59e03cb4e12461c0b | N60: =COUNTIF(M:M,M60) -> 2
A61: =IFERROR(YEAR(F61)&"年","-") -> 2025年 | B61: =IFERROR(YEAR(F61)&"年"&MONTH(F61)&"月","-") -> 2025年10月 | C61: 西厨 | D61: 智慧厨房 | E61: 0 | F61: 2025-10-11 | G61: j***5 | H61: 10176475918498 | I61: 德玛仕智慧智能厨房食堂进销存报表导出 智能出入库磅秤 【网络版】联网存储丨可称300kg | J61: 马玉 | K61: 询单 | L61: 未成交 | M61: f60ac272e09e99b59e03cb4e12461c0b | N61: =COUNTIF(M:M,M61) -> 2
A62: =IFERROR(YEAR(F62)&"年","-") -> 2025年 | B62: =IFERROR(YEAR(F62)&"年"&MONTH(F62)&"月","-") -> 2025年11月 | C62: 西厨 | D62: 智慧厨房 | E62: 0 | F62: 2025-11-19 | G62: j***6 | H62: 10199026465216 | I62: 德玛仕（DEMASHI）商用油烟机智能抽油烟机 食堂饭店单位厨房用 油烟排烟净化机大吸力不锈钢吸油烟机 智能留样仪丨可导报表标签丨RX1011 | J62: 许炎宏 | K62: 非询单 | L62: 未成交 | M62: 039b6ef81a021590457add49b955e7fe | N62: =COUNTIF(M:M,M62) -> 1
A63: =IFERROR(YEAR(F63)&"年","-") -> 2025年 | B63: =IFERROR(YEAR(F63)&"年"&MONTH(F63)&"月","-") -> 2025年11月 | C63: 西厨 | D63: 智慧厨房 | E63: 12636 | F63: 2025-11-27 | G63: j***e | H63: 10198258287734 | I63: 德玛仕（DEMASHI）高原款食品留样柜蔬菜保鲜柜冷藏柜商用高原展示柜立式冰箱果蔬保鲜柜单位食堂饭堂水果保鲜柜 智能留样仪丨可导报表标签丨RX1011 | J63: 许炎宏 | K63: 询单 | L63: 成交 | M63: 7d6d77ca5afc5b2cab1e3b13d77dc7ae | N63: =COUNTIF(M:M,M63) -> 3
A64: =IFERROR(YEAR(F64)&"年","-") -> 2025年 | B64: =IFERROR(YEAR(F64)&"年"&MONTH(F64)&"月","-") -> 2025年12月 | C64: 西厨 | D64: 智慧厨房 | E64: 0 | F64: 2025-12-05 | G64: j***b | H64: 10203225618564 | I64: 德玛仕（DEMASHI）智慧智能厨房食堂 食安智能留样仪部队用打菜机 自动称重 食品菜品 保存日期标签打印收银机 【AI监测】后厨AI管理服务一体机丨WC8 | J64: 许炎宏 | K64: 询单 | L64: 未成交 | M64: 5259dc09fd445873f8eece8aae5e44c5 | N64: =COUNTIF(M:M,M64) -> 1
A65: =IFERROR(YEAR(F65)&"年","-") -> 2025年 | B65: =IFERROR(YEAR(F65)&"年"&MONTH(F65)&"月","-") -> 2025年12月 | C65: 西厨 | D65: 智慧厨房 | E65: 12636 | F65: 2025-12-12 | G65: j***e | H65: 10198258287734 | I65: 德玛仕（DEMASHI）高原款食品留样柜蔬菜保鲜柜冷藏柜商用高原展示柜立式冰箱果蔬保鲜柜单位食堂饭堂水果保鲜柜 智能留样仪丨可导报表标签丨RX1011 | J65: 王帅康 | K65: 非询单 | L65: 未成交 | M65: 7d6d77ca5afc5b2cab1e3b13d77dc7ae | N65: =COUNTIF(M:M,M65) -> 3
A66: =IFERROR(YEAR(F66)&"年","-") -> 2025年 | B66: =IFERROR(YEAR(F66)&"年"&MONTH(F66)&"月","-") -> 2025年8月 | C66: 饮水 | D66: 智慧厨房 | E66: 0 | F66: 2025-08-28 | G66: j***d | H66: 100119912611 | I66: 德玛仕（DEMASHI）智能食堂厨房出入库磅秤 进销存报表导出 300KG称重 学校单位食堂用 商用净水设备网络版T600-300A | J66: 陈满红 | K66: 询单 | L66: 未成交 | M66: 2e22c0fe32cadf99cc329371beaaba2b | N66: =COUNTIF(M:M,M66) -> 1
A67: =IFERROR(YEAR(F67)&"年","-") -> 2025年 | B67: =IFERROR(YEAR(F67)&"年"&MONTH(F67)&"月","-") -> 2025年7月 | C67: 工程 | D67: 智慧厨房 | E67: 0 | F67: 2025-07-01 | G67: j***b | H67: 100185439639 | I67: 德玛仕（DEMASHI）智慧厨房食品留样柜幼儿园学校公司食堂后厨标签打印智能留样记录仪自动称重拍照食安留样仪RX1011 | J67: 朱燕霞 | K67: 询单 | L67: 未成交 | M67: cc51cd7d4021054fd117ef20bb086e3c | N67: =COUNTIF(M:M,M67) -> 2
A68: =IFERROR(YEAR(F68)&"年","-") -> 2025年 | B68: =IFERROR(YEAR(F68)&"年"&MONTH(F68)&"月","-") -> 2025年7月 | C68: 工程 | D68: 智慧厨房 | E68: 0 | F68: 2025-07-01 | G68: j***b | H68: 100185439639 | I68: 德玛仕（DEMASHI）智慧厨房食品留样柜幼儿园学校公司食堂后厨标签打印智能留样记录仪自动称重拍照食安留样仪RX1011 | J68: 许炎宏 | K68: 非询单 | L68: 未成交 | M68: cc51cd7d4021054fd117ef20bb086e3c | N68: =COUNTIF(M:M,M68) -> 2
A69: =IFERROR(YEAR(F69)&"年","-") -> 2025年 | B69: =IFERROR(YEAR(F69)&"年"&MONTH(F69)&"月","-") -> 2025年7月 | C69: 工程 | D69: 智慧厨房 | E69: 0 | F69: 2025-07-23 | G69: j***2 | H69: 100185439639 | I69: 德玛仕（DEMASHI）智慧厨房食品留样柜幼儿园学校公司食堂后厨标签打印智能留样记录仪自动称重拍照食安留样仪RX1011 | J69: 陈欣 | K69: 非询单 | L69: 未成交 | M69: 11de8e8b9b3c847a8d2179b31d3f2b07 | N69: =COUNTIF(M:M,M69) -> 1
... A83: =IFERROR(YEAR(F83)&"年","-") -> 2025年 | B83: =IFERROR(YEAR(F83)&"年"&MONTH(F83)&"月","-") -> 2025年8月 | C83: 工程 | D83: 智慧厨房 | E83: 0 | F83: 2025-08-12 | G83: j***a | H83: 100185439639 | I83: 德玛仕（DEMASHI）智慧厨房食品留样柜幼儿园学校公司食堂后厨标签打印智能留样记录仪自动称重拍照食安留样仪RX1011 | J83: 林静宜 | K83: 询单 | L83: 未成交 | M83: 14f64fbe3fa0751fb9fc20c90eeebe61 | N83: =COUNTIF(M:M,M83) -> 1
A84: =IFERROR(YEAR(F84)&"年","-") -> 2025年 | B84: =IFERROR(YEAR(F84)&"年"&MONTH(F84)&"月","-") -> 2025年8月 | C84: 工程 | D84: 智慧厨房 | E84: #VALUE! | F84: 2025-08-12 | G84: j***7 | H84: 100185439639 | I84: 德玛仕（DEMASHI）智慧厨房食品留样柜幼儿园学校公司食堂后厨标签打印智能留样记录仪自动称重拍照食安留样仪RX1011 | J84: 林静宜 | K84: 询单 | L84: 成交 | M84: cdb8d0b5b047d96c6514309e82558f79 | N84: =COUNTIF(M:M,M84) -> 3
A85: =IFERROR(YEAR(F85)&"年","-") -> 2025年 | B85: =IFERROR(YEAR(F85)&"年"&MONTH(F85)&"月","-") -> 2025年8月 | C85: 工程 | D85: 智慧厨房 | E85: 0 | F85: 2025-08-13 | G85: j***b | H85: 100185439639 | I85: 德玛仕（DEMASHI）智慧厨房食品留样柜幼儿园学校公司食堂后厨标签打印智能留样记录仪自动称重拍照食安留样仪RX1011 | J85: 许炎宏 | K85: 询单 | L85: 未成交 | M85: 2b157fd6ea7736575762b6aa05649531 | N85: =COUNTIF(M:M,M85) -> 3
A86: =IFERROR(YEAR(F86)&"年","-") -> 2025年 | B86: =IFERROR(YEAR(F86)&"年"&MONTH(F86)&"月","-") -> 2025年8月 | C86: 工程 | D86: 智慧厨房 | E86: #VALUE! | F86: 2025-08-13 | G86: j***7 | H86: 100251652724 | I86: 德玛仕（DEMASHI）智慧智能厨房食堂进销存报表导出 智能出入库磅秤 T600-150A（单机版 不锈钢） | J86: 许炎宏 | K86: 询单 | L86: 未成交 | M86: cdb8d0b5b047d96c6514309e82558f79 | N86: =COUNTIF(M:M,M86) -> 3
A87: =IFERROR(YEAR(F87)&"年","-") -> 2025年 | B87: =IFERROR(YEAR(F87)&"年"&MONTH(F87)&"月","-") -> 2025年8月 | C87: 工程 | D87: 智慧厨房 | E87: 0 | F87: 2025-08-13 | G87: w***i | H87: 100185439639 | I87: 德玛仕（DEMASHI）智慧厨房食品留样柜幼儿园学校公司食堂后厨标签打印智能留样记录仪自动称重拍照食安留样仪RX1011 | J87: 许炎宏 | K87: 询单 | L87: 未成交 | M87: 521ddebcbb89fa8d34a19066811fac8a | N87: =COUNTIF(M:M,M87) -> 2
A88: =IFERROR(YEAR(F88)&"年","-") -> 2025年 | B88: =IFERROR(YEAR(F88)&"年"&MONTH(F88)&"月","-") -> 2025年8月 | C88: 工程 | D88: 智慧厨房 | E88: 4530 | F88: 2025-08-14 | G88: w***f | H88: 100185439639 | I88: 德玛仕（DEMASHI）智慧厨房食品留样柜幼儿园学校公司食堂后厨标签打印智能留样记录仪自动称重拍照食安留样仪RX1011 | J88: 蔡梦飞 | K88: 非询单 | L88: 未成交 | M88: a5ef42208444c100f722e935bb7ea6a7 | N88: =COUNTIF(M:M,M88) -> 2
A89: =IFERROR(YEAR(F89)&"年","-") -> 2025年 | B89: =IFERROR(YEAR(F89)&"年"&MONTH(F89)&"月","-") -> 2025年8月 | C89: 工程 | D89: 智慧厨房 | E89: 0 | F89: 2025-08-14 | G89: 1***p | H89: 100185439639 | I89: 德玛仕（DEMASHI）智慧厨房食品留样柜幼儿园学校公司食堂后厨标签打印智能留样记录仪自动称重拍照食安留样仪RX1011 | J89: 许炎宏 | K89: 询单 | L89: 未成交 | M89: 0da2a34c85f59f50e90229c0a43e8414 | N89: =COUNTIF(M:M,M89) -> 1
A90: =IFERROR(YEAR(F90)&"年","-") -> 2025年 | B90: =IFERROR(YEAR(F90)&"年"&MONTH(F90)&"月","-") -> 2025年8月 | C90: 工程 | D90: 智慧厨房 | E90: 0 | F90: 2025-08-15 | G90: j***b | H90: 100185439639 | I90: 德玛仕（DEMASHI）智慧厨房食品留样柜幼儿园学校公司食堂后厨标签打印智能留样记录仪自动称重拍照食安留样仪RX1011 | J90: 周远锋 | K90: 非询单 | L90: 未成交 | M90: 2b157fd6ea7736575762b6aa05649531 | N90: =COUNTIF(M:M,M90) -> 3
A91: =IFERROR(YEAR(F91)&"年","-") -> 2025年 | B91: =IFERROR(YEAR(F91)&"年"&MONTH(F91)&"月","-") -> 2025年8月 | C91: 工程 | D91: 智慧厨房 | E91: 0 | F91: 2025-08-15 | G91: j***e | H91: 100185439639 | I91: 德玛仕（DEMASHI）智慧厨房食品留样柜幼儿园学校公司食堂后厨标签打印智能留样记录仪自动称重拍照食安留样仪RX1011 | J91: 林静宜 | K91: 询单 | L91: 未成交 | M91: f7fdc4995e15a7fdbb67a89fbcedc0b4 | N91: =COUNTIF(M:M,M91) -> 1
A92: =IFERROR(YEAR(F92)&"年","-") -> 2025年 | B92: =IFERROR(YEAR(F92)&"年"&MONTH(F92)&"月","-") -> 2025年8月 | C92: 工程 | D92: 智慧厨房 | E92: 0 | F92: 2025-08-15 | G92: j***b | H92: 100185439639 | I92: 德玛仕（DEMASHI）智慧厨房食品留样柜幼儿园学校公司食堂后厨标签打印智能留样记录仪自动称重拍照食安留样仪RX1011 | J92: 蔡梦飞 | K92: 非询单 | L92: 未成交 | M92: 2b157fd6ea7736575762b6aa05649531 | N92: =COUNTIF(M:M,M92) -> 3
A93: =IFERROR(YEAR(F93)&"年","-") -> 2025年 | B93: =IFERROR(YEAR(F93)&"年"&MONTH(F93)&"月","-") -> 2025年8月 | C93: 工程 | D93: 智慧厨房 | E93: 0 | F93: 2025-08-18 | G93: j***0 | H93: 100185439639 | I93: 德玛仕（DEMASHI）智慧厨房食品留样柜幼儿园学校公司食堂后厨标签打印智能留样记录仪自动称重拍照食安留样仪RX1011 | J93: 许炎宏 | K93: 非询单 | L93: 未成交 | M93: dd5a68d3100616d0dd97cd51fc4c57db | N93: =COUNTIF(M:M,M93) -> 1
A94: =IFERROR(YEAR(F94)&"年","-") -> 2025年 | B94: =IFERROR(YEAR(F94)&"年"&MONTH(F94)&"月","-") -> 2025年8月 | C94: 工程 | D94: 智慧厨房 | E94: 0 | F94: 2025-08-18 | G94: w***i | H94: 100185439639 | I94: 德玛仕（DEMASHI）智慧厨房食品留样柜幼儿园学校公司食堂后厨标签打印智能留样记录仪自动称重拍照食安留样仪RX1011 | J94: 许炎宏 | K94: 询单 | L94: 未成交 | M94: 521ddebcbb89fa8d34a19066811fac8a | N94: =COUNTIF(M:M,M94) -> 2
A95: =IFERROR(YEAR(F95)&"年","-") -> 2025年 | B95: =IFERROR(YEAR(F95)&"年"&MONTH(F95)&"月","-") -> 2025年8月 | C95: 工程 | D95: 智慧厨房 | E95: 4680 | F95: 2025-08-18 | G95: 阳***0 | H95: 100185439639 | I95: 德玛仕（DEMASHI）智慧厨房食品留样柜幼儿园学校公司食堂后厨标签打印智能留样记录仪自动称重拍照食安留样仪RX1011 | J95: 许炎宏 | K95: 非询单 | L95: 未成交 | M95: 806dfb2b688f67f512608a0b74be5864 | N95: =COUNTIF(M:M,M95) -> 3
A96: =IFERROR(YEAR(F96)&"年","-") -> 2025年 | B96: =IFERROR(YEAR(F96)&"年"&MONTH(F96)&"月","-") -> 2025年8月 | C96: 工程 | D96: 智慧厨房 | E96: 0 | F96: 2025-08-19 | G96: j***d | H96: 100185439639 | I96: 德玛仕（DEMASHI）智慧厨房食品留样柜幼儿园学校公司食堂后厨标签打印智能留样记录仪自动称重拍照食安留样仪RX1011 | J96: 吴仁迪 | K96: 非询单 | L96: 未成交 | M96: 304d147f7e7f88cdced9899ee80ed5f7 | N96: =COUNTIF(M:M,M96) -> 1
A97: =IFERROR(YEAR(F97)&"年","-") -> 2025年 | B97: =IFERROR(YEAR(F97)&"年"&MONTH(F97)&"月","-") -> 2025年8月 | C97: 工程 | D97: 智慧厨房 | E97: 0 | F97: 2025-08-19 | G97: j***e | H97: 100251652724 | I97: 德玛仕（DEMASHI）智慧智能厨房食堂进销存报表导出 智能出入库磅秤 T600-150A（单机版 不锈钢） | J97: 许炎宏 | K97: 询单 | L97: 未成交 | M97: 006ae5b849782559189433153b6fcc9a | N97: =COUNTIF(M:M,M97) -> 1
A98: =IFERROR(YEAR(F98)&"年","-") -> 2025年 | B98: =IFERROR(YEAR(F98)&"年"&MONTH(F98)&"月","-") -> 2025年8月 | C98: 工程 | D98: 智慧厨房 | E98: 0 | F98: 2025-08-20 | G98: 3***m | H98: 100185439639 | I98: 德玛仕（DEMASHI）智慧厨房食品留样柜幼儿园学校公司食堂后厨标签打印智能留样记录仪自动称重拍照食安留样仪RX1011 | J98: 吴仁迪 | K98: 询单 | L98: 未成交 | M98: 7325ed9be56b03cba1624b800e56d76d | N98: =COUNTIF(M:M,M98) -> 2
... A105: =IFERROR(YEAR(F105)&"年","-") -> 2025年 | B105: =IFERROR(YEAR(F105)&"年"&MONTH(F105)&"月","-") -> 2025年8月 | C105: 工程 | D105: 智慧厨房 | E105: 0 | F105: 2025-08-22 | G105: j***d | H105: 100185439639 | I105: 德玛仕（DEMASHI）智慧厨房食品留样柜幼儿园学校公司食堂后厨标签打印智能留样记录仪自动称重拍照食安留样仪RX1011 | J105: 罗栋铭 | K105: 询单 | L105: 未成交 | M105: b9539301ab04993aba18be2198dae42b | N105: =COUNTIF(M:M,M105) -> 1
A106: =IFERROR(YEAR(F106)&"年","-") -> 2025年 | B106: =IFERROR(YEAR(F106)&"年"&MONTH(F106)&"月","-") -> 2025年8月 | C106: 工程 | D106: 智慧厨房 | E106: #VALUE! | F106: 2025-08-23 | G106: j***f | H106: 100185439639 | I106: 德玛仕（DEMASHI）智慧厨房食品留样柜幼儿园学校公司食堂后厨标签打印智能留样记录仪自动称重拍照食安留样仪RX1011 | J106: 罗栋铭 | K106: 询单 | L106: 成交 | M106: c7403a5c95aa7424fd8704b7dc68af1c | N106: =COUNTIF(M:M,M106) -> 2
A107: =IFERROR(YEAR(F107)&"年","-") -> 2025年 | B107: =IFERROR(YEAR(F107)&"年"&MONTH(F107)&"月","-") -> 2025年8月 | C107: 工程 | D107: 智慧厨房 | E107: 0 | F107: 2025-08-23 | G107: 1***p | H107: 100185439639 | I107: 德玛仕（DEMASHI）智慧厨房食品留样柜幼儿园学校公司食堂后厨标签打印智能留样记录仪自动称重拍照食安留样仪RX1011 | J107: 林静宜 | K107: 询单 | L107: 未成交 | M107: 3d6f85d8cb6372c2a0851f2e84fe5a44 | N107: =COUNTIF(M:M,M107) -> 1
A108: =IFERROR(YEAR(F108)&"年","-") -> 2025年 | B108: =IFERROR(YEAR(F108)&"年"&MONTH(F108)&"月","-") -> 2025年8月 | C108: 工程 | D108: 智慧厨房 | E108: #VALUE! | F108: 2025-08-24 | G108: j***o | H108: 100185439639 | I108: 德玛仕（DEMASHI）智慧厨房食品留样柜幼儿园学校公司食堂后厨标签打印智能留样记录仪自动称重拍照食安留样仪RX1011 | J108: 林静宜 | K108: 询单 | L108: 未成交 | M108: fe8680fb07728c9458bcd3fb537752e8 | N108: =COUNTIF(M:M,M108) -> 1
A109: =IFERROR(YEAR(F109)&"年","-") -> 2025年 | B109: =IFERROR(YEAR(F109)&"年"&MONTH(F109)&"月","-") -> 2025年8月 | C109: 工程 | D109: 智慧厨房 | E109: 4680 | F109: 2025-08-24 | G109: 阳***0 | H109: 100185439639 | I109: 德玛仕（DEMASHI）智慧厨房食品留样柜幼儿园学校公司食堂后厨标签打印智能留样记录仪自动称重拍照食安留样仪RX1011 | J109: 林静宜 | K109: 非询单 | L109: 成交 | M109: 806dfb2b688f67f512608a0b74be5864 | N109: =COUNTIF(M:M,M109) -> 3
A110: =IFERROR(YEAR(F110)&"年","-") -> 2025年 | B110: =IFERROR(YEAR(F110)&"年"&MONTH(F110)&"月","-") -> 2025年8月 | C110: 工程 | D110: 智慧厨房 | E110: 0 | F110: 2025-08-25 | G110: 1***p | H110: 100185439639 | I110: 德玛仕（DEMASHI）智慧厨房食品留样柜幼儿园学校公司食堂后厨标签打印智能留样记录仪自动称重拍照食安留样仪RX1011 | J110: 许炎宏 | K110: 非询单 | L110: 未成交 | M110: 2fc757dfb5b3bc54da0d82b629204c81 | N110: =COUNTIF(M:M,M110) -> 1
A111: =IFERROR(YEAR(F111)&"年","-") -> 2025年 | B111: =IFERROR(YEAR(F111)&"年"&MONTH(F111)&"月","-") -> 2025年8月 | C111: 工程 | D111: 智慧厨房 | E111: 0 | F111: 2025-08-26 | G111: j***l | H111: 100185439639 | I111: 德玛仕（DEMASHI）智慧厨房食品留样柜幼儿园学校公司食堂后厨标签打印智能留样记录仪自动称重拍照食安留样仪RX1011 | J111: 罗栋铭 | K111: 非询单 | L111: 未成交 | M111: 8cabfb0808851085366bf4ff4988b7d8 | N111: =COUNTIF(M:M,M111) -> 2
A112: =IFERROR(YEAR(F112)&"年","-") -> 2025年 | B112: =IFERROR(YEAR(F112)&"年"&MONTH(F112)&"月","-") -> 2025年8月 | C112: 工程 | D112: 智慧厨房 | E112: 0 | F112: 2025-08-26 | G112: j***l | H112: 100185439639 | I112: 德玛仕（DEMASHI）智慧厨房食品留样柜幼儿园学校公司食堂后厨标签打印智能留样记录仪自动称重拍照食安留样仪RX1011 | J112: 刘韵兰 | K112: 非询单 | L112: 未成交 | M112: 8cabfb0808851085366bf4ff4988b7d8 | N112: =COUNTIF(M:M,M112) -> 2
A113: =IFERROR(YEAR(F113)&"年","-") -> 2025年 | B113: =IFERROR(YEAR(F113)&"年"&MONTH(F113)&"月","-") -> 2025年8月 | C113: 工程 | D113: 智慧厨房 | E113: 0 | F113: 2025-08-27 | G113: j***8 | H113: 100185439639 | I113: 德玛仕（DEMASHI）智慧厨房食品留样柜幼儿园学校公司食堂后厨标签打印智能留样记录仪自动称重拍照食安留样仪RX1011 | J113: 林静宜 | K113: 询单 | L113: 未成交 | M113: cf0894a5490b7a391faeac37560e2235 | N113: =COUNTIF(M:M,M113) -> 1
A114: =IFERROR(YEAR(F114)&"年","-") -> 2025年 | B114: =IFERROR(YEAR(F114)&"年"&MONTH(F114)&"月","-") -> 2025年8月 | C114: 工程 | D114: 智慧厨房 | E114: 0 | F114: 2025-08-28 | G114: j***l | H114: 100251652724 | I114: 德玛仕（DEMASHI）智慧智能厨房食堂进销存报表导出 智能出入库磅秤 T600-150A（单机版 不锈钢） | J114: 陈满红 | K114: 询单 | L114: 未成交 | M114: 900b328fb75420671f81a9becbdf15f2 | N114: =COUNTIF(M:M,M114) -> 1
A115: =IFERROR(YEAR(F115)&"年","-") -> 2025年 | B115: =IFERROR(YEAR(F115)&"年"&MONTH(F115)&"月","-") -> 2025年8月 | C115: 工程 | D115: 智慧厨房 | E115: 4680 | F115: 2025-08-28 | G115: 阳***0 | H115: 100185439639 | I115: 德玛仕（DEMASHI）智慧厨房食品留样柜幼儿园学校公司食堂后厨标签打印智能留样记录仪自动称重拍照食安留样仪RX1011 | J115: 林静宜 | K115: 询单 | L115: 成交 | M115: 806dfb2b688f67f512608a0b74be5864 | N115: =COUNTIF(M:M,M115) -> 3
A116: =IFERROR(YEAR(F116)&"年","-") -> 2025年 | B116: =IFERROR(YEAR(F116)&"年"&MONTH(F116)&"月","-") -> 2025年8月 | C116: 工程 | D116: 智慧厨房 | E116: #VALUE! | F116: 2025-08-30 | G116: j***f | H116: 100185439639 | I116: 德玛仕（DEMASHI）智慧厨房食品留样柜幼儿园学校公司食堂后厨标签打印智能留样记录仪自动称重拍照食安留样仪RX1011 | J116: 黄植胜 | K116: 非询单 | L116: 未成交 | M116: c7403a5c95aa7424fd8704b7dc68af1c | N116: =COUNTIF(M:M,M116) -> 2
A117: =IFERROR(YEAR(F117)&"年","-") -> 2025年 | B117: =IFERROR(YEAR(F117)&"年"&MONTH(F117)&"月","-") -> 2025年8月 | C117: 工程 | D117: 智慧厨房 | E117: 0 | F117: 2025-08-30 | G117: w***y | H117: 100185439639 | I117: 德玛仕（DEMASHI）智慧厨房食品留样柜幼儿园学校公司食堂后厨标签打印智能留样记录仪自动称重拍照食安留样仪RX1011 | J117: 许炎宏 | K117: 非询单 | L117: 未成交 | M117: 3326db7a8efc9acb93b9aebee3a96c2e | N117: =COUNTIF(M:M,M117) -> 2
A118: =IFERROR(YEAR(F118)&"年","-") -> 2025年 | B118: =IFERROR(YEAR(F118)&"年"&MONTH(F118)&"月","-") -> 2025年8月 | C118: 工程 | D118: 智慧厨房 | E118: 4680 | F118: 2025-08-31 | G118: j***0 | H118: 100185439639 | I118: 德玛仕（DEMASHI）智慧厨房食品留样柜幼儿园学校公司食堂后厨标签打印智能留样记录仪自动称重拍照食安留样仪RX1011 | J118: 蔡梦飞 | K118: 询单 | L118: 成交 | M118: 4e8dc353a1e07656d75bef2810d23597 | N118: =COUNTIF(M:M,M118) -> 2
A119: =IFERROR(YEAR(F119)&"年","-") -> 2025年 | B119: =IFERROR(YEAR(F119)&"年"&MONTH(F119)&"月","-") -> 2025年8月 | C119: 工程 | D119: 智慧厨房 | E119: 4680 | F119: 2025-08-31 | G119: j***0 | H119: 100185439639 | I119: 德玛仕（DEMASHI）智慧厨房食品留样柜幼儿园学校公司食堂后厨标签打印智能留样记录仪自动称重拍照食安留样仪RX1011 | J119: 许炎宏 | K119: 非询单 | L119: 未成交 | M119: 4e8dc353a1e07656d75bef2810d23597 | N119: =COUNTIF(M:M,M119) -> 2
A120: =IFERROR(YEAR(F120)&"年","-") -> 2025年 | B120: =IFERROR(YEAR(F120)&"年"&MONTH(F120)&"月","-") -> 2025年9月 | C120: 工程 | D120: 智慧厨房 | E120: 0 | F120: 2025-09-01 | G120: w***y | H120: 100185439639 | I120: 德玛仕（DEMASHI）智慧厨房食品留样柜幼儿园学校公司食堂后厨标签打印智能留样记录仪自动称重拍照食安留样仪RX1011 | J120: 冯俊明 | K120: 非询单 | L120: 未成交 | M120: 3326db7a8efc9acb93b9aebee3a96c2e | N120: =COUNTIF(M:M,M120) -> 2
A121: =IFERROR(YEAR(F121)&"年","-") -> 2025年 | B121: =IFERROR(YEAR(F121)&"年"&MONTH(F121)&"月","-") -> 2025年9月 | C121: 工程 | D121: 智慧厨房 | E121: 0 | F121: 2025-09-01 | G121: j***7 | H121: 100185439639 | I121: 德玛仕（DEMASHI）智慧厨房食品留样柜幼儿园学校公司食堂后厨标签打印智能留样记录仪自动称重拍照食安留样仪RX1011 | J121: 蔡梦飞 | K121: 非询单 | L121: 未成交 | M121: 5675351a088236ddb0259a2e70c6fb68 | N121: =COUNTIF(M:M,M121) -> 1
A122: =IFERROR(YEAR(F122)&"年","-") -> 2025年 | B122: =IFERROR(YEAR(F122)&"年"&MONTH(F122)&"月","-") -> 2025年9月 | C122: 工程 | D122: 智慧厨房 | E122: 0 | F122: 2025-09-02 | G122: 迟***2 | H122: 100251652644 | I122: 德玛仕（DEMASHI）智慧智能厨房食堂 食安智能留样仪留样机留样秤 RX1011（10.1寸 A规屏，58mm热敏打印机） | J122: 许炎宏 | K122: 询单 | L122: 未成交 | M122: 298cb6133433ec458be023bd964bdeed | N122: =COUNTIF(M:M,M122) -> 1
A123: =IFERROR(YEAR(F123)&"年","-") -> 2025年 | B123: =IFERROR(YEAR(F123)&"年"&MONTH(F123)&"月","-") -> 2025年9月 | C123: 工程 | D123: 智慧厨房 | E123: 0 | F123: 2025-09-08 | G123: j***9 | H123: 100185439639 | I123: 德玛仕（DEMASHI）智慧厨房食品留样柜幼儿园学校公司食堂后厨标签打印智能留样记录仪自动称重拍照食安留样仪RX1011 | J123: 吴仁迪 | K123: 询单 | L123: 未成交 | M123: c588bb5a6c7bee0459fb4de2bbb550d3 | N123: =COUNTIF(M:M,M123) -> 1
A124: =IFERROR(YEAR(F124)&"年","-") -> 2025年 | B124: =IFERROR(YEAR(F124)&"年"&MONTH(F124)&"月","-") -> 2025年9月 | C124: 工程 | D124: 智慧厨房 | E124: 0 | F124: 2025-09-09 | G124: j***o | H124: 100185439639 | I124: 德玛仕（DEMASHI）智慧厨房食品留样柜幼儿园学校公司食堂后厨标签打印智能留样记录仪自动称重拍照食安留样仪RX1011 | J124: 吴仁迪 | K124: 询单 | L124: 未成交 | M124: 9ab05fab5eb5a28db71d495fb1628350 | N124: =COUNTIF(M:M,M124) -> 1
A125: =IFERROR(YEAR(F125)&"年","-") -> 2025年 | B125: =IFERROR(YEAR(F125)&"年"&MONTH(F125)&"月","-") -> 2025年9月 | C125: 工程 | D125: 智慧厨房 | E125: 4680 | F125: 2025-09-10 | G125: j***w | H125: 100185439639 | I125: 德玛仕（DEMASHI）智慧厨房食品留样柜幼儿园学校公司食堂后厨标签打印智能留样记录仪自动称重拍照食安留样仪RX1011 | J125: 罗栋铭 | K125: 询单 | L125: 成交 | M125: 481f0f1365eecd1f489afd7ad816a68f | N125: =COUNTIF(M:M,M125) -> 1
A126: =IFERROR(YEAR(F126)&"年","-") -> 2025年 | B126: =IFERROR(YEAR(F126)&"年"&MONTH(F126)&"月","-") -> 2025年9月 | C126: 工程 | D126: 智慧厨房 | E126: 4212 | F126: 2025-09-11 | G126: j***m | H126: 100185439639 | I126: 德玛仕（DEMASHI）智慧厨房食品留样柜幼儿园学校公司食堂后厨标签打印智能留样记录仪自动称重拍照食安留样仪RX1011 | J126: 罗栋铭 | K126: 询单 | L126: 成交 | M126: c7d3ac9fa648d8db08f16a30cb41c17d | N126: =COUNTIF(M:M,M126) -> 4
A127: =IFERROR(YEAR(F127)&"年","-") -> 2025年 | B127: =IFERROR(YEAR(F127)&"年"&MONTH(F127)&"月","-") -> 2025年9月 | C127: 工程 | D127: 智慧厨房 | E127: 0 | F127: 2025-09-11 | G127: 3***站 | H127: 100251652646 | I127: 德玛仕（DEMASHI）智慧智能厨房食堂进销存报表导出 智能出入库磅秤 T600-300A（网络版 不锈钢） | J127: 许炎宏 | K127: 询单 | L127: 未成交 | M127: a2890cb97e167d78e7a7e2d726c229dc | N127: =COUNTIF(M:M,M127) -> 1
A128: =IFERROR(YEAR(F128)&"年","-") -> 2025年 | B128: =IFERROR(YEAR(F128)&"年"&MONTH(F128)&"月","-") -> 2025年9月 | C128: 工程 | D128: 智慧厨房 | E128: 0 | F128: 2025-09-13 | G128: 小***x | H128: 100185439639 | I128: 德玛仕（DEMASHI）智慧厨房食品留样柜幼儿园学校公司食堂后厨标签打印智能留样记录仪自动称重拍照食安留样仪RX1011 | J128: 罗栋铭 | K128: 询单 | L128: 未成交 | M128: e53f4d0213129fa53e4fdaf73a67df51 | N128: =COUNTIF(M:M,M128) -> 1
... A130: =IFERROR(YEAR(F130)&"年","-") -> 2025年 | B130: =IFERROR(YEAR(F130)&"年"&MONTH(F130)&"月","-") -> 2025年9月 | C130: 工程 | D130: 智慧厨房 | E130: 4212 | F130: 2025-09-15 | G130: j***m | H130: 100185439639 | I130: 德玛仕（DEMASHI）智慧厨房食品留样柜幼儿园学校公司食堂后厨标签打印智能留样记录仪自动称重拍照食安留样仪RX1011 | J130: 刘韵兰 | K130: 非询单 | L130: 未成交 | M130: c7d3ac9fa648d8db08f16a30cb41c17d | N130: =COUNTIF(M:M,M130) -> 4
A131: =IFERROR(YEAR(F131)&"年","-") -> 2025年 | B131: =IFERROR(YEAR(F131)&"年"&MONTH(F131)&"月","-") -> 2025年9月 | C131: 工程 | D131: 智慧厨房 | E131: #VALUE! | F131: 2025-09-15 | G131: b***7 | H131: 100185439639 | I131: 德玛仕（DEMASHI）智慧厨房食品留样柜幼儿园学校公司食堂后厨标签打印智能留样记录仪自动称重拍照食安留样仪RX1011 | J131: 许炎宏 | K131: 非询单 | L131: 未成交 | M131: ea6c8b3a4154ab365affb5075506d040 | N131: =COUNTIF(M:M,M131) -> 2
A132: =IFERROR(YEAR(F132)&"年","-") -> 2025年 | B132: =IFERROR(YEAR(F132)&"年"&MONTH(F132)&"月","-") -> 2025年9月 | C132: 工程 | D132: 智慧厨房 | E132: 0 | F132: 2025-09-16 | G132: j***0 | H132: 100191557553 | I132: 德玛仕（DEMASHI）智慧智能厨房食堂进销存报表导出 智能出入库磅秤 T600-150A（网络版 不锈钢） | J132: 许炎宏 | K132: 询单 | L132: 未成交 | M132: a4c105249d017970652c28b4842c66b7 | N132: =COUNTIF(M:M,M132) -> 2
A133: =IFERROR(YEAR(F133)&"年","-") -> 2025年 | B133: =IFERROR(YEAR(F133)&"年"&MONTH(F133)&"月","-") -> 2025年9月 | C133: 工程 | D133: 智慧厨房 | E133: 0 | F133: 2025-09-17 | G133: k***4 | H133: 100185439639 | I133: 德玛仕（DEMASHI）智慧厨房食品留样柜幼儿园学校公司食堂后厨标签打印智能留样记录仪自动称重拍照食安留样仪RX1011 | J133: 许炎宏 | K133: 非询单 | L133: 未成交 | M133: 367cf7c00d1eab961df1ca98db1b0e05 | N133: =COUNTIF(M:M,M133) -> 1
A134: =IFERROR(YEAR(F134)&"年","-") -> 2025年 | B134: =IFERROR(YEAR(F134)&"年"&MONTH(F134)&"月","-") -> 2025年9月 | C134: 工程 | D134: 智慧厨房 | E134: 0 | F134: 2025-09-17 | G134: v***8 | H134: 100251652724 | I134: 德玛仕（DEMASHI）智慧智能厨房食堂进销存报表导出 智能出入库磅秤 T600-150A（单机版 不锈钢） | J134: 许炎宏 | K134: 询单 | L134: 未成交 | M134: f7e1214dcb7891270095c2bd5d34b179 | N134: =COUNTIF(M:M,M134) -> 1
...

Sheet 商品咨询-数据源
A1: 月份 | B1: 店铺 | C1: 类目 | D1: 商品编号 | E1: 商品名称 | F1: 接待人数 | G1: 询单人数 | H1: 付款人数 | I1: 询单->付款成功率 | J1: 付款件数 | K1: 金额
A2: 6月 | B2: 官旗 | C2: 智慧厨房 | D2: 10162200870892 | E2: 德玛仕（DEMASHI）智慧智能厨房食堂 食安智能留样仪留样机留样秤 自动称重 食品菜品 保存日期标签打印一体机 智能留样仪丨留样自动记录丨可报表导出 | F2: 3 | G2: 3 | H2: 0 | I2: 0 | J2: 0 | K2: 0
A3: 8月 | B3: 官旗 | C3: 智慧厨房 | D3: 10175269720969 | E3: 德玛仕（DEMASHI）食品留样冰箱柜 冷藏柜保鲜柜商用展示柜 生物实验室设备学校幼儿园食堂公司用 食物冷藏保鲜商用 智能留样仪丨留样自动记录丨可报表导出 | F3: 1 | G3: 1 | H3: 1 | I3: 100 | J3: 1 | K3: 3808.009
A4: 9月 | B4: 官旗 | C4: 智慧厨房 | D4: 10162203268678 | E4: 德玛仕（DEMASHI）智能智慧食堂厨房 智能出入库磅秤 进销存报表导出 商用高精度精准 不锈钢防水充电可移动 物联网 单机版丨无需联网丨可称150KG | F4: 1 | G4: 1 | H4: 0 | I4: 0 | J4: 0 | K4: 0
A5: 9月 | B5: 官旗 | C5: 智慧厨房 | D5: 10162205073104 | E5: 德玛仕（DEMASHI）智能食堂厨房自助视觉识别智能双屏 刷卡扫码人脸识别三合一支付点餐结算机双屏人脸识别结算机 | F5: 1 | G5: 1 | H5: 0 | I5: 0 | J5: 0 | K5: 0
A6: 9月 | B6: 官旗 | C6: 智慧厨房 | D6: 10172530525873 | E6: 德玛仕（DEMASHI）智能智慧厨房食堂 食安智能留样仪留样机留样秤 自动称重 食品菜品 保存日期标签打印留样仪RX1011 自动称重丨自动拍照丨可导数据 | F6: 1 | G6: 0 | H6: 0 | I6: 0 | J6: 0 | K6: 0
A7: 9月 | B7: 官旗 | C7: 智慧厨房 | D7: 10175269720969 | E7: 德玛仕（DEMASHI）食品留样冰箱柜 冷藏柜保鲜柜商用展示柜 生物实验室设备学校幼儿园食堂公司用 食物冷藏保鲜商用 智能留样仪丨留样自动记录丨可报表导出 | F7: 2 | G7: 1 | H7: 0 | I7: 0 | J7: 0 | K7: 0
A8: 10月 | B8: 官旗 | C8: 智慧厨房 | D8: 10162200870892 | E8: 德玛仕（DEMASHI）智慧智能厨房食堂 食安智能留样仪留样机留样秤 自动称重 食品菜品 保存日期标签打印一体机 智能留样仪丨留样自动记录丨可报表导出 | F8: 1 | G8: 1 | H8: 0 | I8: 0 | J8: 0 | K8: 0
A9: 10月 | B9: 官旗 | C9: 智慧厨房 | D9: 10162203268678 | E9: 德玛仕（DEMASHI）智能智慧食堂厨房 智能出入库磅秤 进销存报表导出 商用高精度精准 不锈钢防水充电可移动 物联网 单机版丨无需联网丨可称150KG | F9: 1 | G9: 1 | H9: 0 | I9: 0 | J9: 0 | K9: 0
A10: 10月 | B10: 官旗 | C10: 智慧厨房 | D10: 10172530525873 | E10: 德玛仕（DEMASHI）智能智慧厨房食堂 食安智能留样仪留样机留样秤 自动称重 食品菜品 保存日期标签打印留样仪RX1011 自动称重丨自动拍照丨可导数据 | F10: 3 | G10: 2 | H10: 1 | I10: 50 | J10: 1 | K10: 4043.02
A11: 10月 | B11: 官旗 | C11: 智慧厨房 | D11: 10174209434926 | E11: 德玛仕（DEMASHI）智能智慧厨房食堂 双屏视觉结算机 台式挂式人脸识别 刷卡刷脸刷码高精度灵敏 食堂学校企业酒店 挂式智慧双屏结算机丨多种支付方式丨记录随时看 | F11: 1 | G11: 1 | H11: 0 | I11: 0 | J11: 0 | K11: 0
A12: 10月 | B12: 官旗 | C12: 智慧厨房 | D12: 10175269720969 | E12: 德玛仕（DEMASHI）食品留样冰箱柜 冷藏柜保鲜柜商用展示柜 生物实验室设备学校幼儿园食堂公司用 食物冷藏保鲜商用 智能留样仪丨留样自动记录丨可报表导出 | F12: 8 | G12: 6 | H12: 0 | I12: 0 | J12: 0 | K12: 0
A13: 10月 | B13: 官旗 | C13: 智慧厨房 | D13: 10186484654926 | E13: 德玛仕（DEMASHI）商用豆浆机大容量浆渣分离早餐店单位食堂用全自动磨煮一体大型免煮全自动打玉米汁米糊五谷豆浆机 【学校优选】智能食品留样仪丨符合食品安全 | F13: 2 | G13: 2 | H13: 0 | I13: 0 | J13: 0 | K13: 0
... A43: 12月 | B43: 西厨 | C43: 智慧厨房 | D43: 10203225618564 | E43: 德玛仕（DEMASHI）智慧智能厨房食堂 食安智能留样仪部队用打菜机 自动称重 食品菜品 保存日期标签打印收银机 【AI监测】后厨AI管理服务一体机丨WC8 | F43: 1 | G43: 1 | H43: 0 | I43: 0 | J43: 0 | K43: 0
A44: 8月 | B44: 饮水 | C44: 智慧厨房 | D44: 100119912611 | E44: 德玛仕（DEMASHI）智能食堂厨房出入库磅秤 进销存报表导出 300KG称重 学校单位食堂用 商用净水设备网络版T600-300A | F44: 1 | G44: 1 | H44: 0 | I44: 0.0 | J44: 0 | K44: 0
A45: 6月 | B45: 工程 | C45: 智慧厨房 | D45: 100185439639 | E45: 德玛仕（DEMASHI）智慧厨房食品留样柜幼儿园学校公司食堂后厨标签打印智能留样记录仪自动称重拍照食安留样仪RX1011 | F45: 0 | G45: 0 | H45: 0 | I45: 0.0 | J45: 0 | K45: 0
A46: 7月 | B46: 工程 | C46: 智慧厨房 | D46: 100185439639 | E46: 德玛仕（DEMASHI）智慧厨房食品留样柜幼儿园学校公司食堂后厨标签打印智能留样记录仪自动称重拍照食安留样仪RX1011 | F46: 6 | G46: 4 | H46: 0 | I46: 0.0 | J46: 0 | K46: 0
A47: 7月 | B47: 工程 | C47: 智慧厨房 | D47: 100251652724 | E47: 德玛仕（DEMASHI）智慧智能厨房食堂进销存报表导出 智能出入库磅秤 T600-150A（单机版 不锈钢） | F47: 0 | G47: 0 | H47: 0 | I47: 0.0 | J47: 0 | K47: 0
A48: 8月 | B48: 工程 | C48: 智慧厨房 | D48: 100185439639 | E48: 德玛仕（DEMASHI）智慧厨房食品留样柜幼儿园学校公司食堂后厨标签打印智能留样记录仪自动称重拍照食安留样仪RX1011 | F48: 40 | G48: 21 | H48: 7 | I48: 33.33 | J48: 8 | K48: 55992
A49: 8月 | B49: 工程 | C49: 智慧厨房 | D49: 100251652638 | E49: 德玛仕（DEMASHI）智慧厨房学校单位食堂用商用高精度仓库出货电子秤智能磅秤食材出入收货秤验货秤150公斤T600-150A | F49: 1 | G49: 1 | H49: 0 | I49: 0.0 | J49: 0 | K49: 0
A50: 8月 | B50: 工程 | C50: 智慧厨房 | D50: 100251652646 | E50: 德玛仕（DEMASHI）智慧智能厨房食堂进销存报表导出 智能出入库磅秤 T600-300A（网络版 不锈钢） | F50: 0 | G50: 0 | H50: 0 | I50: 0.0 | J50: 0 | K50: 0
A51: 8月 | B51: 工程 | C51: 智慧厨房 | D51: 100251652724 | E51: 德玛仕（DEMASHI）智慧智能厨房食堂进销存报表导出 智能出入库磅秤 T600-150A（单机版 不锈钢） | F51: 6 | G51: 6 | H51: 0 | I51: 0.0 | J51: 0 | K51: 0
A52: 9月 | B52: 工程 | C52: 智慧厨房 | D52: 100185439639 | E52: 德玛仕（DEMASHI）智慧厨房食品留样柜幼儿园学校公司食堂后厨标签打印智能留样记录仪自动称重拍照食安留样仪RX1011 | F52: 18 | G52: 10 | H52: 2 | I52: 20.0 | J52: 2 | K52: 13998
A53: 9月 | B53: 工程 | C53: 智慧厨房 | D53: 100191557553 | E53: 德玛仕（DEMASHI）智慧智能厨房食堂进销存报表导出 智能出入库磅秤 T600-150A（网络版 不锈钢） | F53: 1 | G53: 1 | H53: 0 | I53: 0.0 | J53: 0 | K53: 0
A54: 9月 | B54: 工程 | C54: 智慧厨房 | D54: 100251652644 | E54: 德玛仕（DEMASHI）智慧智能厨房食堂 食安智能留样仪留样机留样秤 RX1011（10.1寸 A规屏，58mm热敏打印机） | F54: 1 | G54: 1 | H54: 0 | I54: 0.0 | J54: 0 | K54: 0
A55: 9月 | B55: 工程 | C55: 智慧厨房 | D55: 100251652646 | E55: 德玛仕（DEMASHI）智慧智能厨房食堂进销存报表导出 智能出入库磅秤 T600-300A（网络版 不锈钢） | F55: 1 | G55: 1 | H55: 0 | I55: 0.0 | J55: 0 | K55: 0
... A136: 12月 | B136: 自营 | C136: 智慧厨房 | D136: 100308983078 | E136: 德玛仕（DEMASHI）智慧食堂视觉自助计量打餐终端 多种支付科学就餐一体机 人脸识别就餐丨无需绑盘丨可供1000人食堂 | F136: 2 | G136: 1 | H136: 0 | I136: 0.0 | J136: 0 | K136: 0

Sheet 转化率
B1: 2025年 | E1: 2026年 | H1: 45658 | K1: 45689 | N1: 45717 | Q1: 45748 | T1: 45778 | W1: 45809 | Z1: 45839 | AC1: 45870 | AF1: 45901 | AI1: 45931 | AL1: 45962 | AO1: 45992
A2: 客服昵称 | B2: 询单 | C2: 成交数量 | D2: 转化率 | E2: 询单 | F2: 成交数量 | G2: 转化率 | H2: 询单 | I2: 成交数量 | J2: 转化率 | K2: 询单 | L2: 成交数量 | M2: 转化率 | N2: 询单 | O2: 成交数量 | P2: 转化率 | Q2: 询单 | R2: 成交数量 | S2: 转化率 | T2: 询单 | U2: 成交数量 | V2: 转化率 | W2: 询单 | X2: 成交数量 | Y2: 转化率 | Z2: 询单 | AA2: 成交数量 | AB2: 转化率 | AC2: 询单 | AD2: 成交数量 | AE2: 转化率 | AF2: 询单 | AG2: 成交数量 | AH2: 转化率 | AI2: 询单 | AJ2: 成交数量 | AK2: 转化率 | AL2: 询单 | AM2: 成交数量 | AN2: 转化率 | AO2: 询单 | AP2: 成交数量 | AQ2: 转化率
A3: 许炎宏 | B3: =COUNTIFS('咨询明细-数据源'!$J:$J,$A3,'咨询明细-数据源'!$K:$K,B$2,'咨询明细-数据源'!$A:$A,B$1) -> 84 | C3: =COUNTIFS('咨询明细-数据源'!$J:$J,$A3,'咨询明细-数据源'!$L:$L,"成交",'咨询明细-数据源'!$A:$A,B$1) -> 12 | D3: =IFERROR(C3/B3,0) -> 0.14285714 | E3: =COUNTIFS('咨询明细-数据源'!$J:$J,$A3,'咨询明细-数据源'!$K:$K,E$2,'咨询明细-数据源'!$A:$A,E$1) -> 15 | F3: =COUNTIFS('咨询明细-数据源'!$J:$J,$A3,'咨询明细-数据源'!$L:$L,"成交",'咨询明细-数据源'!$A:$A,E$1) -> 0 | G3: =IFERROR(F3/E3,0) -> 0 | H3: =COUNTIFS('咨询明细-数据源'!$J:$J,$A3,'咨询明细-数据源'!$K:$K,H$2,'咨询明细-数据源'!$A:$A,H$1) -> 0 | I3: =COUNTIFS('咨询明细-数据源'!$J:$J,$A3,'咨询明细-数据源'!$L:$L,"成交",'咨询明细-数据源'!$A:$A,H$1) -> 0 | J3: =IFERROR(I3/H3,0) -> 0 | K3: =COUNTIFS('咨询明细-数据源'!$J:$J,$A3,'咨询明细-数据源'!$K:$K,K$2,'咨询明细-数据源'!$A:$A,K$1) -> 0 | L3: =COUNTIFS('咨询明细-数据源'!$J:$J,$A3,'咨询明细-数据源'!$L:$L,"成交",'咨询明细-数据源'!$A:$A,K$1) -> 0 | M3: =IFERROR(L3/K3,0) -> 0 | N3: =COUNTIFS('咨询明细-数据源'!$J:$J,$A3,'咨询明细-数据源'!$K:$K,N$2,'咨询明细-数据源'!$A:$A,N$1) -> 0 | O3: =COUNTIFS('咨询明细-数据源'!$J:$J,$A3,'咨询明细-数据源'!$L:$L,"成交",'咨询明细-数据源'!$A:$A,N$1) -> 0 | P3: =IFERROR(O3/N3,0) -> 0 | Q3: =COUNTIFS('咨询明细-数据源'!$J:$J,$A3,'咨询明细-数据源'!$K:$K,Q$2,'咨询明细-数据源'!$A:$A,Q$1) -> 0 | R3: =COUNTIFS('咨询明细-数据源'!$J:$J,$A3,'咨询明细-数据源'!$L:$L,"成交",'咨询明细-数据源'!$A:$A,Q$1) -> 0 | S3: =IFERROR(R3/Q3,0) -> 0 | T3: =COUNTIFS('咨询明细-数据源'!$J:$J,$A3,'咨询明细-数据源'!$K:$K,T$2,'咨询明细-数据源'!$A:$A,T$1) -> 0 | U3: =COUNTIFS('咨询明细-数据源'!$J:$J,$A3,'咨询明细-数据源'!$L:$L,"成交",'咨询明细-数据源'!$A:$A,T$1) -> 0 | V3: =IFERROR(U3/T3,0) -> 0 | W3: =COUNTIFS('咨询明细-数据源'!$J:$J,$A3,'咨询明细-数据源'!$K:$K,W$2,'咨询明细-数据源'!$A:$A,W$1) -> 0 | X3: =COUNTIFS('咨询明细-数据源'!$J:$J,$A3,'咨询明细-数据源'!$L:$L,"成交",'咨询明细-数据源'!$A:$A,W$1) -> 0 | Y3: =IFERROR(X3/W3,0) -> 0 | Z3: =COUNTIFS('咨询明细-数据源'!$J:$J,$A3,'咨询明细-数据源'!$K:$K,Z$2,'咨询明细-数据源'!$A:$A,Z$1) -> 0 | AA3: =COUNTIFS('咨询明细-数据源'!$J:$J,$A3,'咨询明细-数据源'!$L:$L,"成交",'咨询明细-数据源'!$A:$A,Z$1) -> 0 | AB3: =IFERROR(AA3/Z3,0) -> 0 | AC3: =COUNTIFS('咨询明细-数据源'!$J:$J,$A3,'咨询明细-数据源'!$K:$K,AC$2,'咨询明细-数据源'!$A:$A,AC$1) -> 0 | AD3: =COUNTIFS('咨询明细-数据源'!$J:$J,$A3,'咨询明细-数据源'!$L:$L,"成交",'咨询明细-数据源'!$A:$A,AC$1) -> 0 | AE3: =IFERROR(AD3/AC3,0) -> 0 | AF3: =COUNTIFS('咨询明细-数据源'!$J:$J,$A3,'咨询明细-数据源'!$K:$K,AF$2,'咨询明细-数据源'!$A:$A,AF$1) -> 0 | AG3: =COUNTIFS('咨询明细-数据源'!$J:$J,$A3,'咨询明细-数据源'!$L:$L,"成交",'咨询明细-数据源'!$A:$A,AF$1) -> 0 | AH3: =IFERROR(AG3/AF3,0) -> 0 | AI3: =COUNTIFS('咨询明细-数据源'!$J:$J,$A3,'咨询明细-数据源'!$K:$K,AI$2,'咨询明细-数据源'!$A:$A,AI$1) -> 0 | AJ3: =COUNTIFS('咨询明细-数据源'!$J:$J,$A3,'咨询明细-数据源'!$L:$L,"成交",'咨询明细-数据源'!$A:$A,AI$1) -> 0 | AK3: =IFERROR(AJ3/AI3,0) -> 0 | AL3: =COUNTIFS('咨询明细-数据源'!$J:$J,$A3,'咨询明细-数据源'!$K:$K,AL$2,'咨询明细-数据源'!$A:$A,AL$1) -> 0 | AM3: =COUNTIFS('咨询明细-数据源'!$J:$J,$A3,'咨询明细-数据源'!$L:$L,"成交",'咨询明细-数据源'!$A:$A,AL$1) -> 0 | AN3: =IFERROR(AM3/AL3,0) -> 0 | AO3: =COUNTIFS('咨询明细-数据源'!$J:$J,$A3,'咨询明细-数据源'!$K:$K,AO$2,'咨询明细-数据源'!$A:$A,AO$1) -> 0 | AP3: =COUNTIFS('咨询明细-数据源'!$J:$J,$A3,'咨询明细-数据源'!$L:$L,"成交",'咨询明细-数据源'!$A:$A,AO$1) -> 0 | AQ3: =IFERROR(AP3/AO3,0) -> 0
A4: 林静宜 | B4: =COUNTIFS('咨询明细-数据源'!$J:$J,$A4,'咨询明细-数据源'!$K:$K,B$2,'咨询明细-数据源'!$A:$A,B$1) -> 12 | C4: =COUNTIFS('咨询明细-数据源'!$J:$J,$A4,'咨询明细-数据源'!$L:$L,"成交",'咨询明细-数据源'!$A:$A,B$1) -> 4 | D4: =IFERROR(C4/B4,0) -> 0.33333333 | E4: =COUNTIFS('咨询明细-数据源'!$J:$J,$A4,'咨询明细-数据源'!$K:$K,E$2,'咨询明细-数据源'!$A:$A,E$1) -> 0 | F4: =COUNTIFS('咨询明细-数据源'!$J:$J,$A4,'咨询明细-数据源'!$L:$L,"成交",'咨询明细-数据源'!$A:$A,E$1) -> 0 | G4: =IFERROR(F4/E4,0) -> 0 | H4: =COUNTIFS('咨询明细-数据源'!$J:$J,$A4,'咨询明细-数据源'!$K:$K,H$2,'咨询明细-数据源'!$B:$B,H$1) -> 0 | I4: =COUNTIFS('咨询明细-数据源'!$J:$J,$A4,'咨询明细-数据源'!$L:$L,"成交",'咨询明细-数据源'!$B:$B,H$1) -> 0 | J4: =IFERROR(I4/H4,0) -> 0 | K4: =COUNTIFS('咨询明细-数据源'!$J:$J,$A4,'咨询明细-数据源'!$K:$K,K$2,'咨询明细-数据源'!$B:$B,K$1) -> 0 | L4: =COUNTIFS('咨询明细-数据源'!$J:$J,$A4,'咨询明细-数据源'!$L:$L,"成交",'咨询明细-数据源'!$B:$B,K$1) -> 0 | M4: =IFERROR(L4/K4,0) -> 0 | N4: =COUNTIFS('咨询明细-数据源'!$J:$J,$A4,'咨询明细-数据源'!$K:$K,N$2,'咨询明细-数据源'!$B:$B,N$1) -> 0 | O4: =COUNTIFS('咨询明细-数据源'!$J:$J,$A4,'咨询明细-数据源'!$L:$L,"成交",'咨询明细-数据源'!$B:$B,N$1) -> 0 | P4: =IFERROR(O4/N4,0) -> 0 | Q4: =COUNTIFS('咨询明细-数据源'!$J:$J,$A4,'咨询明细-数据源'!$K:$K,Q$2,'咨询明细-数据源'!$B:$B,Q$1) -> 0 | R4: =COUNTIFS('咨询明细-数据源'!$J:$J,$A4,'咨询明细-数据源'!$L:$L,"成交",'咨询明细-数据源'!$B:$B,Q$1) -> 0 | S4: =IFERROR(R4/Q4,0) -> 0 | T4: =COUNTIFS('咨询明细-数据源'!$J:$J,$A4,'咨询明细-数据源'!$K:$K,T$2,'咨询明细-数据源'!$B:$B,T$1) -> 0 | U4: =COUNTIFS('咨询明细-数据源'!$J:$J,$A4,'咨询明细-数据源'!$L:$L,"成交",'咨询明细-数据源'!$B:$B,T$1) -> 0 | V4: =IFERROR(U4/T4,0) -> 0 | W4: =COUNTIFS('咨询明细-数据源'!$J:$J,$A4,'咨询明细-数据源'!$K:$K,W$2,'咨询明细-数据源'!$B:$B,W$1) -> 0 | X4: =COUNTIFS('咨询明细-数据源'!$J:$J,$A4,'咨询明细-数据源'!$L:$L,"成交",'咨询明细-数据源'!$B:$B,W$1) -> 0 | Y4: =IFERROR(X4/W4,0) -> 0 | Z4: =COUNTIFS('咨询明细-数据源'!$J:$J,$A4,'咨询明细-数据源'!$K:$K,Z$2,'咨询明细-数据源'!$B:$B,Z$1) -> 0 | AA4: =COUNTIFS('咨询明细-数据源'!$J:$J,$A4,'咨询明细-数据源'!$L:$L,"成交",'咨询明细-数据源'!$B:$B,Z$1) -> 0 | AB4: =IFERROR(AA4/Z4,0) -> 0 | AC4: =COUNTIFS('咨询明细-数据源'!$J:$J,$A4,'咨询明细-数据源'!$K:$K,AC$2,'咨询明细-数据源'!$B:$B,AC$1) -> 7 | AD4: =COUNTIFS('咨询明细-数据源'!$J:$J,$A4,'咨询明细-数据源'!$L:$L,"成交",'咨询明细-数据源'!$B:$B,AC$1) -> 3 | AE4: =IFERROR(AD4/AC4,0) -> 0.42857143 | AF4: =COUNTIFS('咨询明细-数据源'!$J:$J,$A4,'咨询明细-数据源'!$K:$K,AF$2,'咨询明细-数据源'!$B:$B,AF$1) -> 3 | AG4: =COUNTIFS('咨询明细-数据源'!$J:$J,$A4,'咨询明细-数据源'!$L:$L,"成交",'咨询明细-数据源'!$B:$B,AF$1) -> 0 | AH4: =IFERROR(AG4/AF4,0) -> 0 | AI4: =COUNTIFS('咨询明细-数据源'!$J:$J,$A4,'咨询明细-数据源'!$K:$K,AI$2,'咨询明细-数据源'!$B:$B,AI$1) -> 2 | AJ4: =COUNTIFS('咨询明细-数据源'!$J:$J,$A4,'咨询明细-数据源'!$L:$L,"成交",'咨询明细-数据源'!$B:$B,AI$1) -> 1 | AK4: =IFERROR(AJ4/AI4,0) -> 0.5 | AL4: =COUNTIFS('咨询明细-数据源'!$J:$J,$A4,'咨询明细-数据源'!$K:$K,AL$2,'咨询明细-数据源'!$B:$B,AL$1) -> 0 | AM4: =COUNTIFS('咨询明细-数据源'!$J:$J,$A4,'咨询明细-数据源'!$L:$L,"成交",'咨询明细-数据源'!$B:$B,AL$1) -> 0 | AN4: =IFERROR(AM4/AL4,0) -> 0 | AO4: =COUNTIFS('咨询明细-数据源'!$J:$J,$A4,'咨询明细-数据源'!$K:$K,AO$2,'咨询明细-数据源'!$B:$B,AO$1) -> 0 | AP4: =COUNTIFS('咨询明细-数据源'!$J:$J,$A4,'咨询明细-数据源'!$L:$L,"成交",'咨询明细-数据源'!$B:$B,AO$1) -> 0 | AQ4: =IFERROR(AP4/AO4,0) -> 0
A5: 蔡梦飞 | B5: =COUNTIFS('咨询明细-数据源'!$J:$J,$A5,'咨询明细-数据源'!$K:$K,B$2,'咨询明细-数据源'!$A:$A,B$1) -> 23 | C5: =COUNTIFS('咨询明细-数据源'!$J:$J,$A5,'咨询明细-数据源'!$L:$L,"成交",'咨询明细-数据源'!$A:$A,B$1) -> 3 | D5: =IFERROR(C5/B5,0) -> 0.13043478 | E5: =COUNTIFS('咨询明细-数据源'!$J:$J,$A5,'咨询明细-数据源'!$K:$K,E$2,'咨询明细-数据源'!$A:$A,E$1) -> 14 | F5: =COUNTIFS('咨询明细-数据源'!$J:$J,$A5,'咨询明细-数据源'!$L:$L,"成交",'咨询明细-数据源'!$A:$A,E$1) -> 0 | G5: =IFERROR(F5/E5,0) -> 0 | H5: =COUNTIFS('咨询明细-数据源'!$J:$J,$A5,'咨询明细-数据源'!$K:$K,H$2,'咨询明细-数据源'!$B:$B,H$1) -> 0 | I5: =COUNTIFS('咨询明细-数据源'!$J:$J,$A5,'咨询明细-数据源'!$L:$L,"成交",'咨询明细-数据源'!$B:$B,H$1) -> 0 | J5: =IFERROR(I5/H5,0) -> 0 | K5: =COUNTIFS('咨询明细-数据源'!$J:$J,$A5,'咨询明细-数据源'!$K:$K,K$2,'咨询明细-数据源'!$B:$B,K$1) -> 0 | L5: =COUNTIFS('咨询明细-数据源'!$J:$J,$A5,'咨询明细-数据源'!$L:$L,"成交",'咨询明细-数据源'!$B:$B,K$1) -> 0 | M5: =IFERROR(L5/K5,0) -> 0 | N5: =COUNTIFS('咨询明细-数据源'!$J:$J,$A5,'咨询明细-数据源'!$K:$K,N$2,'咨询明细-数据源'!$B:$B,N$1) -> 0 | O5: =COUNTIFS('咨询明细-数据源'!$J:$J,$A5,'咨询明细-数据源'!$L:$L,"成交",'咨询明细-数据源'!$B:$B,N$1) -> 0 | P5: =IFERROR(O5/N5,0) -> 0 | Q5: =COUNTIFS('咨询明细-数据源'!$J:$J,$A5,'咨询明细-数据源'!$K:$K,Q$2,'咨询明细-数据源'!$B:$B,Q$1) -> 0 | R5: =COUNTIFS('咨询明细-数据源'!$J:$J,$A5,'咨询明细-数据源'!$L:$L,"成交",'咨询明细-数据源'!$B:$B,Q$1) -> 0 | S5: =IFERROR(R5/Q5,0) -> 0 | T5: =COUNTIFS('咨询明细-数据源'!$J:$J,$A5,'咨询明细-数据源'!$K:$K,T$2,'咨询明细-数据源'!$B:$B,T$1) -> 0 | U5: =COUNTIFS('咨询明细-数据源'!$J:$J,$A5,'咨询明细-数据源'!$L:$L,"成交",'咨询明细-数据源'!$B:$B,T$1) -> 0 | V5: =IFERROR(U5/T5,0) -> 0 | W5: =COUNTIFS('咨询明细-数据源'!$J:$J,$A5,'咨询明细-数据源'!$K:$K,W$2,'咨询明细-数据源'!$B:$B,W$1) -> 0 | X5: =COUNTIFS('咨询明细-数据源'!$J:$J,$A5,'咨询明细-数据源'!$L:$L,"成交",'咨询明细-数据源'!$B:$B,W$1) -> 0 | Y5: =IFERROR(X5/W5,0) -> 0 | Z5: =COUNTIFS('咨询明细-数据源'!$J:$J,$A5,'咨询明细-数据源'!$K:$K,Z$2,'咨询明细-数据源'!$B:$B,Z$1) -> 0 | AA5: =COUNTIFS('咨询明细-数据源'!$J:$J,$A5,'咨询明细-数据源'!$L:$L,"成交",'咨询明细-数据源'!$B:$B,Z$1) -> 0 | AB5: =IFERROR(AA5/Z5,0) -> 0 | AC5: =COUNTIFS('咨询明细-数据源'!$J:$J,$A5,'咨询明细-数据源'!$K:$K,AC$2,'咨询明细-数据源'!$B:$B,AC$1) -> 2 | AD5: =COUNTIFS('咨询明细-数据源'!$J:$J,$A5,'咨询明细-数据源'!$L:$L,"成交",'咨询明细-数据源'!$B:$B,AC$1) -> 2 | AE5: =IFERROR(AD5/AC5,0) -> 1 | AF5: =COUNTIFS('咨询明细-数据源'!$J:$J,$A5,'咨询明细-数据源'!$K:$K,AF$2,'咨询明细-数据源'!$B:$B,AF$1) -> 0 | AG5: =COUNTIFS('咨询明细-数据源'!$J:$J,$A5,'咨询明细-数据源'!$L:$L,"成交",'咨询明细-数据源'!$B:$B,AF$1) -> 0 | AH5: =IFERROR(AG5/AF5,0) -> 0 | AI5: =COUNTIFS('咨询明细-数据源'!$J:$J,$A5,'咨询明细-数据源'!$K:$K,AI$2,'咨询明细-数据源'!$B:$B,AI$1) -> 4 | AJ5: =COUNTIFS('咨询明细-数据源'!$J:$J,$A5,'咨询明细-数据源'!$L:$L,"成交",'咨询明细-数据源'!$B:$B,AI$1) -> 1 | AK5: =IFERROR(AJ5/AI5,0) -> 0.25 | AL5: =COUNTIFS('咨询明细-数据源'!$J:$J,$A5,'咨询明细-数据源'!$K:$K,AL$2,'咨询明细-数据源'!$B:$B,AL$1) -> 7 | AM5: =COUNTIFS('咨询明细-数据源'!$J:$J,$A5,'咨询明细-数据源'!$L:$L,"成交",'咨询明细-数据源'!$B:$B,AL$1) -> 0 | AN5: =IFERROR(AM5/AL5,0) -> 0 | AO5: =COUNTIFS('咨询明细-数据源'!$J:$J,$A5,'咨询明细-数据源'!$K:$K,AO$2,'咨询明细-数据源'!$B:$B,AO$1) -> 10 | AP5: =COUNTIFS('咨询明细-数据源'!$J:$J,$A5,'咨询明细-数据源'!$L:$L,"成交",'咨询明细-数据源'!$B:$B,AO$1) -> 0 | AQ5: =IFERROR(AP5/AO5,0) -> 0
A6: 罗栋铭 | B6: =COUNTIFS('咨询明细-数据源'!$J:$J,$A6,'咨询明细-数据源'!$K:$K,B$2,'咨询明细-数据源'!$A:$A,B$1) -> 5 | C6: =COUNTIFS('咨询明细-数据源'!$J:$J,$A6,'咨询明细-数据源'!$L:$L,"成交",'咨询明细-数据源'!$A:$A,B$1) -> 3 | D6: =IFERROR(C6/B6,0) -> 0.6 | E6: =COUNTIFS('咨询明细-数据源'!$J:$J,$A6,'咨询明细-数据源'!$K:$K,E$2,'咨询明细-数据源'!$A:$A,E$1) -> 0 | F6: =COUNTIFS('咨询明细-数据源'!$J:$J,$A6,'咨询明细-数据源'!$L:$L,"成交",'咨询明细-数据源'!$A:$A,E$1) -> 0 | G6: =IFERROR(F6/E6,0) -> 0 | H6: =COUNTIFS('咨询明细-数据源'!$J:$J,$A6,'咨询明细-数据源'!$K:$K,H$2,'咨询明细-数据源'!$B:$B,H$1) -> 0 | I6: =COUNTIFS('咨询明细-数据源'!$J:$J,$A6,'咨询明细-数据源'!$L:$L,"成交",'咨询明细-数据源'!$B:$B,H$1) -> 0 | J6: =IFERROR(I6/H6,0) -> 0 | K6: =COUNTIFS('咨询明细-数据源'!$J:$J,$A6,'咨询明细-数据源'!$K:$K,K$2,'咨询明细-数据源'!$B:$B,K$1) -> 0 | L6: =COUNTIFS('咨询明细-数据源'!$J:$J,$A6,'咨询明细-数据源'!$L:$L,"成交",'咨询明细-数据源'!$B:$B,K$1) -> 0 | M6: =IFERROR(L6/K6,0) -> 0 | N6: =COUNTIFS('咨询明细-数据源'!$J:$J,$A6,'咨询明细-数据源'!$K:$K,N$2,'咨询明细-数据源'!$B:$B,N$1) -> 0 | O6: =COUNTIFS('咨询明细-数据源'!$J:$J,$A6,'咨询明细-数据源'!$L:$L,"成交",'咨询明细-数据源'!$B:$B,N$1) -> 0 | P6: =IFERROR(O6/N6,0) -> 0 | Q6: =COUNTIFS('咨询明细-数据源'!$J:$J,$A6,'咨询明细-数据源'!$K:$K,Q$2,'咨询明细-数据源'!$B:$B,Q$1) -> 0 | R6: =COUNTIFS('咨询明细-数据源'!$J:$J,$A6,'咨询明细-数据源'!$L:$L,"成交",'咨询明细-数据源'!$B:$B,Q$1) -> 0 | S6: =IFERROR(R6/Q6,0) -> 0 | T6: =COUNTIFS('咨询明细-数据源'!$J:$J,$A6,'咨询明细-数据源'!$K:$K,T$2,'咨询明细-数据源'!$B:$B,T$1) -> 0 | U6: =COUNTIFS('咨询明细-数据源'!$J:$J,$A6,'咨询明细-数据源'!$L:$L,"成交",'咨询明细-数据源'!$B:$B,T$1) -> 0 | V6: =IFERROR(U6/T6,0) -> 0 | W6: =COUNTIFS('咨询明细-数据源'!$J:$J,$A6,'咨询明细-数据源'!$K:$K,W$2,'咨询明细-数据源'!$B:$B,W$1) -> 0 | X6: =COUNTIFS('咨询明细-数据源'!$J:$J,$A6,'咨询明细-数据源'!$L:$L,"成交",'咨询明细-数据源'!$B:$B,W$1) -> 0 | Y6: =IFERROR(X6/W6,0) -> 0 | Z6: =COUNTIFS('咨询明细-数据源'!$J:$J,$A6,'咨询明细-数据源'!$K:$K,Z$2,'咨询明细-数据源'!$B:$B,Z$1) -> 0 | AA6: =COUNTIFS('咨询明细-数据源'!$J:$J,$A6,'咨询明细-数据源'!$L:$L,"成交",'咨询明细-数据源'!$B:$B,Z$1) -> 0 | AB6: =IFERROR(AA6/Z6,0) -> 0 | AC6: =COUNTIFS('咨询明细-数据源'!$J:$J,$A6,'咨询明细-数据源'!$K:$K,AC$2,'咨询明细-数据源'!$B:$B,AC$1) -> 2 | AD6: =COUNTIFS('咨询明细-数据源'!$J:$J,$A6,'咨询明细-数据源'!$L:$L,"成交",'咨询明细-数据源'!$B:$B,AC$1) -> 1 | AE6: =IFERROR(AD6/AC6,0) -> 0.5 | AF6: =COUNTIFS('咨询明细-数据源'!$J:$J,$A6,'咨询明细-数据源'!$K:$K,AF$2,'咨询明细-数据源'!$B:$B,AF$1) -> 3 | AG6: =COUNTIFS('咨询明细-数据源'!$J:$J,$A6,'咨询明细-数据源'!$L:$L,"成交",'咨询明细-数据源'!$B:$B,AF$1) -> 2 | AH6: =IFERROR(AG6/AF6,0) -> 0.66666667 | AI6: =COUNTIFS('咨询明细-数据源'!$J:$J,$A6,'咨询明细-数据源'!$K:$K,AI$2,'咨询明细-数据源'!$B:$B,AI$1) -> 0 | AJ6: =COUNTIFS('咨询明细-数据源'!$J:$J,$A6,'咨询明细-数据源'!$L:$L,"成交",'咨询明细-数据源'!$B:$B,AI$1) -> 0 | AK6: =IFERROR(AJ6/AI6,0) -> 0 | AL6: =COUNTIFS('咨询明细-数据源'!$J:$J,$A6,'咨询明细-数据源'!$K:$K,AL$2,'咨询明细-数据源'!$B:$B,AL$1) -> 0 | AM6: =COUNTIFS('咨询明细-数据源'!$J:$J,$A6,'咨询明细-数据源'!$L:$L,"成交",'咨询明细-数据源'!$B:$B,AL$1) -> 0 | AN6: =IFERROR(AM6/AL6,0) -> 0 | AO6: =COUNTIFS('咨询明细-数据源'!$J:$J,$A6,'咨询明细-数据源'!$K:$K,AO$2,'咨询明细-数据源'!$B:$B,AO$1) -> 0 | AP6: =COUNTIFS('咨询明细-数据源'!$J:$J,$A6,'咨询明细-数据源'!$L:$L,"成交",'咨询明细-数据源'!$B:$B,AO$1) -> 0 | AQ6: =IFERROR(AP6/AO6,0) -> 0
A7: 罗广强 | B7: =COUNTIFS('咨询明细-数据源'!$J:$J,$A7,'咨询明细-数据源'!$K:$K,B$2,'咨询明细-数据源'!$A:$A,B$1) -> 4 | C7: =COUNTIFS('咨询明细-数据源'!$J:$J,$A7,'咨询明细-数据源'!$L:$L,"成交",'咨询明细-数据源'!$A:$A,B$1) -> 1 | D7: =IFERROR(C7/B7,0) -> 0.25 | E7: =COUNTIFS('咨询明细-数据源'!$J:$J,$A7,'咨询明细-数据源'!$K:$K,E$2,'咨询明细-数据源'!$A:$A,E$1) -> 0 | F7: =COUNTIFS('咨询明细-数据源'!$J:$J,$A7,'咨询明细-数据源'!$L:$L,"成交",'咨询明细-数据源'!$A:$A,E$1) -> 0 | G7: =IFERROR(F7/E7,0) -> 0 | H7: =COUNTIFS('咨询明细-数据源'!$J:$J,$A7,'咨询明细-数据源'!$K:$K,H$2,'咨询明细-数据源'!$B:$B,H$1) -> 0 | I7: =COUNTIFS('咨询明细-数据源'!$J:$J,$A7,'咨询明细-数据源'!$L:$L,"成交",'咨询明细-数据源'!$B:$B,H$1) -> 0 | J7: =IFERROR(I7/H7,0) -> 0 | K7: =COUNTIFS('咨询明细-数据源'!$J:$J,$A7,'咨询明细-数据源'!$K:$K,K$2,'咨询明细-数据源'!$B:$B,K$1) -> 0 | L7: =COUNTIFS('咨询明细-数据源'!$J:$J,$A7,'咨询明细-数据源'!$L:$L,"成交",'咨询明细-数据源'!$B:$B,K$1) -> 0 | M7: =IFERROR(L7/K7,0) -> 0 | N7: =COUNTIFS('咨询明细-数据源'!$J:$J,$A7,'咨询明细-数据源'!$K:$K,N$2,'咨询明细-数据源'!$B:$B,N$1) -> 0 | O7: =COUNTIFS('咨询明细-数据源'!$J:$J,$A7,'咨询明细-数据源'!$L:$L,"成交",'咨询明细-数据源'!$B:$B,N$1) -> 0 | P7: =IFERROR(O7/N7,0) -> 0 | Q7: =COUNTIFS('咨询明细-数据源'!$J:$J,$A7,'咨询明细-数据源'!$K:$K,Q$2,'咨询明细-数据源'!$B:$B,Q$1) -> 0 | R7: =COUNTIFS('咨询明细-数据源'!$J:$J,$A7,'咨询明细-数据源'!$L:$L,"成交",'咨询明细-数据源'!$B:$B,Q$1) -> 0 | S7: =IFERROR(R7/Q7,0) -> 0 | T7: =COUNTIFS('咨询明细-数据源'!$J:$J,$A7,'咨询明细-数据源'!$K:$K,T$2,'咨询明细-数据源'!$B:$B,T$1) -> 0 | U7: =COUNTIFS('咨询明细-数据源'!$J:$J,$A7,'咨询明细-数据源'!$L:$L,"成交",'咨询明细-数据源'!$B:$B,T$1) -> 0 | V7: =IFERROR(U7/T7,0) -> 0 | W7: =COUNTIFS('咨询明细-数据源'!$J:$J,$A7,'咨询明细-数据源'!$K:$K,W$2,'咨询明细-数据源'!$B:$B,W$1) -> 0 | X7: =COUNTIFS('咨询明细-数据源'!$J:$J,$A7,'咨询明细-数据源'!$L:$L,"成交",'咨询明细-数据源'!$B:$B,W$1) -> 0 | Y7: =IFERROR(X7/W7,0) -> 0 | Z7: =COUNTIFS('咨询明细-数据源'!$J:$J,$A7,'咨询明细-数据源'!$K:$K,Z$2,'咨询明细-数据源'!$B:$B,Z$1) -> 0 | AA7: =COUNTIFS('咨询明细-数据源'!$J:$J,$A7,'咨询明细-数据源'!$L:$L,"成交",'咨询明细-数据源'!$B:$B,Z$1) -> 0 | AB7: =IFERROR(AA7/Z7,0) -> 0 | AC7: =COUNTIFS('咨询明细-数据源'!$J:$J,$A7,'咨询明细-数据源'!$K:$K,AC$2,'咨询明细-数据源'!$B:$B,AC$1) -> 0 | AD7: =COUNTIFS('咨询明细-数据源'!$J:$J,$A7,'咨询明细-数据源'!$L:$L,"成交",'咨询明细-数据源'!$B:$B,AC$1) -> 0 | AE7: =IFERROR(AD7/AC7,0) -> 0 | AF7: =COUNTIFS('咨询明细-数据源'!$J:$J,$A7,'咨询明细-数据源'!$K:$K,AF$2,'咨询明细-数据源'!$B:$B,AF$1) -> 0 | AG7: =COUNTIFS('咨询明细-数据源'!$J:$J,$A7,'咨询明细-数据源'!$L:$L,"成交",'咨询明细-数据源'!$B:$B,AF$1) -> 0 | AH7: =IFERROR(AG7/AF7,0) -> 0 | AI7: =COUNTIFS('咨询明细-数据源'!$J:$J,$A7,'咨询明细-数据源'!$K:$K,AI$2,'咨询明细-数据源'!$B:$B,AI$1) -> 0 | AJ7: =COUNTIFS('咨询明细-数据源'!$J:$J,$A7,'咨询明细-数据源'!$L:$L,"成交",'咨询明细-数据源'!$B:$B,AI$1) -> 0 | AK7: =IFERROR(AJ7/AI7,0) -> 0 | AL7: =COUNTIFS('咨询明细-数据源'!$J:$J,$A7,'咨询明细-数据源'!$K:$K,AL$2,'咨询明细-数据源'!$B:$B,AL$1) -> 1 | AM7: =COUNTIFS('咨询明细-数据源'!$J:$J,$A7,'咨询明细-数据源'!$L:$L,"成交",'咨询明细-数据源'!$B:$B,AL$1) -> 0 | AN7: =IFERROR(AM7/AL7,0) -> 0 | AO7: =COUNTIFS('咨询明细-数据源'!$J:$J,$A7,'咨询明细-数据源'!$K:$K,AO$2,'咨询明细-数据源'!$B:$B,AO$1) -> 3 | AP7: =COUNTIFS('咨询明细-数据源'!$J:$J,$A7,'咨询明细-数据源'!$L:$L,"成交",'咨询明细-数据源'!$B:$B,AO$1) -> 1 | AQ7: =IFERROR(AP7/AO7,0) -> 0.33333333
A8: 李想 | B8: =COUNTIFS('咨询明细-数据源'!$J:$J,$A8,'咨询明细-数据源'!$K:$K,B$2,'咨询明细-数据源'!$A:$A,B$1) -> 2 | C8: =COUNTIFS('咨询明细-数据源'!$J:$J,$A8,'咨询明细-数据源'!$L:$L,"成交",'咨询明细-数据源'!$A:$A,B$1) -> 1 | D8: =IFERROR(C8/B8,0) -> 0.5 | E8: =COUNTIFS('咨询明细-数据源'!$J:$J,$A8,'咨询明细-数据源'!$K:$K,E$2,'咨询明细-数据源'!$A:$A,E$1) -> 5 | F8: =COUNTIFS('咨询明细-数据源'!$J:$J,$A8,'咨询明细-数据源'!$L:$L,"成交",'咨询明细-数据源'!$A:$A,E$1) -> 0 | G8: =IFERROR(F8/E8,0) -> 0 | H8: =COUNTIFS('咨询明细-数据源'!$J:$J,$A8,'咨询明细-数据源'!$K:$K,H$2,'咨询明细-数据源'!$B:$B,H$1) -> 0 | I8: =COUNTIFS('咨询明细-数据源'!$J:$J,$A8,'咨询明细-数据源'!$L:$L,"成交",'咨询明细-数据源'!$B:$B,H$1) -> 0 | J8: =IFERROR(I8/H8,0) -> 0 | K8: =COUNTIFS('咨询明细-数据源'!$J:$J,$A8,'咨询明细-数据源'!$K:$K,K$2,'咨询明细-数据源'!$B:$B,K$1) -> 0 | L8: =COUNTIFS('咨询明细-数据源'!$J:$J,$A8,'咨询明细-数据源'!$L:$L,"成交",'咨询明细-数据源'!$B:$B,K$1) -> 0 | M8: =IFERROR(L8/K8,0) -> 0 | N8: =COUNTIFS('咨询明细-数据源'!$J:$J,$A8,'咨询明细-数据源'!$K:$K,N$2,'咨询明细-数据源'!$B:$B,N$1) -> 0 | O8: =COUNTIFS('咨询明细-数据源'!$J:$J,$A8,'咨询明细-数据源'!$L:$L,"成交",'咨询明细-数据源'!$B:$B,N$1) -> 0 | P8: =IFERROR(O8/N8,0) -> 0 | Q8: =COUNTIFS('咨询明细-数据源'!$J:$J,$A8,'咨询明细-数据源'!$K:$K,Q$2,'咨询明细-数据源'!$B:$B,Q$1) -> 0 | R8: =COUNTIFS('咨询明细-数据源'!$J:$J,$A8,'咨询明细-数据源'!$L:$L,"成交",'咨询明细-数据源'!$B:$B,Q$1) -> 0 | S8: =IFERROR(R8/Q8,0) -> 0 | T8: =COUNTIFS('咨询明细-数据源'!$J:$J,$A8,'咨询明细-数据源'!$K:$K,T$2,'咨询明细-数据源'!$B:$B,T$1) -> 0 | U8: =COUNTIFS('咨询明细-数据源'!$J:$J,$A8,'咨询明细-数据源'!$L:$L,"成交",'咨询明细-数据源'!$B:$B,T$1) -> 0 | V8: =IFERROR(U8/T8,0) -> 0 | W8: =COUNTIFS('咨询明细-数据源'!$J:$J,$A8,'咨询明细-数据源'!$K:$K,W$2,'咨询明细-数据源'!$B:$B,W$1) -> 0 | X8: =COUNTIFS('咨询明细-数据源'!$J:$J,$A8,'咨询明细-数据源'!$L:$L,"成交",'咨询明细-数据源'!$B:$B,W$1) -> 0 | Y8: =IFERROR(X8/W8,0) -> 0 | Z8: =COUNTIFS('咨询明细-数据源'!$J:$J,$A8,'咨询明细-数据源'!$K:$K,Z$2,'咨询明细-数据源'!$B:$B,Z$1) -> 0 | AA8: =COUNTIFS('咨询明细-数据源'!$J:$J,$A8,'咨询明细-数据源'!$L:$L,"成交",'咨询明细-数据源'!$B:$B,Z$1) -> 0 | AB8: =IFERROR(AA8/Z8,0) -> 0 | AC8: =COUNTIFS('咨询明细-数据源'!$J:$J,$A8,'咨询明细-数据源'!$K:$K,AC$2,'咨询明细-数据源'!$B:$B,AC$1) -> 0 | AD8: =COUNTIFS('咨询明细-数据源'!$J:$J,$A8,'咨询明细-数据源'!$L:$L,"成交",'咨询明细-数据源'!$B:$B,AC$1) -> 0 | AE8: =IFERROR(AD8/AC8,0) -> 0 | AF8: =COUNTIFS('咨询明细-数据源'!$J:$J,$A8,'咨询明细-数据源'!$K:$K,AF$2,'咨询明细-数据源'!$B:$B,AF$1) -> 0 | AG8: =COUNTIFS('咨询明细-数据源'!$J:$J,$A8,'咨询明细-数据源'!$L:$L,"成交",'咨询明细-数据源'!$B:$B,AF$1) -> 0 | AH8: =IFERROR(AG8/AF8,0) -> 0 | AI8: =COUNTIFS('咨询明细-数据源'!$J:$J,$A8,'咨询明细-数据源'!$K:$K,AI$2,'咨询明细-数据源'!$B:$B,AI$1) -> 0 | AJ8: =COUNTIFS('咨询明细-数据源'!$J:$J,$A8,'咨询明细-数据源'!$L:$L,"成交",'咨询明细-数据源'!$B:$B,AI$1) -> 0 | AK8: =IFERROR(AJ8/AI8,0) -> 0 | AL8: =COUNTIFS('咨询明细-数据源'!$J:$J,$A8,'咨询明细-数据源'!$K:$K,AL$2,'咨询明细-数据源'!$B:$B,AL$1) -> 0 | AM8: =COUNTIFS('咨询明细-数据源'!$J:$J,$A8,'咨询明细-数据源'!$L:$L,"成交",'咨询明细-数据源'!$B:$B,AL$1) -> 0 | AN8: =IFERROR(AM8/AL8,0) -> 0 | AO8: =COUNTIFS('咨询明细-数据源'!$J:$J,$A8,'咨询明细-数据源'!$K:$K,AO$2,'咨询明细-数据源'!$B:$B,AO$1) -> 2 | AP8: =COUNTIFS('咨询明细-数据源'!$J:$J,$A8,'咨询明细-数据源'!$L:$L,"成交",'咨询明细-数据源'!$B:$B,AO$1) -> 1 | AQ8: =IFERROR(AP8/AO8,0) -> 0.5
A9: 袁业骏 | B9: =COUNTIFS('咨询明细-数据源'!$J:$J,$A9,'咨询明细-数据源'!$K:$K,B$2,'咨询明细-数据源'!$A:$A,B$1) -> 5 | C9: =COUNTIFS('咨询明细-数据源'!$J:$J,$A9,'咨询明细-数据源'!$L:$L,"成交",'咨询明细-数据源'!$A:$A,B$1) -> 1 | D9: =IFERROR(C9/B9,0) -> 0.2 | E9: =COUNTIFS('咨询明细-数据源'!$J:$J,$A9,'咨询明细-数据源'!$K:$K,E$2,'咨询明细-数据源'!$A:$A,E$1) -> 0 | F9: =COUNTIFS('咨询明细-数据源'!$J:$J,$A9,'咨询明细-数据源'!$L:$L,"成交",'咨询明细-数据源'!$A:$A,E$1) -> 0 | G9: =IFERROR(F9/E9,0) -> 0 | H9: =COUNTIFS('咨询明细-数据源'!$J:$J,$A9,'咨询明细-数据源'!$K:$K,H$2,'咨询明细-数据源'!$B:$B,H$1) -> 0 | I9: =COUNTIFS('咨询明细-数据源'!$J:$J,$A9,'咨询明细-数据源'!$L:$L,"成交",'咨询明细-数据源'!$B:$B,H$1) -> 0 | J9: =IFERROR(I9/H9,0) -> 0 | K9: =COUNTIFS('咨询明细-数据源'!$J:$J,$A9,'咨询明细-数据源'!$K:$K,K$2,'咨询明细-数据源'!$B:$B,K$1) -> 0 | L9: =COUNTIFS('咨询明细-数据源'!$J:$J,$A9,'咨询明细-数据源'!$L:$L,"成交",'咨询明细-数据源'!$B:$B,K$1) -> 0 | M9: =IFERROR(L9/K9,0) -> 0 | N9: =COUNTIFS('咨询明细-数据源'!$J:$J,$A9,'咨询明细-数据源'!$K:$K,N$2,'咨询明细-数据源'!$B:$B,N$1) -> 1 | O9: =COUNTIFS('咨询明细-数据源'!$J:$J,$A9,'咨询明细-数据源'!$L:$L,"成交",'咨询明细-数据源'!$B:$B,N$1) -> 0 | P9: =IFERROR(O9/N9,0) -> 0 | Q9: =COUNTIFS('咨询明细-数据源'!$J:$J,$A9,'咨询明细-数据源'!$K:$K,Q$2,'咨询明细-数据源'!$B:$B,Q$1) -> 4 | R9: =COUNTIFS('咨询明细-数据源'!$J:$J,$A9,'咨询明细-数据源'!$L:$L,"成交",'咨询明细-数据源'!$B:$B,Q$1) -> 1 | S9: =IFERROR(R9/Q9,0) -> 0.25 | T9: =COUNTIFS('咨询明细-数据源'!$J:$J,$A9,'咨询明细-数据源'!$K:$K,T$2,'咨询明细-数据源'!$B:$B,T$1) -> 0 | U9: =COUNTIFS('咨询明细-数据源'!$J:$J,$A9,'咨询明细-数据源'!$L:$L,"成交",'咨询明细-数据源'!$B:$B,T$1) -> 0 | V9: =IFERROR(U9/T9,0) -> 0 | W9: =COUNTIFS('咨询明细-数据源'!$J:$J,$A9,'咨询明细-数据源'!$K:$K,W$2,'咨询明细-数据源'!$B:$B,W$1) -> 0 | X9: =COUNTIFS('咨询明细-数据源'!$J:$J,$A9,'咨询明细-数据源'!$L:$L,"成交",'咨询明细-数据源'!$B:$B,W$1) -> 0 | Y9: =IFERROR(X9/W9,0) -> 0 | Z9: =COUNTIFS('咨询明细-数据源'!$J:$J,$A9,'咨询明细-数据源'!$K:$K,Z$2,'咨询明细-数据源'!$B:$B,Z$1) -> 0 | AA9: =COUNTIFS('咨询明细-数据源'!$J:$J,$A9,'咨询明细-数据源'!$L:$L,"成交",'咨询明细-数据源'!$B:$B,Z$1) -> 0 | AB9: =IFERROR(AA9/Z9,0) -> 0 | AC9: =COUNTIFS('咨询明细-数据源'!$J:$J,$A9,'咨询明细-数据源'!$K:$K,AC$2,'咨询明细-数据源'!$B:$B,AC$1) -> 0 | AD9: =COUNTIFS('咨询明细-数据源'!$J:$J,$A9,'咨询明细-数据源'!$L:$L,"成交",'咨询明细-数据源'!$B:$B,AC$1) -> 0 | AE9: =IFERROR(AD9/AC9,0) -> 0 | AF9: =COUNTIFS('咨询明细-数据源'!$J:$J,$A9,'咨询明细-数据源'!$K:$K,AF$2,'咨询明细-数据源'!$B:$B,AF$1) -> 0 | AG9: =COUNTIFS('咨询明细-数据源'!$J:$J,$A9,'咨询明细-数据源'!$L:$L,"成交",'咨询明细-数据源'!$B:$B,AF$1) -> 0 | AH9: =IFERROR(AG9/AF9,0) -> 0 | AI9: =COUNTIFS('咨询明细-数据源'!$J:$J,$A9,'咨询明细-数据源'!$K:$K,AI$2,'咨询明细-数据源'!$B:$B,AI$1) -> 0 | AJ9: =COUNTIFS('咨询明细-数据源'!$J:$J,$A9,'咨询明细-数据源'!$L:$L,"成交",'咨询明细-数据源'!$B:$B,AI$1) -> 0 | AK9: =IFERROR(AJ9/AI9,0) -> 0 | AL9: =COUNTIFS('咨询明细-数据源'!$J:$J,$A9,'咨询明细-数据源'!$K:$K,AL$2,'咨询明细-数据源'!$B:$B,AL$1) -> 0 | AM9: =COUNTIFS('咨询明细-数据源'!$J:$J,$A9,'咨询明细-数据源'!$L:$L,"成交",'咨询明细-数据源'!$B:$B,AL$1) -> 0 | AN9: =IFERROR(AM9/AL9,0) -> 0 | AO9: =COUNTIFS('咨询明细-数据源'!$J:$J,$A9,'咨询明细-数据源'!$K:$K,AO$2,'咨询明细-数据源'!$B:$B,AO$1) -> 0 | AP9: =COUNTIFS('咨询明细-数据源'!$J:$J,$A9,'咨询明细-数据源'!$L:$L,"成交",'咨询明细-数据源'!$B:$B,AO$1) -> 0 | AQ9: =IFERROR(AP9/AO9,0) -> 0
A10: 陈满红 | B10: =COUNTIFS('咨询明细-数据源'!$J:$J,$A10,'咨询明细-数据源'!$K:$K,B$2,'咨询明细-数据源'!$A:$A,B$1) -> 13 | C10: =COUNTIFS('咨询明细-数据源'!$J:$J,$A10,'咨询明细-数据源'!$L:$L,"成交",'咨询明细-数据源'!$A:$A,B$1) -> 0 | D10: =IFERROR(C10/B10,0) -> 0 | E10: =COUNTIFS('咨询明细-数据源'!$J:$J,$A10,'咨询明细-数据源'!$K:$K,E$2,'咨询明细-数据源'!$A:$A,E$1) -> 1 | F10: =COUNTIFS('咨询明细-数据源'!$J:$J,$A10,'咨询明细-数据源'!$L:$L,"成交",'咨询明细-数据源'!$A:$A,E$1) -> 0 | G10: =IFERROR(F10/E10,0) -> 0 | H10: =COUNTIFS('咨询明细-数据源'!$J:$J,$A10,'咨询明细-数据源'!$K:$K,H$2,'咨询明细-数据源'!$B:$B,H$1) -> 0 | I10: =COUNTIFS('咨询明细-数据源'!$J:$J,$A10,'咨询明细-数据源'!$L:$L,"成交",'咨询明细-数据源'!$B:$B,H$1) -> 0 | J10: =IFERROR(I10/H10,0) -> 0 | K10: =COUNTIFS('咨询明细-数据源'!$J:$J,$A10,'咨询明细-数据源'!$K:$K,K$2,'咨询明细-数据源'!$B:$B,K$1) -> 0 | L10: =COUNTIFS('咨询明细-数据源'!$J:$J,$A10,'咨询明细-数据源'!$L:$L,"成交",'咨询明细-数据源'!$B:$B,K$1) -> 0 | M10: =IFERROR(L10/K10,0) -> 0 | N10: =COUNTIFS('咨询明细-数据源'!$J:$J,$A10,'咨询明细-数据源'!$K:$K,N$2,'咨询明细-数据源'!$B:$B,N$1) -> 0 | O10: =COUNTIFS('咨询明细-数据源'!$J:$J,$A10,'咨询明细-数据源'!$L:$L,"成交",'咨询明细-数据源'!$B:$B,N$1) -> 0 | P10: =IFERROR(O10/N10,0) -> 0 | Q10: =COUNTIFS('咨询明细-数据源'!$J:$J,$A10,'咨询明细-数据源'!$K:$K,Q$2,'咨询明细-数据源'!$B:$B,Q$1) -> 0 | R10: =COUNTIFS('咨询明细-数据源'!$J:$J,$A10,'咨询明细-数据源'!$L:$L,"成交",'咨询明细-数据源'!$B:$B,Q$1) -> 0 | S10: =IFERROR(R10/Q10,0) -> 0 | T10: =COUNTIFS('咨询明细-数据源'!$J:$J,$A10,'咨询明细-数据源'!$K:$K,T$2,'咨询明细-数据源'!$B:$B,T$1) -> 0 | U10: =COUNTIFS('咨询明细-数据源'!$J:$J,$A10,'咨询明细-数据源'!$L:$L,"成交",'咨询明细-数据源'!$B:$B,T$1) -> 0 | V10: =IFERROR(U10/T10,0) -> 0 | W10: =COUNTIFS('咨询明细-数据源'!$J:$J,$A10,'咨询明细-数据源'!$K:$K,W$2,'咨询明细-数据源'!$B:$B,W$1) -> 1 | X10: =COUNTIFS('咨询明细-数据源'!$J:$J,$A10,'咨询明细-数据源'!$L:$L,"成交",'咨询明细-数据源'!$B:$B,W$1) -> 0 | Y10: =IFERROR(X10/W10,0) -> 0 | Z10: =COUNTIFS('咨询明细-数据源'!$J:$J,$A10,'咨询明细-数据源'!$K:$K,Z$2,'咨询明细-数据源'!$B:$B,Z$1) -> 1 | AA10: =COUNTIFS('咨询明细-数据源'!$J:$J,$A10,'咨询明细-数据源'!$L:$L,"成交",'咨询明细-数据源'!$B:$B,Z$1) -> 0 | AB10: =IFERROR(AA10/Z10,0) -> 0 | AC10: =COUNTIFS('咨询明细-数据源'!$J:$J,$A10,'咨询明细-数据源'!$K:$K,AC$2,'咨询明细-数据源'!$B:$B,AC$1) -> 3 | AD10: =COUNTIFS('咨询明细-数据源'!$J:$J,$A10,'咨询明细-数据源'!$L:$L,"成交",'咨询明细-数据源'!$B:$B,AC$1) -> 0 | AE10: =IFERROR(AD10/AC10,0) -> 0 | AF10: =COUNTIFS('咨询明细-数据源'!$J:$J,$A10,'咨询明细-数据源'!$K:$K,AF$2,'咨询明细-数据源'!$B:$B,AF$1) -> 0 | AG10: =COUNTIFS('咨询明细-数据源'!$J:$J,$A10,'咨询明细-数据源'!$L:$L,"成交",'咨询明细-数据源'!$B:$B,AF$1) -> 0 | AH10: =IFERROR(AG10/AF10,0) -> 0 | AI10: =COUNTIFS('咨询明细-数据源'!$J:$J,$A10,'咨询明细-数据源'!$K:$K,AI$2,'咨询明细-数据源'!$B:$B,AI$1) -> 1 | AJ10: =COUNTIFS('咨询明细-数据源'!$J:$J,$A10,'咨询明细-数据源'!$L:$L,"成交",'咨询明细-数据源'!$B:$B,AI$1) -> 0 | AK10: =IFERROR(AJ10/AI10,0) -> 0 | AL10: =COUNTIFS('咨询明细-数据源'!$J:$J,$A10,'咨询明细-数据源'!$K:$K,AL$2,'咨询明细-数据源'!$B:$B,AL$1) -> 2 | AM10: =COUNTIFS('咨询明细-数据源'!$J:$J,$A10,'咨询明细-数据源'!$L:$L,"成交",'咨询明细-数据源'!$B:$B,AL$1) -> 0 | AN10: =IFERROR(AM10/AL10,0) -> 0 | AO10: =COUNTIFS('咨询明细-数据源'!$J:$J,$A10,'咨询明细-数据源'!$K:$K,AO$2,'咨询明细-数据源'!$B:$B,AO$1) -> 5 | AP10: =COUNTIFS('咨询明细-数据源'!$J:$J,$A10,'咨询明细-数据源'!$L:$L,"成交",'咨询明细-数据源'!$B:$B,AO$1) -> 0 | AQ10: =IFERROR(AP10/AO10,0) -> 0
A11: 梁毅聪 | B11: =COUNTIFS('咨询明细-数据源'!$J:$J,$A11,'咨询明细-数据源'!$K:$K,B$2,'咨询明细-数据源'!$A:$A,B$1) -> 2 | C11: =COUNTIFS('咨询明细-数据源'!$J:$J,$A11,'咨询明细-数据源'!$L:$L,"成交",'咨询明细-数据源'!$A:$A,B$1) -> 0 | D11: =IFERROR(C11/B11,0) -> 0 | E11: =COUNTIFS('咨询明细-数据源'!$J:$J,$A11,'咨询明细-数据源'!$K:$K,E$2,'咨询明细-数据源'!$A:$A,E$1) -> 0 | F11: =COUNTIFS('咨询明细-数据源'!$J:$J,$A11,'咨询明细-数据源'!$L:$L,"成交",'咨询明细-数据源'!$A:$A,E$1) -> 0 | G11: =IFERROR(F11/E11,0) -> 0 | H11: =COUNTIFS('咨询明细-数据源'!$J:$J,$A11,'咨询明细-数据源'!$K:$K,H$2,'咨询明细-数据源'!$B:$B,H$1) -> 0 | I11: =COUNTIFS('咨询明细-数据源'!$J:$J,$A11,'咨询明细-数据源'!$L:$L,"成交",'咨询明细-数据源'!$B:$B,H$1) -> 0 | J11: =IFERROR(I11/H11,0) -> 0 | K11: =COUNTIFS('咨询明细-数据源'!$J:$J,$A11,'咨询明细-数据源'!$K:$K,K$2,'咨询明细-数据源'!$B:$B,K$1) -> 0 | L11: =COUNTIFS('咨询明细-数据源'!$J:$J,$A11,'咨询明细-数据源'!$L:$L,"成交",'咨询明细-数据源'!$B:$B,K$1) -> 0 | M11: =IFERROR(L11/K11,0) -> 0 | N11: =COUNTIFS('咨询明细-数据源'!$J:$J,$A11,'咨询明细-数据源'!$K:$K,N$2,'咨询明细-数据源'!$B:$B,N$1) -> 0 | O11: =COUNTIFS('咨询明细-数据源'!$J:$J,$A11,'咨询明细-数据源'!$L:$L,"成交",'咨询明细-数据源'!$B:$B,N$1) -> 0 | P11: =IFERROR(O11/N11,0) -> 0 | Q11: =COUNTIFS('咨询明细-数据源'!$J:$J,$A11,'咨询明细-数据源'!$K:$K,Q$2,'咨询明细-数据源'!$B:$B,Q$1) -> 0 | R11: =COUNTIFS('咨询明细-数据源'!$J:$J,$A11,'咨询明细-数据源'!$L:$L,"成交",'咨询明细-数据源'!$B:$B,Q$1) -> 0 | S11: =IFERROR(R11/Q11,0) -> 0 | T11: =COUNTIFS('咨询明细-数据源'!$J:$J,$A11,'咨询明细-数据源'!$K:$K,T$2,'咨询明细-数据源'!$B:$B,T$1) -> 0 | U11: =COUNTIFS('咨询明细-数据源'!$J:$J,$A11,'咨询明细-数据源'!$L:$L,"成交",'咨询明细-数据源'!$B:$B,T$1) -> 0 | V11: =IFERROR(U11/T11,0) -> 0 | W11: =COUNTIFS('咨询明细-数据源'!$J:$J,$A11,'咨询明细-数据源'!$K:$K,W$2,'咨询明细-数据源'!$B:$B,W$1) -> 2 | X11: =COUNTIFS('咨询明细-数据源'!$J:$J,$A11,'咨询明细-数据源'!$L:$L,"成交",'咨询明细-数据源'!$B:$B,W$1) -> 0 | Y11: =IFERROR(X11/W11,0) -> 0 | Z11: =COUNTIFS('咨询明细-数据源'!$J:$J,$A11,'咨询明细-数据源'!$K:$K,Z$2,'咨询明细-数据源'!$B:$B,Z$1) -> 0 | AA11: =COUNTIFS('咨询明细-数据源'!$J:$J,$A11,'咨询明细-数据源'!$L:$L,"成交",'咨询明细-数据源'!$B:$B,Z$1) -> 0 | AB11: =IFERROR(AA11/Z11,0) -> 0 | AC11: =COUNTIFS('咨询明细-数据源'!$J:$J,$A11,'咨询明细-数据源'!$K:$K,AC$2,'咨询明细-数据源'!$B:$B,AC$1) -> 0 | AD11: =COUNTIFS('咨询明细-数据源'!$J:$J,$A11,'咨询明细-数据源'!$L:$L,"成交",'咨询明细-数据源'!$B:$B,AC$1) -> 0 | AE11: =IFERROR(AD11/AC11,0) -> 0 | AF11: =COUNTIFS('咨询明细-数据源'!$J:$J,$A11,'咨询明细-数据源'!$K:$K,AF$2,'咨询明细-数据源'!$B:$B,AF$1) -> 0 | AG11: =COUNTIFS('咨询明细-数据源'!$J:$J,$A11,'咨询明细-数据源'!$L:$L,"成交",'咨询明细-数据源'!$B:$B,AF$1) -> 0 | AH11: =IFERROR(AG11/AF11,0) -> 0 | AI11: =COUNTIFS('咨询明细-数据源'!$J:$J,$A11,'咨询明细-数据源'!$K:$K,AI$2,'咨询明细-数据源'!$B:$B,AI$1) -> 0 | AJ11: =COUNTIFS('咨询明细-数据源'!$J:$J,$A11,'咨询明细-数据源'!$L:$L,"成交",'咨询明细-数据源'!$B:$B,AI$1) -> 0 | AK11: =IFERROR(AJ11/AI11,0) -> 0 | AL11: =COUNTIFS('咨询明细-数据源'!$J:$J,$A11,'咨询明细-数据源'!$K:$K,AL$2,'咨询明细-数据源'!$B:$B,AL$1) -> 0 | AM11: =COUNTIFS('咨询明细-数据源'!$J:$J,$A11,'咨询明细-数据源'!$L:$L,"成交",'咨询明细-数据源'!$B:$B,AL$1) -> 0 | AN11: =IFERROR(AM11/AL11,0) -> 0 | AO11: =COUNTIFS('咨询明细-数据源'!$J:$J,$A11,'咨询明细-数据源'!$K:$K,AO$2,'咨询明细-数据源'!$B:$B,AO$1) -> 0 | AP11: =COUNTIFS('咨询明细-数据源'!$J:$J,$A11,'咨询明细-数据源'!$L:$L,"成交",'咨询明细-数据源'!$B:$B,AO$1) -> 0 | AQ11: =IFERROR(AP11/AO11,0) -> 0
A12: 刘惠雯 | B12: =COUNTIFS('咨询明细-数据源'!$J:$J,$A12,'咨询明细-数据源'!$K:$K,B$2,'咨询明细-数据源'!$A:$A,B$1) -> 6 | C12: =COUNTIFS('咨询明细-数据源'!$J:$J,$A12,'咨询明细-数据源'!$L:$L,"成交",'咨询明细-数据源'!$A:$A,B$1) -> 0 | D12: =IFERROR(C12/B12,0) -> 0 | E12: =COUNTIFS('咨询明细-数据源'!$J:$J,$A12,'咨询明细-数据源'!$K:$K,E$2,'咨询明细-数据源'!$A:$A,E$1) -> 2 | F12: =COUNTIFS('咨询明细-数据源'!$J:$J,$A12,'咨询明细-数据源'!$L:$L,"成交",'咨询明细-数据源'!$A:$A,E$1) -> 0 | G12: =IFERROR(F12/E12,0) -> 0 | H12: =COUNTIFS('咨询明细-数据源'!$J:$J,$A12,'咨询明细-数据源'!$K:$K,H$2,'咨询明细-数据源'!$B:$B,H$1) -> 0 | I12: =COUNTIFS('咨询明细-数据源'!$J:$J,$A12,'咨询明细-数据源'!$L:$L,"成交",'咨询明细-数据源'!$B:$B,H$1) -> 0 | J12: =IFERROR(I12/H12,0) -> 0 | K12: =COUNTIFS('咨询明细-数据源'!$J:$J,$A12,'咨询明细-数据源'!$K:$K,K$2,'咨询明细-数据源'!$B:$B,K$1) -> 0 | L12: =COUNTIFS('咨询明细-数据源'!$J:$J,$A12,'咨询明细-数据源'!$L:$L,"成交",'咨询明细-数据源'!$B:$B,K$1) -> 0 | M12: =IFERROR(L12/K12,0) -> 0 | N12: =COUNTIFS('咨询明细-数据源'!$J:$J,$A12,'咨询明细-数据源'!$K:$K,N$2,'咨询明细-数据源'!$B:$B,N$1) -> 0 | O12: =COUNTIFS('咨询明细-数据源'!$J:$J,$A12,'咨询明细-数据源'!$L:$L,"成交",'咨询明细-数据源'!$B:$B,N$1) -> 0 | P12: =IFERROR(O12/N12,0) -> 0 | Q12: =COUNTIFS('咨询明细-数据源'!$J:$J,$A12,'咨询明细-数据源'!$K:$K,Q$2,'咨询明细-数据源'!$B:$B,Q$1) -> 0 | R12: =COUNTIFS('咨询明细-数据源'!$J:$J,$A12,'咨询明细-数据源'!$L:$L,"成交",'咨询明细-数据源'!$B:$B,Q$1) -> 0 | S12: =IFERROR(R12/Q12,0) -> 0 | T12: =COUNTIFS('咨询明细-数据源'!$J:$J,$A12,'咨询明细-数据源'!$K:$K,T$2,'咨询明细-数据源'!$B:$B,T$1) -> 0 | U12: =COUNTIFS('咨询明细-数据源'!$J:$J,$A12,'咨询明细-数据源'!$L:$L,"成交",'咨询明细-数据源'!$B:$B,T$1) -> 0 | V12: =IFERROR(U12/T12,0) -> 0 | W12: =COUNTIFS('咨询明细-数据源'!$J:$J,$A12,'咨询明细-数据源'!$K:$K,W$2,'咨询明细-数据源'!$B:$B,W$1) -> 0 | X12: =COUNTIFS('咨询明细-数据源'!$J:$J,$A12,'咨询明细-数据源'!$L:$L,"成交",'咨询明细-数据源'!$B:$B,W$1) -> 0 | Y12: =IFERROR(X12/W12,0) -> 0 | Z12: =COUNTIFS('咨询明细-数据源'!$J:$J,$A12,'咨询明细-数据源'!$K:$K,Z$2,'咨询明细-数据源'!$B:$B,Z$1) -> 0 | AA12: =COUNTIFS('咨询明细-数据源'!$J:$J,$A12,'咨询明细-数据源'!$L:$L,"成交",'咨询明细-数据源'!$B:$B,Z$1) -> 0 | AB12: =IFERROR(AA12/Z12,0) -> 0 | AC12: =COUNTIFS('咨询明细-数据源'!$J:$J,$A12,'咨询明细-数据源'!$K:$K,AC$2,'咨询明细-数据源'!$B:$B,AC$1) -> 1 | AD12: =COUNTIFS('咨询明细-数据源'!$J:$J,$A12,'咨询明细-数据源'!$L:$L,"成交",'咨询明细-数据源'!$B:$B,AC$1) -> 0 | AE12: =IFERROR(AD12/AC12,0) -> 0 | AF12: =COUNTIFS('咨询明细-数据源'!$J:$J,$A12,'咨询明细-数据源'!$K:$K,AF$2,'咨询明细-数据源'!$B:$B,AF$1) -> 1 | AG12: =COUNTIFS('咨询明细-数据源'!$J:$J,$A12,'咨询明细-数据源'!$L:$L,"成交",'咨询明细-数据源'!$B:$B,AF$1) -> 0 | AH12: =IFERROR(AG12/AF12,0) -> 0 | AI12: =COUNTIFS('咨询明细-数据源'!$J:$J,$A12,'咨询明细-数据源'!$K:$K,AI$2,'咨询明细-数据源'!$B:$B,AI$1) -> 2 | AJ12: =COUNTIFS('咨询明细-数据源'!$J:$J,$A12,'咨询明细-数据源'!$L:$L,"成交",'咨询明细-数据源'!$B:$B,AI$1) -> 0 | AK12: =IFERROR(AJ12/AI12,0) -> 0 | AL12: =COUNTIFS('咨询明细-数据源'!$J:$J,$A12,'咨询明细-数据源'!$K:$K,AL$2,'咨询明细-数据源'!$B:$B,AL$1) -> 2 | AM12: =COUNTIFS('咨询明细-数据源'!$J:$J,$A12,'咨询明细-数据源'!$L:$L,"成交",'咨询明细-数据源'!$B:$B,AL$1) -> 0 | AN12: =IFERROR(AM12/AL12,0) -> 0 | AO12: =COUNTIFS('咨询明细-数据源'!$J:$J,$A12,'咨询明细-数据源'!$K:$K,AO$2,'咨询明细-数据源'!$B:$B,AO$1) -> 0 | AP12: =COUNTIFS('咨询明细-数据源'!$J:$J,$A12,'咨询明细-数据源'!$L:$L,"成交",'咨询明细-数据源'!$B:$B,AO$1) -> 0 | AQ12: =IFERROR(AP12/AO12,0) -> 0
A13: 陈冠中 | B13: =COUNTIFS('咨询明细-数据源'!$J:$J,$A13,'咨询明细-数据源'!$K:$K,B$2,'咨询明细-数据源'!$A:$A,B$1) -> 2 | C13: =COUNTIFS('咨询明细-数据源'!$J:$J,$A13,'咨询明细-数据源'!$L:$L,"成交",'咨询明细-数据源'!$A:$A,B$1) -> 0 | D13: =IFERROR(C13/B13,0) -> 0 | E13: =COUNTIFS('咨询明细-数据源'!$J:$J,$A13,'咨询明细-数据源'!$K:$K,E$2,'咨询明细-数据源'!$A:$A,E$1) -> 0 | F13: =COUNTIFS('咨询明细-数据源'!$J:$J,$A13,'咨询明细-数据源'!$L:$L,"成交",'咨询明细-数据源'!$A:$A,E$1) -> 0 | G13: =IFERROR(F13/E13,0) -> 0 | H13: =COUNTIFS('咨询明细-数据源'!$J:$J,$A13,'咨询明细-数据源'!$K:$K,H$2,'咨询明细-数据源'!$B:$B,H$1) -> 0 | I13: =COUNTIFS('咨询明细-数据源'!$J:$J,$A13,'咨询明细-数据源'!$L:$L,"成交",'咨询明细-数据源'!$B:$B,H$1) -> 0 | J13: =IFERROR(I13/H13,0) -> 0 | K13: =COUNTIFS('咨询明细-数据源'!$J:$J,$A13,'咨询明细-数据源'!$K:$K,K$2,'咨询明细-数据源'!$B:$B,K$1) -> 0 | L13: =COUNTIFS('咨询明细-数据源'!$J:$J,$A13,'咨询明细-数据源'!$L:$L,"成交",'咨询明细-数据源'!$B:$B,K$1) -> 0 | M13: =IFERROR(L13/K13,0) -> 0 | N13: =COUNTIFS('咨询明细-数据源'!$J:$J,$A13,'咨询明细-数据源'!$K:$K,N$2,'咨询明细-数据源'!$B:$B,N$1) -> 0 | O13: =COUNTIFS('咨询明细-数据源'!$J:$J,$A13,'咨询明细-数据源'!$L:$L,"成交",'咨询明细-数据源'!$B:$B,N$1) -> 0 | P13: =IFERROR(O13/N13,0) -> 0 | Q13: =COUNTIFS('咨询明细-数据源'!$J:$J,$A13,'咨询明细-数据源'!$K:$K,Q$2,'咨询明细-数据源'!$B:$B,Q$1) -> 0 | R13: =COUNTIFS('咨询明细-数据源'!$J:$J,$A13,'咨询明细-数据源'!$L:$L,"成交",'咨询明细-数据源'!$B:$B,Q$1) -> 0 | S13: =IFERROR(R13/Q13,0) -> 0 | T13: =COUNTIFS('咨询明细-数据源'!$J:$J,$A13,'咨询明细-数据源'!$K:$K,T$2,'咨询明细-数据源'!$B:$B,T$1) -> 0 | U13: =COUNTIFS('咨询明细-数据源'!$J:$J,$A13,'咨询明细-数据源'!$L:$L,"成交",'咨询明细-数据源'!$B:$B,T$1) -> 0 | V13: =IFERROR(U13/T13,0) -> 0 | W13: =COUNTIFS('咨询明细-数据源'!$J:$J,$A13,'咨询明细-数据源'!$K:$K,W$2,'咨询明细-数据源'!$B:$B,W$1) -> 0 | X13: =COUNTIFS('咨询明细-数据源'!$J:$J,$A13,'咨询明细-数据源'!$L:$L,"成交",'咨询明细-数据源'!$B:$B,W$1) -> 0 | Y13: =IFERROR(X13/W13,0) -> 0 | Z13: =COUNTIFS('咨询明细-数据源'!$J:$J,$A13,'咨询明细-数据源'!$K:$K,Z$2,'咨询明细-数据源'!$B:$B,Z$1) -> 0 | AA13: =COUNTIFS('咨询明细-数据源'!$J:$J,$A13,'咨询明细-数据源'!$L:$L,"成交",'咨询明细-数据源'!$B:$B,Z$1) -> 0 | AB13: =IFERROR(AA13/Z13,0) -> 0 | AC13: =COUNTIFS('咨询明细-数据源'!$J:$J,$A13,'咨询明细-数据源'!$K:$K,AC$2,'咨询明细-数据源'!$B:$B,AC$1) -> 0 | AD13: =COUNTIFS('咨询明细-数据源'!$J:$J,$A13,'咨询明细-数据源'!$L:$L,"成交",'咨询明细-数据源'!$B:$B,AC$1) -> 0 | AE13: =IFERROR(AD13/AC13,0) -> 0 | AF13: =COUNTIFS('咨询明细-数据源'!$J:$J,$A13,'咨询明细-数据源'!$K:$K,AF$2,'咨询明细-数据源'!$B:$B,AF$1) -> 0 | AG13: =COUNTIFS('咨询明细-数据源'!$J:$J,$A13,'咨询明细-数据源'!$L:$L,"成交",'咨询明细-数据源'!$B:$B,AF$1) -> 0 | AH13: =IFERROR(AG13/AF13,0) -> 0 | AI13: =COUNTIFS('咨询明细-数据源'!$J:$J,$A13,'咨询明细-数据源'!$K:$K,AI$2,'咨询明细-数据源'!$B:$B,AI$1) -> 1 | AJ13: =COUNTIFS('咨询明细-数据源'!$J:$J,$A13,'咨询明细-数据源'!$L:$L,"成交",'咨询明细-数据源'!$B:$B,AI$1) -> 0 | AK13: =IFERROR(AJ13/AI13,0) -> 0 | AL13: =COUNTIFS('咨询明细-数据源'!$J:$J,$A13,'咨询明细-数据源'!$K:$K,AL$2,'咨询明细-数据源'!$B:$B,AL$1) -> 0 | AM13: =COUNTIFS('咨询明细-数据源'!$J:$J,$A13,'咨询明细-数据源'!$L:$L,"成交",'咨询明细-数据源'!$B:$B,AL$1) -> 0 | AN13: =IFERROR(AM13/AL13,0) -> 0 | AO13: =COUNTIFS('咨询明细-数据源'!$J:$J,$A13,'咨询明细-数据源'!$K:$K,AO$2,'咨询明细-数据源'!$B:$B,AO$1) -> 1 | AP13: =COUNTIFS('咨询明细-数据源'!$J:$J,$A13,'咨询明细-数据源'!$L:$L,"成交",'咨询明细-数据源'!$B:$B,AO$1) -> 0 | AQ13: =IFERROR(AP13/AO13,0) -> 0
A14: 冯俊燊 | B14: =COUNTIFS('咨询明细-数据源'!$J:$J,$A14,'咨询明细-数据源'!$K:$K,B$2,'咨询明细-数据源'!$A:$A,B$1) -> 11 | C14: =COUNTIFS('咨询明细-数据源'!$J:$J,$A14,'咨询明细-数据源'!$L:$L,"成交",'咨询明细-数据源'!$A:$A,B$1) -> 0 | D14: =IFERROR(C14/B14,0) -> 0 | E14: =COUNTIFS('咨询明细-数据源'!$J:$J,$A14,'咨询明细-数据源'!$K:$K,E$2,'咨询明细-数据源'!$A:$A,E$1) -> 0 | F14: =COUNTIFS('咨询明细-数据源'!$J:$J,$A14,'咨询明细-数据源'!$L:$L,"成交",'咨询明细-数据源'!$A:$A,E$1) -> 0 | G14: =IFERROR(F14/E14,0) -> 0 | H14: =COUNTIFS('咨询明细-数据源'!$J:$J,$A14,'咨询明细-数据源'!$K:$K,H$2,'咨询明细-数据源'!$B:$B,H$1) -> 0 | I14: =COUNTIFS('咨询明细-数据源'!$J:$J,$A14,'咨询明细-数据源'!$L:$L,"成交",'咨询明细-数据源'!$B:$B,H$1) -> 0 | J14: =IFERROR(I14/H14,0) -> 0 | K14: =COUNTIFS('咨询明细-数据源'!$J:$J,$A14,'咨询明细-数据源'!$K:$K,K$2,'咨询明细-数据源'!$B:$B,K$1) -> 0 | L14: =COUNTIFS('咨询明细-数据源'!$J:$J,$A14,'咨询明细-数据源'!$L:$L,"成交",'咨询明细-数据源'!$B:$B,K$1) -> 0 | M14: =IFERROR(L14/K14,0) -> 0 | N14: =COUNTIFS('咨询明细-数据源'!$J:$J,$A14,'咨询明细-数据源'!$K:$K,N$2,'咨询明细-数据源'!$B:$B,N$1) -> 4 | O14: =COUNTIFS('咨询明细-数据源'!$J:$J,$A14,'咨询明细-数据源'!$L:$L,"成交",'咨询明细-数据源'!$B:$B,N$1) -> 0 | P14: =IFERROR(O14/N14,0) -> 0 | Q14: =COUNTIFS('咨询明细-数据源'!$J:$J,$A14,'咨询明细-数据源'!$K:$K,Q$2,'咨询明细-数据源'!$B:$B,Q$1) -> 1 | R14: =COUNTIFS('咨询明细-数据源'!$J:$J,$A14,'咨询明细-数据源'!$L:$L,"成交",'咨询明细-数据源'!$B:$B,Q$1) -> 0 | S14: =IFERROR(R14/Q14,0) -> 0 | T14: =COUNTIFS('咨询明细-数据源'!$J:$J,$A14,'咨询明细-数据源'!$K:$K,T$2,'咨询明细-数据源'!$B:$B,T$1) -> 0 | U14: =COUNTIFS('咨询明细-数据源'!$J:$J,$A14,'咨询明细-数据源'!$L:$L,"成交",'咨询明细-数据源'!$B:$B,T$1) -> 0 | V14: =IFERROR(U14/T14,0) -> 0 | W14: =COUNTIFS('咨询明细-数据源'!$J:$J,$A14,'咨询明细-数据源'!$K:$K,W$2,'咨询明细-数据源'!$B:$B,W$1) -> 0 | X14: =COUNTIFS('咨询明细-数据源'!$J:$J,$A14,'咨询明细-数据源'!$L:$L,"成交",'咨询明细-数据源'!$B:$B,W$1) -> 0 | Y14: =IFERROR(X14/W14,0) -> 0 | Z14: =COUNTIFS('咨询明细-数据源'!$J:$J,$A14,'咨询明细-数据源'!$K:$K,Z$2,'咨询明细-数据源'!$B:$B,Z$1) -> 0 | AA14: =COUNTIFS('咨询明细-数据源'!$J:$J,$A14,'咨询明细-数据源'!$L:$L,"成交",'咨询明细-数据源'!$B:$B,Z$1) -> 0 | AB14: =IFERROR(AA14/Z14,0) -> 0 | AC14: =COUNTIFS('咨询明细-数据源'!$J:$J,$A14,'咨询明细-数据源'!$K:$K,AC$2,'咨询明细-数据源'!$B:$B,AC$1) -> 1 | AD14: =COUNTIFS('咨询明细-数据源'!$J:$J,$A14,'咨询明细-数据源'!$L:$L,"成交",'咨询明细-数据源'!$B:$B,AC$1) -> 0 | AE14: =IFERROR(AD14/AC14,0) -> 0 | AF14: =COUNTIFS('咨询明细-数据源'!$J:$J,$A14,'咨询明细-数据源'!$K:$K,AF$2,'咨询明细-数据源'!$B:$B,AF$1) -> 2 | AG14: =COUNTIFS('咨询明细-数据源'!$J:$J,$A14,'咨询明细-数据源'!$L:$L,"成交",'咨询明细-数据源'!$B:$B,AF$1) -> 0 | AH14: =IFERROR(AG14/AF14,0) -> 0 | AI14: =COUNTIFS('咨询明细-数据源'!$J:$J,$A14,'咨询明细-数据源'!$K:$K,AI$2,'咨询明细-数据源'!$B:$B,AI$1) -> 2 | AJ14: =COUNTIFS('咨询明细-数据源'!$J:$J,$A14,'咨询明细-数据源'!$L:$L,"成交",'咨询明细-数据源'!$B:$B,AI$1) -> 0 | AK14: =IFERROR(AJ14/AI14,0) -> 0 | AL14: =COUNTIFS('咨询明细-数据源'!$J:$J,$A14,'咨询明细-数据源'!$K:$K,AL$2,'咨询明细-数据源'!$B:$B,AL$1) -> 1 | AM14: =COUNTIFS('咨询明细-数据源'!$J:$J,$A14,'咨询明细-数据源'!$L:$L,"成交",'咨询明细-数据源'!$B:$B,AL$1) -> 0 | AN14: =IFERROR(AM14/AL14,0) -> 0 | AO14: =COUNTIFS('咨询明细-数据源'!$J:$J,$A14,'咨询明细-数据源'!$K:$K,AO$2,'咨询明细-数据源'!$B:$B,AO$1) -> 0 | AP14: =COUNTIFS('咨询明细-数据源'!$J:$J,$A14,'咨询明细-数据源'!$L:$L,"成交",'咨询明细-数据源'!$B:$B,AO$1) -> 0 | AQ14: =IFERROR(AP14/AO14,0) -> 0
A15: 周远锋 | B15: =COUNTIFS('咨询明细-数据源'!$J:$J,$A15,'咨询明细-数据源'!$K:$K,B$2,'咨询明细-数据源'!$A:$A,B$1) -> 0 | C15: =COUNTIFS('咨询明细-数据源'!$J:$J,$A15,'咨询明细-数据源'!$L:$L,"成交",'咨询明细-数据源'!$A:$A,B$1) -> 0 | D15: =IFERROR(C15/B15,0) -> 0 | E15: =COUNTIFS('咨询明细-数据源'!$J:$J,$A15,'咨询明细-数据源'!$K:$K,E$2,'咨询明细-数据源'!$A:$A,E$1) -> 0 | F15: =COUNTIFS('咨询明细-数据源'!$J:$J,$A15,'咨询明细-数据源'!$L:$L,"成交",'咨询明细-数据源'!$A:$A,E$1) -> 0 | G15: =IFERROR(F15/E15,0) -> 0 | H15: =COUNTIFS('咨询明细-数据源'!$J:$J,$A15,'咨询明细-数据源'!$K:$K,H$2,'咨询明细-数据源'!$B:$B,H$1) -> 0 | I15: =COUNTIFS('咨询明细-数据源'!$J:$J,$A15,'咨询明细-数据源'!$L:$L,"成交",'咨询明细-数据源'!$B:$B,H$1) -> 0 | J15: =IFERROR(I15/H15,0) -> 0 | K15: =COUNTIFS('咨询明细-数据源'!$J:$J,$A15,'咨询明细-数据源'!$K:$K,K$2,'咨询明细-数据源'!$B:$B,K$1) -> 0 | L15: =COUNTIFS('咨询明细-数据源'!$J:$J,$A15,'咨询明细-数据源'!$L:$L,"成交",'咨询明细-数据源'!$B:$B,K$1) -> 0 | M15: =IFERROR(L15/K15,0) -> 0 | N15: =COUNTIFS('咨询明细-数据源'!$J:$J,$A15,'咨询明细-数据源'!$K:$K,N$2,'咨询明细-数据源'!$B:$B,N$1) -> 0 | O15: =COUNTIFS('咨询明细-数据源'!$J:$J,$A15,'咨询明细-数据源'!$L:$L,"成交",'咨询明细-数据源'!$B:$B,N$1) -> 0 | P15: =IFERROR(O15/N15,0) -> 0 | Q15: =COUNTIFS('咨询明细-数据源'!$J:$J,$A15,'咨询明细-数据源'!$K:$K,Q$2,'咨询明细-数据源'!$B:$B,Q$1) -> 0 | R15: =COUNTIFS('咨询明细-数据源'!$J:$J,$A15,'咨询明细-数据源'!$L:$L,"成交",'咨询明细-数据源'!$B:$B,Q$1) -> 0 | S15: =IFERROR(R15/Q15,0) -> 0 | T15: =COUNTIFS('咨询明细-数据源'!$J:$J,$A15,'咨询明细-数据源'!$K:$K,T$2,'咨询明细-数据源'!$B:$B,T$1) -> 0 | U15: =COUNTIFS('咨询明细-数据源'!$J:$J,$A15,'咨询明细-数据源'!$L:$L,"成交",'咨询明细-数据源'!$B:$B,T$1) -> 0 | V15: =IFERROR(U15/T15,0) -> 0 | W15: =COUNTIFS('咨询明细-数据源'!$J:$J,$A15,'咨询明细-数据源'!$K:$K,W$2,'咨询明细-数据源'!$B:$B,W$1) -> 0 | X15: =COUNTIFS('咨询明细-数据源'!$J:$J,$A15,'咨询明细-数据源'!$L:$L,"成交",'咨询明细-数据源'!$B:$B,W$1) -> 0 | Y15: =IFERROR(X15/W15,0) -> 0 | Z15: =COUNTIFS('咨询明细-数据源'!$J:$J,$A15,'咨询明细-数据源'!$K:$K,Z$2,'咨询明细-数据源'!$B:$B,Z$1) -> 0 | AA15: =COUNTIFS('咨询明细-数据源'!$J:$J,$A15,'咨询明细-数据源'!$L:$L,"成交",'咨询明细-数据源'!$B:$B,Z$1) -> 0 | AB15: =IFERROR(AA15/Z15,0) -> 0 | AC15: =COUNTIFS('咨询明细-数据源'!$J:$J,$A15,'咨询明细-数据源'!$K:$K,AC$2,'咨询明细-数据源'!$B:$B,AC$1) -> 0 | AD15: =COUNTIFS('咨询明细-数据源'!$J:$J,$A15,'咨询明细-数据源'!$L:$L,"成交",'咨询明细-数据源'!$B:$B,AC$1) -> 0 | AE15: =IFERROR(AD15/AC15,0) -> 0 | AF15: =COUNTIFS('咨询明细-数据源'!$J:$J,$A15,'咨询明细-数据源'!$K:$K,AF$2,'咨询明细-数据源'!$B:$B,AF$1) -> 0 | AG15: =COUNTIFS('咨询明细-数据源'!$J:$J,$A15,'咨询明细-数据源'!$L:$L,"成交",'咨询明细-数据源'!$B:$B,AF$1) -> 0 | AH15: =IFERROR(AG15/AF15,0) -> 0 | AI15: =COUNTIFS('咨询明细-数据源'!$J:$J,$A15,'咨询明细-数据源'!$K:$K,AI$2,'咨询明细-数据源'!$B:$B,AI$1) -> 0 | AJ15: =COUNTIFS('咨询明细-数据源'!$J:$J,$A15,'咨询明细-数据源'!$L:$L,"成交",'咨询明细-数据源'!$B:$B,AI$1) -> 0 | AK15: =IFERROR(AJ15/AI15,0) -> 0 | AL15: =COUNTIFS('咨询明细-数据源'!$J:$J,$A15,'咨询明细-数据源'!$K:$K,AL$2,'咨询明细-数据源'!$B:$B,AL$1) -> 0 | AM15: =COUNTIFS('咨询明细-数据源'!$J:$J,$A15,'咨询明细-数据源'!$L:$L,"成交",'咨询明细-数据源'!$B:$B,AL$1) -> 0 | AN15: =IFERROR(AM15/AL15,0) -> 0 | AO15: =COUNTIFS('咨询明细-数据源'!$J:$J,$A15,'咨询明细-数据源'!$K:$K,AO$2,'咨询明细-数据源'!$B:$B,AO$1) -> 0 | AP15: =COUNTIFS('咨询明细-数据源'!$J:$J,$A15,'咨询明细-数据源'!$L:$L,"成交",'咨询明细-数据源'!$B:$B,AO$1) -> 0 | AQ15: =IFERROR(AP15/AO15,0) -> 0
... A38: 梁惠怡 | B38: =COUNTIFS('咨询明细-数据源'!$J:$J,$A38,'咨询明细-数据源'!$K:$K,B$2,'咨询明细-数据源'!$A:$A,B$1) -> 4 | C38: =COUNTIFS('咨询明细-数据源'!$J:$J,$A38,'咨询明细-数据源'!$L:$L,"成交",'咨询明细-数据源'!$A:$A,B$1) -> 0 | D38: =IFERROR(C38/B38,0) -> 0 | E38: =COUNTIFS('咨询明细-数据源'!$J:$J,$A38,'咨询明细-数据源'!$K:$K,E$2,'咨询明细-数据源'!$A:$A,E$1) -> 2 | F38: =COUNTIFS('咨询明细-数据源'!$J:$J,$A38,'咨询明细-数据源'!$L:$L,"成交",'咨询明细-数据源'!$A:$A,E$1) -> 0 | G38: =IFERROR(F38/E38,0) -> 0 | H38: =COUNTIFS('咨询明细-数据源'!$J:$J,$A38,'咨询明细-数据源'!$K:$K,H$2,'咨询明细-数据源'!$B:$B,H$1) -> 0 | I38: =COUNTIFS('咨询明细-数据源'!$J:$J,$A38,'咨询明细-数据源'!$L:$L,"成交",'咨询明细-数据源'!$B:$B,H$1) -> 0 | J38: =IFERROR(I38/H38,0) -> 0 | K38: =COUNTIFS('咨询明细-数据源'!$J:$J,$A38,'咨询明细-数据源'!$K:$K,K$2,'咨询明细-数据源'!$B:$B,K$1) -> 0 | L38: =COUNTIFS('咨询明细-数据源'!$J:$J,$A38,'咨询明细-数据源'!$L:$L,"成交",'咨询明细-数据源'!$B:$B,K$1) -> 0 | M38: =IFERROR(L38/K38,0) -> 0 | N38: =COUNTIFS('咨询明细-数据源'!$J:$J,$A38,'咨询明细-数据源'!$K:$K,N$2,'咨询明细-数据源'!$B:$B,N$1) -> 0 | O38: =COUNTIFS('咨询明细-数据源'!$J:$J,$A38,'咨询明细-数据源'!$L:$L,"成交",'咨询明细-数据源'!$B:$B,N$1) -> 0 | P38: =IFERROR(O38/N38,0) -> 0 | Q38: =COUNTIFS('咨询明细-数据源'!$J:$J,$A38,'咨询明细-数据源'!$K:$K,Q$2,'咨询明细-数据源'!$B:$B,Q$1) -> 0 | R38: =COUNTIFS('咨询明细-数据源'!$J:$J,$A38,'咨询明细-数据源'!$L:$L,"成交",'咨询明细-数据源'!$B:$B,Q$1) -> 0 | S38: =IFERROR(R38/Q38,0) -> 0 | T38: =COUNTIFS('咨询明细-数据源'!$J:$J,$A38,'咨询明细-数据源'!$K:$K,T$2,'咨询明细-数据源'!$B:$B,T$1) -> 0 | U38: =COUNTIFS('咨询明细-数据源'!$J:$J,$A38,'咨询明细-数据源'!$L:$L,"成交",'咨询明细-数据源'!$B:$B,T$1) -> 0 | V38: =IFERROR(U38/T38,0) -> 0 | W38: =COUNTIFS('咨询明细-数据源'!$J:$J,$A38,'咨询明细-数据源'!$K:$K,W$2,'咨询明细-数据源'!$B:$B,W$1) -> 0 | X38: =COUNTIFS('咨询明细-数据源'!$J:$J,$A38,'咨询明细-数据源'!$L:$L,"成交",'咨询明细-数据源'!$B:$B,W$1) -> 0 | Y38: =IFERROR(X38/W38,0) -> 0 | Z38: =COUNTIFS('咨询明细-数据源'!$J:$J,$A38,'咨询明细-数据源'!$K:$K,Z$2,'咨询明细-数据源'!$B:$B,Z$1) -> 0 | AA38: =COUNTIFS('咨询明细-数据源'!$J:$J,$A38,'咨询明细-数据源'!$L:$L,"成交",'咨询明细-数据源'!$B:$B,Z$1) -> 0 | AB38: =IFERROR(AA38/Z38,0) -> 0 | AC38: =COUNTIFS('咨询明细-数据源'!$J:$J,$A38,'咨询明细-数据源'!$K:$K,AC$2,'咨询明细-数据源'!$B:$B,AC$1) -> 0 | AD38: =COUNTIFS('咨询明细-数据源'!$J:$J,$A38,'咨询明细-数据源'!$L:$L,"成交",'咨询明细-数据源'!$B:$B,AC$1) -> 0 | AE38: =IFERROR(AD38/AC38,0) -> 0 | AF38: =COUNTIFS('咨询明细-数据源'!$J:$J,$A38,'咨询明细-数据源'!$K:$K,AF$2,'咨询明细-数据源'!$B:$B,AF$1) -> 0 | AG38: =COUNTIFS('咨询明细-数据源'!$J:$J,$A38,'咨询明细-数据源'!$L:$L,"成交",'咨询明细-数据源'!$B:$B,AF$1) -> 0 | AH38: =IFERROR(AG38/AF38,0) -> 0 | AI38: =COUNTIFS('咨询明细-数据源'!$J:$J,$A38,'咨询明细-数据源'!$K:$K,AI$2,'咨询明细-数据源'!$B:$B,AI$1) -> 0 | AJ38: =COUNTIFS('咨询明细-数据源'!$J:$J,$A38,'咨询明细-数据源'!$L:$L,"成交",'咨询明细-数据源'!$B:$B,AI$1) -> 0 | AK38: =IFERROR(AJ38/AI38,0) -> 0 | AL38: =COUNTIFS('咨询明细-数据源'!$J:$J,$A38,'咨询明细-数据源'!$K:$K,AL$2,'咨询明细-数据源'!$B:$B,AL$1) -> 2 | AM38: =COUNTIFS('咨询明细-数据源'!$J:$J,$A38,'咨询明细-数据源'!$L:$L,"成交",'咨询明细-数据源'!$B:$B,AL$1) -> 0 | AN38: =IFERROR(AM38/AL38,0) -> 0 | AO38: =COUNTIFS('咨询明细-数据源'!$J:$J,$A38,'咨询明细-数据源'!$K:$K,AO$2,'咨询明细-数据源'!$B:$B,AO$1) -> 2 | AP38: =COUNTIFS('咨询明细-数据源'!$J:$J,$A38,'咨询明细-数据源'!$L:$L,"成交",'咨询明细-数据源'!$B:$B,AO$1) -> 0 | AQ38: =IFERROR(AP38/AO38,0) -> 0
A39: 杨木瑞 | B39: =COUNTIFS('咨询明细-数据源'!$J:$J,$A39,'咨询明细-数据源'!$K:$K,B$2,'咨询明细-数据源'!$A:$A,B$1) -> 0 | C39: =COUNTIFS('咨询明细-数据源'!$J:$J,$A39,'咨询明细-数据源'!$L:$L,"成交",'咨询明细-数据源'!$A:$A,B$1) -> 0 | D39: =IFERROR(C39/B39,0) -> 0 | E39: =COUNTIFS('咨询明细-数据源'!$J:$J,$A39,'咨询明细-数据源'!$K:$K,E$2,'咨询明细-数据源'!$A:$A,E$1) -> 9 | F39: =COUNTIFS('咨询明细-数据源'!$J:$J,$A39,'咨询明细-数据源'!$L:$L,"成交",'咨询明细-数据源'!$A:$A,E$1) -> 0 | G39: =IFERROR(F39/E39,0) -> 0
